Workbook
Name BUSCAR: RECIBO!$J$4:$K$4

Sheet RECIBO
C2: Teléfono: 844 413 0504
C4: Whatsapp: 844 443 9987
J5: {=IFERROR(VLOOKUP($J$4,{DATABASE!B2:B27,DATABASE!A2:A27},2,FALSE),"-")} -> -
B7: FECHA | C7: =TODAY() -> 46084
C8: DD/MM/AAAA
B10: No. INDENTIFICACIÓN
B11: NOMBRE COMPLETO | D11: =IFERROR(VLOOKUP($D$10,DATABASE!A2:L27,2,FALSE),"-") -> -
B12: TELEFONO O CELULAR | D12: =IFERROR(VLOOKUP($D$10,DATABASE!A2:L27,5,FALSE),"-") -> -
B13: TERAPEUTA
B14: DETALLES DE PAGO
B15: UBICACIÓN | D15: FACTURA | F15: FORMA DE PAGO
B16: DESCRIPCIÓN DEL SERVICIO | E16: CANTIDAD | F16: VALOR UNITARIO | G16: IMPORTE
F17: =IFERROR(VLOOKUP(B17,catalogo!$B$1:$D$35,2,FALSE),"") | G17: =E17*F17 -> 0
F18: =IFERROR(VLOOKUP(B18,catalogo!$B$1:$D$35,2,FALSE),"") | G18: =E18*F18 -> 0
F19: =IFERROR(VLOOKUP(B19,catalogo!$B$1:$D$35,2,FALSE),"") | G19: =E19*F19 -> 0
F20: =IFERROR(VLOOKUP(B20,catalogo!$B$1:$D$35,2,FALSE),"") | G20: =E20*F20 -> 0
F21: =IFERROR(VLOOKUP(B21,catalogo!$B$1:$D$35,2,FALSE),"") | G21: =E21*F21 -> 0
E22: DESCUENTO
E23: SUBTOTAL | G23: =SUM(G17:G21)-G22 -> 0
E24: COMISIÓN POR PAGO CON TARJETA | G24: =IF(G15="TARJETA", G23 * 0.03, "N/A") -> N/A
E25: IVA | G25: =IF(E15="SI",G23*0.16,"N/A") -> N/A
E26: TOTAL | G26: =SUM(G23:G25) -> 0

Sheet DATABASE
B1: NOMBRE | C1: FECHA DE INICIO | D1: LUGAR | E1: CELULAR | F1: PARENTESCOS | G1: TERAPEUTA | H1: TIPO DE TERAPIA | I1: DIVISIÓN | J1: COSTO | K1: PAGO TERAPEUTA | L1: CULMINACION DE SESIONES
A2: 100 | B2: jesus ignacio galindo | C2: 45054 | E2: dennise giasa | G2: Yulior Ramírez | H2: Individual | I2: N/A | L2: BAJA
A3: 101 | B3: Mely Davila ibarra | C3: 45067 | E3: Dennise giasa | G3: Ale Almanza | H3: Pareja | I3: N/A | L3: No hay contacto
A4: 102 | B4: Wendolyne Carrasco | C4: 45079 | E4: 8443679448 | G4: Karina Montoya | H4: Individual | I4: N/A | L4: No hay contacto
A5: 103 | B5: Nallely Pedrosa | C5: 45081 | E5: 8442908503 | G5: Víctor Gaytán | H5: Individual | I5: N/A | K5: 200 | L5: No hay contacto
A6: 104 | B6: Juany Arellano | C6: 45082 | G6: Arcadio | H6: Individual | I6: N/A | L6: BAJA
A7: 105 | B7: Madeline Rangel | C7: 45082 | E7: 8442782384 | G7: Arcadio | H7: Individual | I7: N/A | L7: BAJA
A8: 106 | B8: Lesly Sarahi Espinosa Rios | C8: 45083 | E8: 8443882328 | G8: Arcadio | H8: Individual | I8: N/A | L8: BAJA
A9: 107 | B9: Roxana Martínez | C9: 45083 | E9: 8445405379 | G9: Ale Almanza | H9: Pareja | I9: N/A | K9: 250 | L9: No hay contacto
A10: 108 | B10: Valeria Monserrat González López | C10: 45083 | D10: Guanajuato | E10: 8447643481 | G10: Lic. Javier Martinez | H10: Individual | I10: INTRA | J10: $380 | L10: Activo
A11: 109 | B11: Regina Samantha Leza | C11: 45085 | E11: 8443501370 | G11: Víctor Gaytán | H11: Individual | I11: N/A | K11: 250 | L11: No hay contacto
A12: 110 | B12: melissa de la paz ovalle | C12: 45086 | E12: 8446076392 | G12: Yulior Ramírez | H12: Individual | I12: N/A | K12: 50 | L12: No hay contacto
A13: 111 | B13: Fernanda Medina | C13: 45094 | E13: 8442055892 | G13: Javier Martinez | H13: Individual | I13: N/A | J13: $380 | K13: 250 | L13: No hay contacto
A14: 112 | B14: Liceide Cardenas | C14: 45095 | E14: 8441298997 | G14: Pablo Acosta | H14: Individual | I14: N/A | L14: No hay contacto
A15: 113 | B15: Rosa Vazquez | C15: 45095 | E15: 8443180543 | G15: Víctor Gaytán | H15: Individual | I15: Servicio Gratuito | K15: 250 | L15: No hay contacto
A16: 114 | B16: Oscar Pedrosa | C16: 45096 | G16: Arcadio | H16: Individual | I16: N/A | K16: 250 | L16: BAJA
A17: 115 | B17: Luis Carlos Olvera | C17: 45100 | E17: 8443534681 | G17: Víctor Gaytán | H17: Individual | I17: N/A | L17: No hay contacto
A18: 116 | B18: Yasmin constante | C18: 45103 | E18: 8448708731 | G18: Pablo Acosta | H18: Breve | I18: N/A | L18: No hay contacto
A19: 117 | B19: LAURA SANCHEZ | C19: 45104 | E19: 8442652903 | G19: Ale Almanza | H19: Infantil | I19: N/A | L19: No hay contacto
A20: 118 | B20: Maria Guadalupe Peña | C20: 45104 | E20: 8441016267 | G20: Arcadio | H20: Individual | I20: N/A | L20: No hay contacto
A21: 119 | B21: Rafael Antonio Lopez Torrres | C21: 45104 | E21: 8442023767 | G21: Ale Almanza | H21: Familiar/Individual | I21: N/A | J21: 807 | K21: Empresa | L21: No hay contacto
A22: 120 | B22: Ramiro Cedillo | C22: 45107 | E22: 8444528980 | G22: Pablo Acosta | H22: Individual | I22: N/A | K22: Sueldo base | L22: No hay contacto
A23: 121 | B23: LUISA MOYA | C23: 45108 | E23: 8443188978 | G23: Arcadio | H23: Individual | I23: $170 | L23: No hay contacto
A24: 122 | B24: Kattya Valeria Vazquez Ortiz | C24: 45109 | E24: 8442034920 | G24: Yulior Ramírez | H24: Individual | I24: N/A | L24: No hay contacto
A25: 123 | B25: sandra fabiola reyna | C25: 45109 | E25: 8442391084 | G25: Yulior Ramírez | H25: Individual | I25: $250 | K25: 200 | L25: No hay contacto
A26: 124 | B26: Sofia de Lourdes Medina | C26: 45109 | E26: 8442432140 | G26: Ale Almanza | H26: Individual | I26: N/A | K26: Sueldo base | L26: No hay contacto
A27: 125 | B27: Ximena Abigail Coronado Torres | C27: 45110 | E27: 8444968680 | G27: Ale Almanza | H27: Infantil | I27: N/A | K27: 9 | L27: No hay contacto
A28: 126 | B28: Maricruz Ibarra Ramírez | C28: 45111 | E28: 8441769041 | G28: Arcadio | H28: Individual | I28: N/A | K28: 200 | L28: No hay contacto
A29: 127 | B29: Samantha Camacho | C29: 45120 | G29: Víctor Gaytán | H29: Individual | I29: N/A | K29: 200 | L29: No hay contacto
A30: 128 | B30: Karla Gabriela Quiroz | C30: 45124 | E30: 8442991953 | G30: Víctor Gaytán | L30: BAJA
A31: 129 | B31: Margarita Lizárraga | C31: 45128 | E31: 8443933370 | G31: Víctor Gaytán | H31: Individual | I31: N/A | L31: No hay contacto
A32: 130 | B32: Perla Cecilia Carrillo | C32: 45131 | E32: 8441385491 | G32: Víctor Gaytán | L32: No hay contacto
A33: 131 | B33: Raul Lopez | C33: 45131 | E33: 8445876432 | G33: Víctor Gaytán | K33: 250 | L33: No hay contacto
A34: 132 | B34: Marcela R. Cordova | C34: 45137 | E34: 8443216217 | G34: Víctor Gaytán | L34: No hay contacto
A35: 133 | B35: Maria Yolanda Morales | C35: 45142 | E35: 8446006639 | G35: Arcadio | K35: 200 | L35: No hay contacto
A36: 134 | B36: Yesenia Gzlz. Hdz | C36: 45142 | E36: 5539072567 | G36: Víctor Gaytán | L36: No hay contacto
A37: 135 | B37: Ulises Ramirez | C37: 44050 | E37: 8442774903 | G37: Arcadio | L37: No hay contacto
A38: 136 | B38: Sergio Isaac Morado García | C38: 44051 | E38: 8443400214 | G38: Arcadio | K38: EMPRESA | L38: No hay contacto
A39: 137 | B39: Pamela Guadalupe Cabral Perez (Reyna) | C39: 45148 | E39: 8443120567 | G39: Víctor Gaytán | K39: 250 | L39: No hay contacto
A40: 138 | B40: Sofia Elena Flores Escobedo | C40: 45150 | E40: 8442218395 | G40: Arcadio | K40: 350 | L40: No hay contacto
A41: 139 | B41: Rogelio Pizaña | C41: 45155 | E41: 8443921740 | G41: Idalia | K41: 250 | L41: No hay contacto
A42: 140 | B42: Perla Palma | C42: 45160 | E42: 8441196470 | G42: Javier Mtz | H42: individual | J42: $380 | K42: 250 | L42: BAJA
A43: 141 | B43: Maria del socorro Rodarte | C43: 45163 | E43: 8445327965 | G43: Pablo Acosta | H43: pareja | L43: No hay contacto
A44: 142
A45: 143 | B45: Marco Antonio Torres Zavala | C45: 16-sep | E45: 8442351391 | G45: Víctor Gaytán | L45: No hay contacto
A46: 144 | B46: Melissa | C46: 44092 | E46: 8444844914 | G46: Arcadio | H46: Individual | K46: 250 | L46: No hay contacto
A47: 145 | B47: Maria Angelica Moreno Alcala | C47: 26-sep | G47: Víctor Gaytán | H47: individual | L47: No hay contacto
A48: 146 | B48: Neymar Rubio Gonzalez | C48: 26-sep | E48: 8442324826 | G48: Ale Almanza | H48: Individual | K48: 0 | L48: No hay contacto
A49: 147 | B49: Pedro Flores | C49: 28-sep | E49: 8448817845 | G49: Miguel | K49: 300 | L49: No hay contacto
A50: 148 | B50: Mariane Alejandra Reyes | C50: 45200 | E50: 844 105 8661 | G50: Victor | H50: individual | K50: 300 | L50: No hay contacto
A51: 149 | B51: PAOLA ROBLEDO | C51: 45201 | E51: 844598342 | G51: Arcadio | H51: individual | K51: Sueldo base | L51: No hay contacto
A52: 150 | B52: Sinddy Sarau Avila Castorena | C52: 45201 | G52: Victor | K52: Sueldo base | L52: BAJA
A53: 151 | B53: Marcela Lopez | C53: 45213 | E53: 8442323325 | G53: Arcadio | H53: Individual | L53: No hay contacto
A54: 152 | B54: Maria Victoria Marines | C54: 45213 | E54: 8128670604 | G54: Arcadio | H54: individual | K54: 50 | L54: No hay contacto
A55: 153 | B55: MARTHA SANCHEZ | C55: 45213 | E55: 84412323046 | G55: Ale Almanza | H55: Individual | K55: 250 | L55: No hay contacto
A56: 154 | B56: Perla Yuvisela Ledezma Mtz | C56: 45214 | E56: 844 597 1070 | G56: Ana Cecilia | H56: Individual | K56: 250 | L56: No hay contacto
A57: 155 | B57: Mirel Yocelin chicano calderon | C57: 44125 | E57: 8442785934 | G57: Rosario | H57: Individual | K57: 200 | L57: No hay contacto
A58: 156 | B58: Miguel Ángel Parra Simental | C58: 45221 | E58: 844391465 | G58: Jesus | H58: Individual | K58: 250 | L58: BAJA
A59: 157 | B59: Maritza Cerda (Madre Violeta Cedillo) | C59: 45225 | E59: 844 464 1101 | G59: Ale Almanza | H59: Individual | K59: 250 | L59: BAJA
A60: 158 | B60: Maria Fernanda | C60: 45227 | E60: 8442918730 | G60: pablo | H60: Individual | L60: No hay contacto
A61: 159 | B61: Samuel y Asenad | C61: 45229 | E61: 844 119 6470 | G61: Arcadio | H61: individual | K61: 300 | L61: No hay contacto
A62: 160 | B62: Yanet García y Jesus Hdz | C62: 45234 | E62: 8442046606 | G62: Ana Cecilia | H62: individual | L62: No hay contacto
A63: 161 | B63: Lucia Salas Flores | C63: 45235 | G63: ANA CECILIA | H63: INDIVIDUAL | L63: BAJA
A64: 162 | B64: Noe Saldaña | C64: 45236 | G64: ALE ALMANZA | H64: INDIVIDUAL | K64: 300 | L64: No hay contacto
A65: 163 | B65: Karen Alejandra Pinales | C65: 45242 | G65: IDALIA | H65: INDIVIDUAL | L65: BAJA
A66: 164 | B66: Mónica Monsivais | C66: 45242 | G66: ALE ALMANZA | H66: INDIVIDUAL | K66: 200 | L66: No hay contacto
A67: 165 | B67: María Guadalupe Garza Alemán | C67: 45243 | G67: VICTOR | H67: INDIVIDUAL | K67: 250 | L67: No hay contacto
A68: 166 | B68: Nelly Marisol Sanchez Martinez | C68: 45244 | G68: ALE ALMANZA | K68: 250 | L68: No hay contacto
A69: 167
A70: 168 | B70: Margarita Martinez Puente | C70: 45249 | E70: 8443501508 | G70: IDALIA | H70: INDIVIDUAL | L70: BAJA
A71: 169 | B71: Karen Janeth | C71: 45250 | E71: 8441569785 | G71: IDALIA | H71: INDIVIDUAL | L71: ALTA
A72: 170 | B72: Leticia Herrera | C72: 45250 | G72: IDALIA | H72: INDIVIDUAL | L72: No hay contacto
A73: 171 | B73: Luis Felipe Garcia | C73: 45250 | E73: 8442286583 | G73: IDALIA | H73: INDIVIDUAL | L73: No hay contacto
A74: 172 | B74: Paola Vaquera Saucedo | C74: 45251 | G74: ARCADIO | H74: INDIVIDUAL | K74: 300 | L74: No hay contacto
A75: 173 | B75: Saul Ricardo Rdz Rivera | C75: 45260 | E75: 844 502 9870 | G75: ALE ALMANZA | H75: INDIVIDUAL | K75: 300 | L75: No hay contacto
A76: 174 | B76: Kevin David Martínez | C76: 45262 | E76: 8444273149 | G76: Alejandra Durán | H76: INDIVIDUAL | L76: BAJA
A77: 175 | B77: Karen Llamas Guevara/ Cristian | C77: 45265 | E77: 8448072855 | G77: Alejandra Durán | H77: INDIVIDUAL | L77: BAJA
A78: 176 | B78: Morana Valentina de Leon | C78: 45265 | E78: 8448792591 | G78: ESMERALDA | H78: INFANTIL | J78: 380 | K78: 250 | L78: No hay contacto
A79: 177 | B79: Yahaira C. Sanchez | C79: 45265 | E79: 8443695396 | G79: Alejandra Durán | H79: INDIVIDUAL | L79: No hay contacto
A80: 178 | B80: Miguel Angel Tapia | C80: 45267 | E80: 8443404725 | G80: Alejandra Durán | H80: INDIVIDUAL | L80: No hay contacto
A81: 179 | B81: Victor Adrian | C81: 44175 | E81: 8442833448 | G81: Javier Martinez | H81: Individual | L81: No hay contacto
A82: 180 | B82: Olga Beatriz Morín Montalvo | C82: 45278 | E82: 8443409064 | G82: IDALIA | H82: INDIVIDUAL | K82: 250 | L82: No hay contacto
A83: 181 | B83: Teresa Soria | C83: 44203 | E83: 844 127 5821 | G83: JAVIER MARTINEZ | H83: PAREJA | L83: No hay contacto
A84: 182 | B84: Laura Berlanga | C84: 44204 | G84: ALE ALMANZA | H84: JUVENIL | L84: BAJA
A85: 183 | B85: Ximena Hernandez | C85: 44205 | E85: 844 292 6179 | G85: Arcadio | H85: Individual | J85: 300 | K85: 200 | L85: No hay contacto
A86: 184 | B86: Santiago Rodriguez | C86: 44207 | E86: 844 347 9046 | G86: Rosario | H86: INFANTIL | K86: 200 | L86: No hay contacto
A87: 185 | B87: Miguel Dominguez | C87: 44211 | G87: ANA CECILIA | H87: INFANTIL | K87: 250 | L87: No hay contacto
A88: 186 | B88: Maria Guadalupe Cuellar | C88: 44218 | E88: 8442136989 | G88: JAVIER MARTINEZ | H88: INDIVIDUAL | L88: No hay contacto
A89: 187 | B89: Leonaedo David Martinez | C89: 44219 | E89: 84449456954 | G89: Rosario | H89: INDIVIDUAL | L89: BAJA
A90: 188 | B90: Martha P. Tovar Cortez | C90: 44219 | E90: 844 405 7201 | G90: Rosario | H90: INFANTIL | K90: 250 | L90: No hay contacto
A91: 189 | B91: Nallely Cruz | C91: 44222 | E91: 8443480033 | G91: JAVIER MARTINEZ | H91: INDIVIDUAL | L91: No hay contacto
A92: 190 | B92: Lluvisela Salas | C92: 44223 | E92: 8443710287 | G92: JAVIER MARTINEZ | H92: FAMILIAR | L92: No hay contacto
A93: 191 | B93: Pedro Alberto Fuentes Martinez | C93: 44224 | E93: 844 277 7212 | G93: Rosario | H93: INDIVIDUAL | K93: Sueldo base | L93: No hay contacto
A94: 192 | B94: RICARDO MAGALLA | C94: 44225 | E94: 8441380404 | G94: ARCADIO | H94: INDIVIDUAL | K94: 250 | L94: No hay contacto
A95: 193 | B95: Yeimi Gpe. Austria | C95: 44225 | E95: 8442019169 | G95: Rosario | H95: FAMILIAR | L95: No hay contacto
A96: 194 | B96: valeria Villalobos | C96: 44228 | E96: 4445065864 | G96: ESMERALDA | H96: INDIVIDUAL | L96: No hay contacto
A97: 195 | B97: Maria Josefa Cordoba | C97: 44229 | E97: 8441029526 | G97: JAVIER MARTINEZ | H97: PAREJA | K97: 250 | L97: No hay contacto
A98: 196 | B98: Rodolfo Macias Lozano | C98: 44231 | G98: ESMERALDA | H98: FAMILIAR | K98: Sueldo base | L98: No hay contacto
A99: 197 | B99: vanessa Jaqueline castillo Robledo | C99: 44231 | E99: 8441039598 | G99: JAVIER MARTINEZ | H99: pareja | L99: No hay contacto
A100: 198 | B100: Michael Sánchez Sotero | C100: 44233 | E100: 8441002322 | G100: ARCADIO | H100: INDIVIDUAL | K100: 200 | L100: BAJA
...

Sheet Convenios
B3: CONVENIO | C3: CATEGORIA | D3: $ | E3: Detalles
B4: Academia INTRA | C4: Escuela | D4: Individual e infantil: $350 Especialización, Pareja, Familiar: $400 Médica $700
B5: Cáritas de Saltillo | C5: Asociación civil | D5: Canalizados: 25% de descuento Colaboradores: 35% de descuento
B6: Colegio Americano | C6: Escuela | D6: Individual e infantil: $300 Pareja, Familiar: $350 Medica: 500 Psiquiatrica: 770
B7: Dorothea | C7: Escuela | D7: Individual e infantil: $350 Pareja, Familiar: $350 Medica: 500 Psiquiatrica: 770
B8: EDUCEM | C8: Escuela | D8: Individual e infantil: $300 Pareja, Familiar: $350 Medica: 500 Psiquiatrica: 770
B9: Facultad de psicologia | C9: Escuela | D9: Individual e infantil: $300 Pareja, Familiar: $350 Medica: 500 Psiquiatrica: 770
B10: Fiscalía Coahuila | C10: Instancia de gobierno | D10: Individual e infantil: $300 Pareja, Familiar: $350 Medica: 500 Psiquiatrica: 770 | E10: Fiscalía General del Estado de Coahuila
B11: Fundación Erika | C11: Asociación civil | D11: Individual e infantil: $300 Pareja, Familiar: $350 Medica: 500 Psiquiatrica: 770
B12: GIASA | C12: Empresa | D12: Paga la empresa | E12: incluye individual o infantil, solo familiares directos (otro servicio ocupan autorización de RH)
B13: Greenhill | C13: Escuela | D13: Individual e infantil: $300 Pareja, Familiar: $350 Medica: 500
B14: iFOOD | C14: Empresa | D14: Paga la empresa, susana nos comparte el nombre del proximo paciente (350 ya incluye iva) | E14: Incluye terapia individual, infantil y de pareja
B15: INSUNTE | C15: Escuela | D15: Individual e infantil: $300 Pareja, Familiar: $350 Medica: 500 Psiquiatrica: 770
B16: NEAPCO | C16: Empresa | D16: Paga la empresa, entregan pase | E16: Incluye todos los servicios. (evaluaciones si son varias sesiones, pedir vale por hora)
B17: Particular | C17: INTRA | D17: individual 420, infantil 480, pareja 520, familiar, 550, medica 550, psiquiatrica 850
B18: Secretaria de Salud | C18: Instancia de gobierno | D18: Individual e infantil: $300 Pareja, Familiar: $350 Medica: 500 Psiquiatrica: 770
B19: Trabajo social | C19: Escuela | D19: Individual e infantil: $300 Pareja, Familiar: $350 Medica: 500 Psiquiatrica: 770
B20: UANE | C20: Escuela | D20: Individual e infantil: $300 Pareja, Familiar: $350 Medica: 500 Psiquiatrica: 770
B21: UNIVAS | C21: Escuela | D21: Individual e infantil: $300 Pareja, Familiar: $350 Medica: 500 Psiquiatrica: 770
B22: USAER | C22: Instancia de gobierno | D22: Individual y Familiar 200, cualquier otro servicio 20%
B23: Colaboradores | C23: INTRA | D23: individual: 250
B24: UTS | C24: Escuela | D24: Individual e infantil: $300 Pareja, Familiar: $350 Medica: 500 Psiquiatrica: 770
B25: Vizcaya | C25: Escuela | D25: Individual e infantil: $300 Pareja, Familiar: $350 Medica: 500 Psiquiatrica: 770

Sheet INGRESOS
A1: fecha | B1: NO. | C1: SERVICIO | D1: TERAPEUTA | E1: PACIENTE | F1: UBICACION | G1: FACTURA | H1: FORMA DE PAGO | I1: SUBTOTAL | J1: COMISIÓN PAGO TARJETA | K1: IVA | L1: TOTAL | M1: pago a terapeuta | N1: BANCO | O1: INGRESO REAL
A2: 45971 | B2: 2221 | C2: Evaluación Wisc | E2: Jorge Arturo Rodríguez Perales | I2: 0 | J2: N/A | K2: N/A | L2: 0 | N2: =L2-M2 -> 0
A3: 45804 | B3: 2097 | C3: Individual | D3: Rosy Macias | E3: Wendy Alexandra Briones Rodríguez | F3: Morelos | G3: NO | H3: EFECTIVO | I3: 420 | J3: N/A | K3: N/A | L3: 420 | N3: =L3-M3 -> 420
A4: 45804 | B4: 819 | C4: Individual | D4: Yessica Leija | E4: Alexa Osorio | F4: Guanajuato | G4: NO | H4: TARJETA | I4: 125 | J4: 3.75 | K4: N/A | L4: 128.75 | N4: =L4-M4 -> 128.75
A5: 45804 | B5: 2098 | C5: Individual | D5: Maricela Sena | E5: Rafael Hassan de las Fuentes Lugo | F5: Guanajuato | G5: NO | H5: TARJETA | I5: 420 | J5: 12.6 | K5: N/A | L5: 432.6 | N5: =L5-M5 -> 432.6
A6: 45804 | B6: 2079 | C6: Individual | D6: Rosy Macias | E6: Paola Guadalupe Rodríguez Pequeño | F6: Morelos | G6: NO | H6: EFECTIVO | I6: 420 | J6: N/A | K6: N/A | L6: 420 | N6: =L6-M6 -> 420
A7: 45804 | B7: 2078 | C7: Individual | D7: Rosy Macias | E7: Jorge Alfonso Gamboa Saldaña | F7: Morelos | G7: NO | H7: EFECTIVO | I7: 420 | J7: N/A | K7: N/A | L7: 420 | N7: =L7-M7 -> 420
A8: 45804 | B8: 1229 | C8: Individual | D8: Rosy Macias | E8: ximena Guadalupe Gonzalez | F8: Morelos | G8: NO | H8: EFECTIVO | I8: 420 | J8: N/A | K8: N/A | L8: 420 | N8: =L8-M8 -> 420
A9: 45803 | B9: 2106 | C9: Pareja | D9: Daniel Salazar | E9: Juan Manuel Cisneros Silva y Claudia Leticia Manzanares Lumbreras | F9: Morelos | G9: NO | I9: 520 | J9: N/A | K9: N/A | L9: 520 | N9: =L9-M9 -> 520
A10: 45803 | B10: 856 | C10: Individual | D10: José Arcadio | E10: Christian Valencia | F10: Praderas | G10: NO | H10: TRANSFERENCIA | I10: 420 | J10: N/A | K10: N/A | L10: 420 | N10: =L10-M10 -> 420
A11: 45803 | B11: 2012 | C11: Individual | D11: Benjamin Villagomez | E11: Maricela Sena García | F11: Guanajuato | G11: NO | H11: EFECTIVO | I11: 300 | J11: N/A | K11: N/A | L11: 300 | N11: =L11-M11 -> 300
A12: 45803 | B12: 1736 | C12: Individual | D12: Daniel Salazar | E12: Carlos Monsivais | F12: TEAMS | G12: NO | H12: TRANSFERENCIA | I12: 400 | J12: N/A | K12: N/A | L12: 400 | N12: =L12-M12 -> 400
A13: 45803 | B13: 2105 | C13: Pareja | D13: José Arcadio | E13: Luis Escobedo Flores y Mariana Castañeda Garcia | F13: Praderas | G13: NO | I13: 520 | J13: N/A | K13: N/A | L13: 520 | N13: =L13-M13 -> 520
A14: 45803 | B14: 1827 | C14: Individual | D14: Alondra Escalon | E14: Andrea Guadalupe Padilla Resendiz | F14: Praderas | G14: NO | H14: SEGURO | I14: 0 | J14: N/A | K14: N/A | L14: 0 | N14: =L14-M14 -> 0
A15: 45803 | B15: 2029 | C15: Evaluación neuropsicológica | D15: Dante Zertuche | E15: Franscisco Daniel Lopez | F15: Morelos | G15: NO | I15: 1850 | J15: N/A | K15: N/A | L15: 1850 | N15: =L15-M15 -> 1850
A16: 45803 | B16: 783 | C16: Individual | D16: Dante Zertuche | E16: Samuel Lozano | F16: Morelos | G16: NO | I16: 400 | J16: N/A | K16: N/A | L16: 400 | N16: =L16-M16 -> 400
A17: 45803 | B17: 1789 | C17: Empresa Atención Psicológica NEAPCO | D17: Dante Zertuche | E17: Dominick Ronaldo García Sánchez | F17: Morelos | G17: NO | H17: EMPRESA | I17: 0 | J17: N/A | K17: N/A | L17: 0 | N17: =L17-M17 -> 0
A18: 45801 | B18: 2062 | C18: Individual | D18: Benjamin Villagomez | E18: David Alberto Sanchez Ramirez | F18: Guanajuato | G18: NO | H18: TARJETA | I18: 420 | J18: 12.6 | K18: N/A | L18: 432.6 | N18: =L18-M18 -> 432.6
A19: 45801 | B19: 796 | C19: Infantil | D19: Daniela Sarmiento | E19: Iker Emiliano Osorio | F19: TEAMS | G19: NO | I19: 125 | J19: N/A | K19: N/A | L19: 125 | N19: =L19-M19 -> 125
A20: 45801 | B20: 2096 | C20: Individual | D20: Benjamin Villagomez | E20: Christian Michelle Calvillo Franco | F20: Guanajuato | G20: NO | H20: EFECTIVO | I20: 420 | J20: N/A | K20: N/A | L20: 420 | N20: =L20-M20 -> 420
A21: 45801 | B21: 2087 | C21: Medica | D21: Enrique Luna | E21: Mario Zamarripa | F21: Guanajuato | G21: NO | I21: 600 | J21: N/A | K21: N/A | L21: 600 | N21: =L21-M21 -> 600
A22: 45801 | B22: 2093 | C22: Individual | D22: Daniela Sarmiento | E22: Izamar Alejandra Rosales Vega | F22: Praderas | G22: NO | H22: EFECTIVO | I22: 250 | J22: N/A | K22: N/A | L22: 250 | N22: =L22-M22 -> 250
A23: 45801 | B23: 2053 | C23: Individual | D23: Daniel Salazar | E23: Olga Liliana De la Canal Galindo | F23: Morelos | G23: NO | H23: EFECTIVO | I23: 420 | J23: N/A | K23: N/A | L23: 420 | N23: =L23-M23 -> 420
A24: 45801 | B24: 2004 | C24: Individual | D24: José Arcadio | E24: Luis Diego Lopez Oropeza | F24: Praderas | G24: NO | H24: EFECTIVO | I24: 420 | J24: N/A | K24: N/A | L24: 420 | N24: =L24-M24 -> 420
A25: 45801 | B25: 2087 | C25: Individual | D25: Javier Martínez | E25: Mario Zamarripa | F25: Guanajuato | G25: NO | I25: 300 | J25: N/A | K25: N/A | L25: 300 | N25: =L25-M25 -> 300
A26: 45800 | B26: 2087 | C26: Individual | D26: Maricela Sena | E26: Mario Zamarripa | F26: Guanajuato | G26: NO | H26: EFECTIVO | I26: 300 | J26: N/A | K26: N/A | L26: 300 | N26: =L26-M26 -> 300
A27: 45800 | B27: 622 | C27: Empresa Atención Psicológica NEAPCO | D27: Psicólogos por hora | E27: Luis Contreras | F27: Consultorio externo | G27: NO | H27: EMPRESA | I27: 0 | J27: N/A | K27: N/A | L27: 0 | N27: =L27-M27 -> 0
A28: 45800 | B28: 1402 | C28: Individual | D28: Maria Amancio | E28: Assef Lara Ibarra | F28: TEAMS | G28: NO | H28: PASE | I28: 0 | J28: N/A | K28: N/A | L28: 0 | N28: =L28-M28 -> 0
A29: 45799 | B29: 2103 | C29: Empresa Atención Psicológica NEAPCO | D29: Gloria Sarmiento | E29: Carlos Alejandro Olvera flores | F29: Colinas | G29: NO | H29: EMPRESA | I29: 0 | J29: N/A | K29: N/A | L29: 0 | N29: =L29-M29 -> 0
A30: 45799 | B30: 2102 | C30: Individual | D30: Ana Juarez | E30: Amarantah Hernández | F30: TEAMS | G30: NO | H30: TRANSFERENCIA | I30: 300 | J30: N/A | K30: N/A | L30: 300 | N30: =L30-M30 -> 300
A31: 45799 | B31: 2059 | C31: GIASA | D31: Gloria Sarmiento | E31: Maricela Herrera | F31: Colinas | G31: NO | H31: EMPRESA | I31: 0 | J31: N/A | K31: N/A | L31: 0 | N31: =L31-M31 -> 0
A32: 45799 | B32: 2050 | C32: Individual | D32: José Arcadio | E32: Magaly Martínez | F32: Praderas | G32: NO | H32: EFECTIVO | I32: 350 | J32: N/A | K32: N/A | L32: 350 | N32: =L32-M32 -> 350
A33: 45799 | C33: Renta de espacios - Asociados | D33: Alondra Escalon | E33: - | F33: Praderas | G33: NO | H33: EFECTIVO | I33: 125 | J33: N/A | K33: N/A | L33: 125 | N33: =L33-M33 -> 125
A34: 45799 | B34: 2081 | C34: Individual | D34: Gloria Sarmiento | E34: Leonel Abraham Galindo Garay | F34: Colinas | G34: NO | I34: 420 | J34: N/A | K34: N/A | L34: 420 | N34: =L34-M34 -> 420
A35: 45799 | B35: 1887 | C35: Individual | D35: Javier Martínez | E35: Sandra Garcia Davila | F35: Guanajuato | G35: NO | I35: 400 | J35: N/A | K35: N/A | L35: 400 | N35: =L35-M35 -> 400
A36: 45799 | B36: 1833 | C36: Individual | D36: Yessica Leija | E36: Vianney González | F36: Guanajuato | G36: NO | H36: EFECTIVO | I36: 400 | J36: N/A | K36: N/A | L36: 400 | N36: =L36-M36 -> 400
A37: 45799 | B37: 1082 | C37: Individual | D37: Maria Amancio | E37: Edwin Resendiz | F37: TEAMS | G37: NO | H37: PASE | I37: 350 | J37: N/A | K37: N/A | L37: 350 | N37: =L37-M37 -> 350
A38: 45798 | B38: 2010 | C38: Individual | D38: Benjamin Villagomez | E38: Jhonatan David Romero Martínez | F38: Guanajuato | G38: NO | H38: EFECTIVO | I38: 420 | J38: N/A | K38: N/A | L38: 420 | N38: =L38-M38 -> 420
A39: 45798 | B39: 2101 | C39: Individual | D39: Benjamin Villagomez | E39: Ana Ma Servin Domínguez | F39: Consultorio externo | G39: NO | H39: EFECTIVO | I39: 570 | J39: N/A | K39: N/A | L39: 570 | N39: =L39-M39 -> 570
A40: 45798 | B40: 1444 | C40: Individual | D40: Javier Martínez | E40: Fernando Medina | F40: Guanajuato | G40: NO | H40: TARJETA | I40: 400 | J40: 12 | K40: N/A | L40: 412 | N40: =L40-M40 -> 412
A41: 45798 | B41: 1788 | C41: Individual | D41: Javier Martínez | E41: Celic Garcia | F41: Guanajuato | G41: NO | H41: TRANSFERENCIA | I41: 280 | J41: N/A | K41: N/A | L41: 280 | N41: =L41-M41 -> 280
A42: 45798 | B42: 2100 | C42: Individual | D42: José Arcadio | E42: Alejandra Patricia Perez Lascano | F42: Colinas | G42: NO | H42: TRANSFERENCIA | I42: 420 | J42: N/A | K42: N/A | L42: 420 | N42: =L42-M42 -> 420
A43: 45798 | B43: 1233 | C43: Individual | D43: Maricela Sena | E43: Assef Lara Ibarra | F43: TEAMS | G43: NO | H43: PASE | I43: 0 | J43: N/A | K43: N/A | L43: 0 | N43: =L43-M43 -> 0
A44: 45797 | B44: 998 | C44: Infantil | D44: Esmeralda Colunga | E44: Debany Adabella Flores | F44: Morelos | G44: NO | I44: 480 | J44: N/A | K44: N/A | L44: 480 | N44: =L44-M44 -> 480
A45: 45797 | B45: 2034 | C45: Infantil | D45: Esmeralda Colunga | E45: Mariana Denisse Conchis | F45: Morelos | G45: NO | I45: 480 | J45: N/A | K45: N/A | L45: 480 | N45: =L45-M45 -> 480
A46: 45797 | B46: 2099 | C46: Individual | D46: Alondra Escalon | E46: Valeria Díaz Rentería | F46: Praderas | G46: NO | H46: EFECTIVO | I46: 420 | J46: N/A | K46: N/A | L46: 420 | N46: =L46-M46 -> 420
A47: 45797 | B47: 2082 | C47: Individual | D47: José Arcadio | E47: Jonás Alejandro Morales Hinojosa | F47: Colinas | G47: NO | H47: TRANSFERENCIA | I47: 420 | J47: N/A | K47: N/A | L47: 420 | N47: =L47-M47 -> 420
A48: 45797 | B48: 1828 | C48: Individual | D48: Ana Juarez | E48: Angel Emmanuel Dimas Varela | F48: Guanajuato | G48: NO | H48: EFECTIVO | I48: 300 | J48: N/A | K48: N/A | L48: 300 | N48: =L48-M48 -> 300
A49: 45797 | B49: 2075 | C49: Individual | D49: Gloria Sarmiento | E49: Ana Luisa Gonzalez Flores | F49: Colinas | G49: NO | H49: EFECTIVO | I49: 250 | J49: N/A | K49: N/A | L49: 250 | N49: =L49-M49 -> 250
A50: 45797 | B50: 2098 | C50: Individual | D50: Maricela Sena | E50: Rafael Hassan de las Fuentes Lugo | F50: Guanajuato | G50: NO | I50: 420 | J50: N/A | K50: N/A | L50: 420 | N50: =L50-M50 -> 420
A51: 45797 | B51: 2097 | C51: Individual | D51: Rosy Macias | E51: Wendy Alexandra Briones Rodríguez | F51: Morelos | G51: NO | H51: EFECTIVO | I51: 420 | J51: N/A | K51: N/A | L51: 420 | N51: =L51-M51 -> 420
A52: 45797 | B52: 2079 | C52: Individual | D52: Rosy Macias | E52: Paola Guadalupe Rodríguez Pequeño | F52: Morelos | G52: NO | H52: EFECTIVO | I52: 420 | J52: N/A | K52: N/A | L52: 420 | N52: =L52-M52 -> 420
A53: 45797 | B53: 2078 | C53: Individual | D53: Rosy Macias | E53: Jorge Alfonso Gamboa Saldaña | F53: Morelos | G53: NO | H53: EFECTIVO | I53: 420 | J53: N/A | K53: N/A | L53: 420 | N53: =L53-M53 -> 420
A54: 45797 | B54: 2033 | C54: Consulta psiquiatrica | D54: Carlos Mendiola | E54: Aarón Martinez Quintanilla | F54: Consultorio externo | G54: NO | H54: TRANSFERENCIA | I54: 1000 | J54: N/A | K54: N/A | L54: 1000 | N54: =L54-M54 -> 1000
A55: 45797 | B55: 2028 | C55: Pareja | D55: Maria Amancio | E55: Jose Mena y Aracely Juarez | F55: TEAMS | G55: NO | H55: TRANSFERENCIA | I55: 520 | J55: N/A | K55: N/A | L55: 520 | N55: =L55-M55 -> 520
A56: 45796 | B56: 856 | C56: Individual | D56: José Arcadio | E56: Christian Valencia | F56: Guanajuato | G56: NO | I56: 420 | J56: N/A | K56: N/A | L56: 420 | N56: =L56-M56 -> 420
A57: 45796 | B57: 2058 | C57: Individual | D57: José Arcadio | E57: Liliana Barrón Ríos | F57: Guanajuato | G57: NO | H57: TRANSFERENCIA | I57: 420 | J57: N/A | K57: N/A | L57: 420 | N57: =L57-M57 -> 420
A58: 45796 | B58: 1715 | C58: Individual | D58: José Arcadio | E58: Luis Orozco Peña | F58: Guanajuato | G58: NO | H58: TRANSFERENCIA | I58: 400 | J58: N/A | K58: N/A | L58: 400 | N58: =L58-M58 -> 400
A59: 45796 | B59: 1617 | C59: Empresa Atención Psicológica NEAPCO | D59: Perla Realme | E59: Derek Daniel Salas | F59: Guanajuato | G59: NO | H59: EMPRESA | I59: 0 | J59: N/A | K59: N/A | L59: 0 | N59: =L59-M59 -> 0
A60: 45796 | B60: 2021 | C60: Evaluación neuropsicológica | D60: Dante Zertuche | E60: Carlos Enrique Molina López | F60: Praderas | G60: NO | I60: 500 | J60: N/A | K60: N/A | L60: 500 | N60: =L60-M60 -> 500
A61: 45796 | B61: 1463 | C61: Individual | D61: José Arcadio | E61: Fernanda Fiorella Torres | F61: Guanajuato | G61: NO | I61: 400 | J61: N/A | K61: N/A | L61: 400 | N61: =L61-M61 -> 400
A62: 45796 | B62: 1827 | C62: Individual | D62: Alondra Escalon | E62: Andrea Guadalupe Padilla Resendiz | F62: Praderas | G62: NO | H62: Pase | I62: 0 | J62: N/A | K62: N/A | L62: 0 | N62: =L62-M62 -> 0
A63: 45796 | B63: 2074 | C63: GIASA | D63: Yessica Leija | E63: Ashley Niobe Beltrán Herrera | F63: TEAMS | G63: NO | H63: EMPRESA | I63: 0 | J63: N/A | K63: N/A | L63: 0 | N63: =L63-M63 -> 0
A64: 45794 | C64: Renta de espacios - Asociados | D64: Rosy Macias | E64: - | F64: Guanajuato | G64: NO | I64: 125 | J64: N/A | K64: N/A | L64: 125 | N64: =L64-M64 -> 125
A65: 45794 | B65: 2062 | C65: Individual | D65: Benjamin Villagomez | E65: David Alberto Sanchez Ramirez | F65: Guanajuato | G65: NO | H65: TARJETA | I65: 420 | J65: 12.6 | K65: N/A | L65: 432.6 | N65: =L65-M65 -> 432.6
A66: 45794 | B66: 2026 | C66: Individual | D66: Daniela Sarmiento | E66: Jennifer Joselyn Martínez | F66: Praderas | G66: NO | H66: EFECTIVO | I66: 420 | J66: N/A | K66: N/A | L66: 420 | N66: =L66-M66 -> 420
A67: 45794 | B67: 1832 | C67: Individual | D67: José Arcadio | E67: Cecilia Noriega Arévalo | F67: Praderas | G67: NO | I67: 400 | J67: N/A | K67: N/A | L67: 400 | N67: =L67-M67 -> 400
A68: 45794 | B68: 2096 | C68: Individual | D68: Benjamin Villagomez | E68: Christian Michelle Calvillo Franco | F68: Guanajuato | G68: NO | H68: EFECTIVO | I68: 420 | J68: N/A | K68: N/A | L68: 420 | N68: =L68-M68 -> 420
A69: 45794 | B69: 2095 | C69: Individual | D69: José Arcadio | E69: Diego de Jesús Vázquez Rosales | F69: Praderas | G69: NO | H69: EFECTIVO | I69: 250 | J69: N/A | K69: N/A | L69: 250 | N69: =L69-M69 -> 250
A70: 45794 | B70: 2094 | C70: Individual | D70: Daniela Sarmiento | E70: Izamar Estefanía Vázquez Rosales | F70: Praderas | G70: NO | H70: EFECTIVO | I70: 250 | J70: N/A | K70: N/A | L70: 250 | N70: =L70-M70 -> 250
A71: 45794 | B71: 2052 | C71: Infantil | D71: Perla Realme | E71: Eydan Gael Moreno Mata | F71: Guanajuato | G71: NO | H71: EFECTIVO | I71: 480 | J71: N/A | K71: N/A | L71: 480 | N71: =L71-M71 -> 480
A72: 45794 | B72: 2093 | C72: Individual | D72: Daniela Sarmiento | E72: Izamar Alejandra Rosales Vega | F72: Praderas | G72: NO | H72: EFECTIVO | I72: 250 | J72: N/A | K72: N/A | L72: 250 | N72: =L72-M72 -> 250
A73: 45794 | B73: 2017 | C73: Individual | D73: Daniela Sarmiento | E73: Carlos Alberto Hernández Gallegos | F73: Praderas | G73: NO | H73: EFECTIVO | I73: 420 | J73: N/A | K73: N/A | L73: 420
A74: 45794 | B74: 1809 | C74: Individual | D74: Javier Martínez | E74: Genoveva Saucedo | F74: Guanajuato | G74: NO | H74: EFECTIVO | I74: 400 | J74: N/A | K74: N/A | L74: 400 | N74: =L74-M74 -> 400
A75: 45794 | B75: 2041 | C75: Familiar | D75: Daniela Sarmiento | E75: Eder Baez y Karen Garcia | F75: Praderas | G75: NO | H75: TRANSFERENCIA | I75: 520 | J75: N/A | K75: N/A | L75: 520 | N75: =L75-M75 -> 520
A76: 45793 | B76: 2053 | C76: Individual | D76: Daniel Salazar | E76: Olga Liliana De la Canal Galindo | F76: Morelos | G76: NO | H76: EFECTIVO | I76: 420 | J76: N/A | K76: N/A | L76: 420 | N76: =L76-M76 -> 420
A77: 45793 | B77: 2092 | C77: Infantil | D77: Perla Realme | E77: Edgar Iturbe Calderon | F77: Guanajuato | G77: NO | H77: EFECTIVO | I77: 480 | J77: N/A | K77: N/A | L77: 480 | N77: =L77-M77 -> 480
A78: 45793 | B78: 2091 | C78: Individual | D78: Benjamin Villagomez | E78: Lizet Baez | F78: Guanajuato | G78: NO | H78: EFECTIVO | I78: 420 | J78: N/A | K78: N/A | L78: 420 | N78: =L78-M78 -> 420
A79: 45793 | B79: 2090 | C79: Pareja | D79: Daniel Salazar | E79: Eduardo Alvarado y Alondra Natividad | F79: Morelos | G79: NO | H79: EFECTIVO | I79: 520 | J79: N/A | K79: N/A | L79: 520 | N79: =L79-M79 -> 520
A80: 45793 | B80: 2015 | C80: INSUNTE | D80: Benjamin Villagomez | E80: Alejandra Monserrat Vasquez Elizondo | F80: Guanajuato | G80: NO | H80: EFECTIVO | I80: 300 | J80: N/A | K80: N/A | L80: 300 | N80: =L80-M80 -> 300
A81: 45793 | C81: Renta de espacios - Asociados | D81: Alondra Escalon | E81: - | F81: Praderas | G81: NO | H81: TRANSFERENCIA | I81: 125 | J81: N/A | K81: N/A | L81: 125 | N81: =L81-M81 -> 125
A82: 45793 | B82: 2089 | C82: Individual | D82: Daniel Salazar | E82: Merari Madai Gamez Esqueda | F82: Morelos | G82: NO | H82: EFECTIVO | I82: 420 | J82: N/A | K82: N/A | L82: 420 | N82: =L82-M82 -> 420
A83: 45793 | B83: 2088 | C83: Evaluación neuropsicológica | D83: Javier Martínez | E83: David Misael Barragán Perez | F83: Guanajuato | G83: NO | H83: EFECTIVO | I83: 420 | J83: N/A | K83: N/A | L83: 420 | N83: =L83-M83 -> 420
A84: 45793 | B84: 2008 | C84: Individual | D84: Javier Martínez | E84: Elsa Isabel Barrera Espinoza | F84: Guanajuato | G84: NO | H84: EFECTIVO | I84: 300 | J84: N/A | K84: N/A | L84: 300 | N84: =L84-M84 -> 300
A85: 45793 | B85: 2087 | C85: Individual | D85: Maricela Sena | E85: Mario Zamarripa | F85: Guanajuato | G85: NO | I85: 750 | J85: N/A | K85: N/A | L85: 750 | N85: =L85-M85 -> 750
A86: 45792 | B86: 2045 | C86: Individual | D86: José Arcadio | E86: Jose Manuel contreras | F86: Colinas | G86: NO | H86: EFECTIVO | I86: 420 | J86: N/A | K86: N/A | L86: 420 | N86: =L86-M86 -> 420
A87: 45792 | B87: 2087 | C87: Individual | D87: Javier Martínez | E87: Mario Zamarripa | F87: Guanajuato | G87: NO | H87: EFECTIVO | I87: 420 | J87: N/A | K87: N/A | L87: 420 | N87: =L87-M87 -> 420
A88: 45792 | B88: 2063 | C88: Individual | D88: José Arcadio | E88: Jesus Hector Castañeda Gomez | F88: Colinas | G88: NO | I88: 420 | J88: N/A | K88: N/A | L88: 420 | N88: =L88-M88 -> 420
A89: 45792 | B89: 2066 | C89: Individual | D89: Gloria Sarmiento | E89: Abraham Adair Garcia Martinez | F89: Colinas | G89: NO | H89: EFECTIVO | I89: 420 | J89: N/A | K89: N/A | L89: 420 | N89: =L89-M89 -> 420
A90: 45792 | B90: 2086 | C90: Individual | D90: Daniel Salazar | E90: Irina Valentina Rodríguez Durán | F90: Morelos | G90: NO | H90: EFECTIVO | I90: 420 | J90: N/A | K90: N/A | L90: 420 | N90: =L90-M90 -> 420
A91: 45792 | B91: 2037 | C91: Individual | D91: José Arcadio | E91: Maria de Jesús Tobias | F91: Colinas | G91: NO | H91: EFECTIVO | I91: 250 | J91: N/A | K91: N/A | L91: 250 | N91: =L91-M91 -> 250
A92: 45792 | B92: 2085 | C92: Individual | D92: Daniel Salazar | E92: Norma Mendoza Hernández | F92: Morelos | G92: NO | H92: EFECTIVO | I92: 420 | J92: N/A | K92: N/A | L92: 420 | N92: =L92-M92 -> 420
A93: 45792 | B93: 2084 | C93: Individual | D93: Gloria Sarmiento | E93: Isacc Hernández Izquierdo | F93: Colinas | G93: NO | H93: EFECTIVO | I93: 200 | J93: N/A | K93: N/A | L93: 200 | N93: =L93-M93 -> 200
A94: 45792 | B94: 2059 | C94: GIASA | D94: Gloria Sarmiento | E94: Maricela Herrera | F94: Colinas | G94: NO | H94: EMPRESA | I94: 0 | J94: N/A | K94: N/A | L94: 0 | N94: =L94-M94 -> 0
A95: 45792 | B95: 2083 | C95: Individual | D95: Daniel Salazar | E95: Alexa Sarahi | F95: Morelos | G95: NO | H95: TRANSFERENCIA | I95: 420 | J95: N/A | K95: N/A | L95: 420 | N95: =L95-M95 -> 420
A96: 45792 | B96: 2082 | C96: Individual | D96: José Arcadio | E96: Jonás Alejandro Morales Hinojosa | F96: Colinas | G96: NO | H96: TRANSFERENCIA | I96: 420 | J96: N/A | K96: N/A | L96: 420 | N96: =L96-M96 -> 420
A97: 45792 | B97: 2081 | C97: Individual | D97: Gloria Sarmiento | E97: Leonel Abraham Galindo Garay | F97: Colinas | G97: NO | H97: EFECTIVO | I97: 420 | J97: N/A | K97: N/A | L97: 420 | N97: =L97-M97 -> 420
A98: 45792 | B98: 783 | C98: Individual | D98: Dante Zertuche | E98: Samuel Lozano | F98: Morelos | G98: NO | H98: EFECTIVO | I98: 400 | J98: N/A | K98: N/A | L98: 400 | N98: =L98-M98 -> 400
A99: 45792 | B99: 2029 | C99: Evaluación neuropsicológica | D99: Dante Zertuche | E99: Franscisco Daniel Lopez | F99: Morelos | G99: NO | H99: TRANSFERENCIA | I99: 1850 | J99: N/A | K99: N/A | L99: 1850 | N99: =L99-M99 -> 1850
A100: 45792 | B100: 2080 | C100: GIASA | D100: Maricela Sena | E100: Alejandra Olguin Estrada | F100: TEAMS | G100: NO | H100: EMPRESA | I100: 0 | J100: N/A | K100: N/A | L100: 0 | N100: =L100-M100 -> 0
...

Sheet Costos Normales
B3: Servicios Individuales
B4: Individual | C4: 420
B5: Infantil | C5: 480
B6: Psicotanatologia | C6: 400
B7: Hipnosis Clinica | C7: 550
B8: Equinoterapia | C8: 900
B9: Consulta Medica | C9: 600
B10: Consulta Medica en Salud Mental | C10: 850
B11: Consulta Psiquiatrica | C11: 1000
B12: Servicios Grupales
B13: Pareja | C13: 520
B14: Familiar | C14: 550
B15: Otros Servicios
B16: Consulta Nutricional | C16: 550
B17: Evaluación Neuropsicologica | C17: $420
B18: Evaluación Psicologica | C18: 1200 - 2400
B19: Certificado Mascota de Apoyo Emocional | C19: 1900
B20: Constancia de Proceso | C20: 120
B21: Informe Psicologico | C21: 1900

Sheet Ene 26
B1: 46023 | L1: =B1+1 -> 46024 | V1: =L1+1 -> 46025 | AF1: =V1+1 -> 46026 | AP1: =AF1+1 -> 46027 | AZ1: =AP1+1 -> 46028 | BJ1: =AZ1+1 -> 46029 | BT1: =BJ1+1 -> 46030 | CD1: =BT1+1 -> 46031 | CN1: =CD1+1 -> 46032 | CX1: =CN1+1 -> 46033 | DH1: =CX1+1 -> 46034 | DR1: =DH1+1 -> 46035 | EB1: =DR1+1 -> 46036 | EL1: =EB1+1 -> 46037 | EV1: =EL1+1 -> 46038 | FF1: =EV1+1 -> 46039 | FP1: =FF1+1 -> 46040 | FZ1: =FP1+1 -> 46041 | GJ1: =FZ1+1 -> 46042 | GT1: =GJ1+1 -> 46043 | HD1: =GT1+1 -> 46044 | HN1: =HD1+1 -> 46045 | HX1: =HN1+1 -> 46046 | IH1: =HX1+1 -> 46047 | IR1: =IH1+1 -> 46048 | JB1: =IR1+1 -> 46049 | JL1: =JB1+1 -> 46050 | JV1: =JL1+1 -> 46051 | KF1: =JV1+1 -> 46052 | KP1: =KF1+1 -> 46053
A2: Hora | B2: Tipo | C2: División | D2: Paciente | E2: Servicio | F2: Terapeuta | G2: Situación | H2: Consultorio | I2: $ / Pase | J2: Tipo pago | K2: Notas | L2: Tipo | M2: División | N2: Paciente | O2: Servicio | P2: Terapeuta | Q2: Situación | R2: Consultorio | S2: $ / Pase | T2: Tipo pago | U2: Notas | V2: Tipo | W2: División | X2: Paciente | Y2: Servicio | Z2: Terapeuta | AA2: Situación | AB2: Consultorio | AC2: $ / Pase | AD2: Tipo pago | AE2: Notas | AF2: Tipo | AG2: División | AH2: Paciente | AI2: Servicio | AJ2: Terapeuta | AK2: Situación | AL2: Consultorio | AM2: $ / Pase | AN2: Tipo pago | AO2: Notas | AP2: Tipo | AQ2: División | AR2: Paciente | AS2: Servicio | AT2: Terapeuta | AU2: Situación | AV2: Consultorio | AW2: $ / Pase | AX2: Tipo pago | AY2: Notas | AZ2: Tipo | BA2: División | BB2: Paciente | BC2: Servicio | BD2: Terapeuta | BE2: Situación | BF2: Consultorio | BG2: $ / Pase | BH2: Tipo pago | BI2: Notas | BJ2: Tipo | BK2: División | BL2: Paciente | BM2: Servicio | BN2: Terapeuta | BO2: Situación | BP2: Consultorio | BQ2: $ / Pase | BR2: Tipo pago | BS2: Notas | BT2: Tipo | BU2: División | BV2: Paciente | BW2: Servicio | BX2: Terapeuta | BY2: Situación | BZ2: Consultorio | CA2: $ / Pase | CB2: Tipo pago | CC2: Notas | CD2: Tipo | CE2: División | CF2: Paciente | CG2: Servicio | CH2: Terapeuta | CI2: Situación | CJ2: Consultorio | CK2: $ / Pase | CL2: Tipo pago | CM2: Notas | CN2: Tipo | CO2: División | CP2: Paciente | CQ2: Servicio | CR2: Terapeuta | CS2: Situación | CT2: Consultorio | CU2: $ / Pase | CV2: Tipo pago | CW2: Notas | CX2: Tipo | CY2: División | CZ2: Paciente | DA2: Servicio | DB2: Terapeuta | DC2: Situación | DD2: Consultorio | DE2: $ / Pase | DF2: Tipo pago | DG2: Notas | DH2: Tipo | DI2: División | DJ2: Paciente | DK2: Servicio | DL2: Terapeuta | DM2: Situación | DN2: Consultorio | DO2: $ / Pase | DP2: Tipo pago | DQ2: Notas | DR2: Tipo | DS2: División | DT2: Paciente | DU2: Servicio | DV2: Terapeuta | DW2: Situación | DX2: Consultorio | DY2: $ / Pase | DZ2: Tipo pago | EA2: Notas | EB2: Tipo | EC2: División | ED2: Paciente | EE2: Servicio | EF2: Terapeuta | EG2: Situación | EH2: Consultorio | EI2: $ / Pase | EJ2: Tipo pago | EK2: Notas | EL2: Tipo | EM2: División | EN2: Paciente | EO2: Servicio | EP2: Terapeuta | EQ2: Situación | ER2: Consultorio | ES2: $ / Pase | ET2: Tipo pago | EU2: Notas | EV2: Tipo | EW2: División | EX2: Paciente | EY2: Servicio | EZ2: Terapeuta | FA2: Situación | FB2: Consultorio | FC2: $ / Pase | FD2: Tipo pago | FE2: Notas | FF2: Tipo | FG2: División | FH2: Paciente | FI2: Servicio | FJ2: Terapeuta | FK2: Situación | FL2: Consultorio | FM2: $ / Pase | FN2: Tipo pago | FO2: Notas | FP2: Tipo | FQ2: División | FR2: Paciente | FS2: Servicio | FT2: Terapeuta | FU2: Situación | FV2: Consultorio | FW2: $ / Pase | FX2: Tipo pago | FY2: Notas | FZ2: Tipo | GA2: División | GB2: Paciente | GC2: Servicio | GD2: Terapeuta | GE2: Situación | GF2: Consultorio | GG2: $ / Pase | GH2: Tipo pago | GI2: Notas | GJ2: Tipo | GK2: División | GL2: Paciente | GM2: Servicio | GN2: Terapeuta | GO2: Situación | GP2: Consultorio | GQ2: $ / Pase | GR2: Tipo pago | GS2: Notas | GT2: Tipo | GU2: División | GV2: Paciente | GW2: Servicio | GX2: Terapeuta | GY2: Situación | GZ2: Consultorio | HA2: $ / Pase | HB2: Tipo pago | HC2: Notas | HD2: Tipo | HE2: División | HF2: Paciente | HG2: Servicio | HH2: Terapeuta | HI2: Situación | HJ2: Consultorio | HK2: $ / Pase | HL2: Tipo pago | HM2: Notas | HN2: Tipo | HO2: División | HP2: Paciente | HQ2: Servicio | HR2: Terapeuta | HS2: Situación | HT2: Consultorio | HU2: $ / Pase | HV2: Tipo pago | HW2: Notas | HX2: Tipo | HY2: División | HZ2: Paciente | IA2: Servicio | IB2: Terapeuta | IC2: Situación | ID2: Consultorio | IE2: $ / Pase | IF2: Tipo pago | IG2: Notas | IH2: Tipo | II2: División | IJ2: Paciente | IK2: Servicio | IL2: Terapeuta | IM2: Situación | IN2: Consultorio | IO2: $ / Pase | IP2: Tipo pago | IQ2: Notas | IR2: Tipo | IS2: División | IT2: Paciente | IU2: Servicio | IV2: Terapeuta | IW2: Situación | IX2: Consultorio | IY2: $ / Pase | IZ2: Tipo pago | JA2: Notas | JB2: Tipo | JC2: División | JD2: Paciente | JE2: Servicio | JF2: Terapeuta | JG2: Situación | JH2: Consultorio | JI2: $ / Pase | JJ2: Tipo pago | JK2: Notas | JL2: Tipo | JM2: División | JN2: Paciente | JO2: Servicio | JP2: Terapeuta | JQ2: Situación | JR2: Consultorio | JS2: $ / Pase | JT2: Tipo pago | JU2: Notas | JV2: Tipo | JW2: División | JX2: Paciente | JY2: Servicio | JZ2: Terapeuta | KA2: Situación | KB2: Consultorio | KC2: $ / Pase | KD2: Tipo pago | KE2: Notas | KF2: Tipo | KG2: División | KH2: Paciente | KI2: Servicio | KJ2: Terapeuta | KK2: Situación | KL2: Consultorio | KM2: $ / Pase | KN2: Tipo pago | KO2: Notas | KP2: Tipo | KQ2: División | KR2: Paciente | KS2: Servicio | KT2: Terapeuta | KU2: Situación | KV2: Consultorio | KW2: $ / Pase | KX2: Tipo pago | KY2: Notas
A3: 0.375 | AP3: S | AQ3: Particular | AS3: Evaluación neuropsicológica | AT3: Javier Martínez | AU3: Asistió | AV3: Guanajuato C3 | AW3: 350 | AX3: Tarjeta | BB3: AGENDAR LUCIA SANCHEZ SÓLO DE 9:00 A 10:00 | CP3: RENTA ESPACIO | CR3: Enrique Luna | CU3: 125 | DJ3: AGENDAR A LA LIC MARICELA A PARTIR DE LAS 3:00 | EC3: Particular | ED3: Alan Eduardo Mora Serrano | EE3: Individual 2025 | EF3: Maricela Sena | EG3: Reagendó | EH3: Guanajuato C1 | EI3: 420 | EK3: Dijo que mandaba mssj para volver a agendar prox. semana | FZ3: S | GA3: Particular | GB3: María Fernanda Rodríguez Daniel | GD3: Javier Martínez | GE3: Asistió | GF3: Guanajuato C3 | GG3: 350 | GH3: Tarjeta | GI3: Tiene costos autorizados por whats 350 con Lic. MArtínez y 150 con Lic Gloria | GJ3: S | GK3: Particular | GL3: Daniel Ramírez Cervantes | GM3: Individual | GN3: Maricela Sena | GO3: Asistió | GP3: Guanajuato C1 | GQ3: 420 | GR3: Efectivo | GS3: Pidio para 15 dias (6 enero) mismo dia misma hora | HF3: RENTA ESPACIO DR LUNA | HI3: Canceló | HX3: S | HY3: Particular | HZ3: Jorge Arturo Rodríguez Perales | IA3: Medica en salud mental | IB3: Javier Martínez | IC3: Asistió | ID3: Guanajuato C1 | IE3: $350 | IF3: Efectivo | IG3: Tiene estudio SE pero no está el papel físicamente | JN3: NO AGENDAR ESTE DIA AL DOC. ENRIQUE | KR3: BLOQUEADO LIC MARÍA AMANCIO | KU3: Confirmó
A4: 0.375 | AZ4: S | BA4: Particular | BB4: Daniel Ramírez | BC4: Individual | BD4: Maricela Sena | BE4: Asistió | BF4: Guanajuato C1 | BG4: 420 | BH4: Efectivo | BI4: su cita la quiere para dentro de 15 días
A5: 0.375 | BJ5: S | BK5: Particular | BL5: Alan Eduardo Mora Serrano | BM5: Individual 2025 | BN5: Maricela Sena | BO5: Asistió | BP5: Guanajuato C1 | BQ5: 420 | KP5: S | KQ5: Particular | KR5: Zaid Eliseo López | KS5: Infantil | KT5: Gloria Sarmiento | KU5: Confirmó | KV5: Guanajuato C3 | KW5: 500
A6: 0.375
A7: 0.41666667 | D7: Del 19 de Dic al 7de Enero, No agendar a Lic. Rosy | V7: N | W7: Particular | X7: Guadalupe Alejandra Aldaco Moya | Y7: Familiar | Z7: José Arcadio | AB7: Morelos C1 | AC7: 600 | AE7: Se presentó sin confirmar cita | AZ7: S | BA7: Particular | BB7: Alicia Minerva Ordóñez Hernandez | BC7: Individual 2025 | BD7: Maricela Sena | BE7: Asistió | BF7: Guanajuato C1 | BG7: $320 | BH7: Tarjeta | BL7: Del 19 de Dic al 7de Enero, No agendar a Lic. Rosy | BT7: S | BU7: GIASA | BV7: Juan Antonio Guerrero Ramírez | BW7: Individual 2025 | BX7: Maricela Sena | BY7: Asistió | BZ7: ZOOM C1 | CA7: 0 | CP7: RENTA ESPACIO | CR7: Enrique Luna | CU7: 125 | DH7: N | DI7: Particular | DJ7: Victor Manuel Agustince Rosales | DK7: Psicotanatología | DL7: Lucía Sánchez | DM7: No confirmó | DN7: Guanajuato C1 | DO7: 500 | DR7: S | DS7: Particular | DT7: Alicia Minerva Ordóñez Hernandez | DU7: Individual 2025 | DV7: Maricela Sena | DW7: Reagendó | DX7: Guanajuato C1 | DY7: $320 | EA7: Dijo que la prox semana se comunicaba para agendar a su mamá | EL7: S | EM7: GIASA | EN7: Juan Antonio Guerrero Ramírez | EO7: Individual 2025 | EP7: Maricela Sena | EQ7: Asistió | ER7: WhereBy 1 | ES7: 0 | ET7: Pase | EU7: Verificar si su siguiente cita será también por zoom o presencial | FF7: S | FG7: Particular | FH7: Monserrat Hernández | FI7: Individual 2025 | FJ7: Javier Martínez | FK7: Asistió | FL7: Guanajuato C1 | FM7: $420 | FN7: Tarjeta | HD7: S | HE7: GIASA | HF7: Juan Antonio Guerrero Ramírez | HG7: Individual 2025 | HH7: Maricela Sena | HI7: Reagendó | HJ7: WhereBy 1 | HK7: 0 | HL7: Pase | HM7: Reagendó para el sábado a las 6:00 presencial | HX7: S | HY7: Particular | HZ7: Luis Alberto Reyes Soto | IA7: Individual | IB7: José Arcadio | IC7: No confirmó | ID7: Morelos C1 | IE7: 420 | KP7: S | KQ7: Particular | KR7: Monserrat Hernández | KS7: Individual 2025 | KT7: Javier Martínez | KU7: Asistió | KV7: Guanajuato C1 | KW7: $420 | KX7: Efectivo
A8: 0.41666667 | V8: S | W8: Particular | X8: Monserrat Hernández | Y8: Individual 2025 | Z8: Javier Martínez | AA8: Asistió | AB8: Guanajuato C1 | AC8: $420 | AD8: Efectivo | BJ8: S | BK8: Particular | BL8: María Fernanda Medina y Hugo Torres | BM8: Pareja | BN8: Maria Amancio | BO8: No llegó | BP8: Guanajuato C1 | BQ8: 600 | BS8: 0.4375 | CN8: S | CO8: Particular | CP8: Genoveva Saucedo | CQ8: Individual | CR8: Javier Martínez | CS8: Reagendó | CT8: Guanajuato C3 | CU8: 420 | CV8: Efectivo | CW8: Ofrecerle cita con la lic Maria Amancio | FF8: N | FG8: Particular | FH8: Jhonatan Alexander de la Peña Sandate | FI8: Individual | FJ8: Daniela Sarmiento | FK8: Reagendó | FL8: Morelos C1 | FM8: 450 | FO8: Que el se comunicaba nuevamente | HX8: S | HY8: Particular | HZ8: Monserrat Hernández | IA8: Individual 2025 | IB8: Javier Martínez | IC8: Reagendó | ID8: Guanajuato C1 | IE8: $420 | KP8: N | KQ8: Particular | KR8: José Eduardo Sánchez Auces | KS8: Individual | KT8: José Arcadio | KU8: Asistió | KV8: Morelos C1 | KW8: 450 | KX8: Transf - 1872
A9: 0.41666667 | CN9: S | CO9: Particular | CP9: Luis Alberto Reyes Soto | CQ9: Individual | CR9: José Arcadio | CS9: Asistió | CT9: Morelos C1 | CU9: 420 | FF9: N | FG9: Particular | FH9: Guillermo Flores Dávila y Miriam Alejandra Argumedo García | FI9: Pareja | FJ9: Maria Amancio | FK9: Asistió | FL9: Guanajuato C2 | FM9: 600 | FN9: Tarjeta | FO9: Se les refirió por separado, Miriam ya tiene fecha el 24, dejó pendiente a Guillermo, con Arcadio | HX9: N | HY9: Particular | HZ9: Esteffani Magali Donias Alvarez | IA9: Individual | IB9: Gloria Sarmiento | IC9: Asistió | ID9: Guanajuato C2 | IE9: 675 | IF9: Tarjeta | IG9: No llegó a su cita pasada, se le avisó del 50% de multa, sobre el costo de cita de 450 | KP9: N | KQ9: Particular | KR9: Nayeli Abigail Santana Villanueva | KS9: Individual | KT9: Gloria Sarmiento | KU9: Canceló | KV9: Guanajuato C2 | KW9: 450
A10: 0.41666667
A11: 0.41666667
A12: 0.45833333 | L12: S | M12: Particular | N12: Juany Arellano | O12: Familiar | P12: David Bermejo | Q12: Por verificar | V12: N | W12: Particular | X12: Carmen Janeth Montiel Zavala, Carlos Roel Zuñiga Serrato | Y12: Pareja | Z12: José Arcadio | AA12: Asistió | AB12: Morelos C1 | AC12: 600 | AD12: Efectivo | AP12: S | AQ12: Particular | AR12: Sofía Alejandra Padilla Martínez | AS12: Individual 2025 | AT12: Lucía Sánchez | AU12: Asistió | AV12: Guanajuato C2 | AW12: $420 | AX12: Efectivo | AZ12: S | BA12: Particular | BB12: Beatriz Camarena | BC12: Individual 2025 | BD12: Maricela Sena | BE12: Asistió | BF12: Guanajuato C1 | BG12: 200 | BH12: Transf - 1872 | BT12: S | BU12: Particular | BV12: Emmanuel Jimenez Maqueda | BW12: Individual 2025 | BX12: Lucía Sánchez | BY12: Asistió | BZ12: Guanajuato C1 | CA12: 420 | CB12: Tarjeta | CP12: RENTA ESPACIO (Sandra Yazmin Salas Realista | CR12: Enrique Luna | CS12: Asistió | CU12: 125 | DR12: S | DS12: Particular | DT12: Fernanda Díaz Ortega | DU12: Individual 2025 | DV12: Maricela Sena | DW12: Confirmó | DX12: Guanajuato C1 | DY12: $350 | FH12: RENTA ESPACIO | FJ12: Enrique Luna | FK12: Confirmó | FZ12: S | GA12: Particular | GB12: Sofía Alejandra Padilla Martínez | GC12: Individual 2025 | GD12: Lucía Sánchez | GE12: Asistió | GF12: Guanajuato C2 | GG12: $420 | GH12: Transf - 1872 | GJ12: S | GK12: Particular | GL12: Alicia Minerva Ordóñez Hernandez | GM12: Individual | GN12: Maricela Sena | GO12: Asistió | GP12: Guanajuato C1 | GQ12: 320 | GS12: Terapeuta indicó citas una vez por semana | HD12: S | HE12: Particular | HF12: Emmanuel Jimenez Maqueda | HG12: Individual 2025 | HH12: Lucía Sánchez | HI12: Reagendó | HJ12: Guanajuato C1 | HK12: 420 | HM12: Le gusta Offenbach y La vie est belle | HX12: S | HY12: Particular | HZ12: Dora Luz Monsivais Martinez | IA12: Individual 2025 | IB12: José Arcadio | IC12: Incidente | ID12: Morelos C3 | IE12: $420 | IF12: Transf - 1872 | IG12: Confirmó cita desde otro contacto y luego no le tocaba hasta el prox sabado | JV12: S | JW12: Particular | JX12: Emmanuel Jimenez Maqueda | JY12: Individual 2025 | JZ12: Lucía Sánchez | KA12: Reagendó | KB12: Guanajuato C1 | KC12: 420
A13: 0.45833333 | Q13: No confirmó | CN13: N | CO13: Particular | CP13: Ana Sofía Zapata | CQ13: Infantil | CR13: Fabiola Fragoso | CS13: Asistió | CT13: Guanajuato C1 | CU13: 350 | CV13: Tarjeta | FF13: S | FG13: Particular | FH13: Carmen Janeth Montiel Zavala, Carlos Roel Zuñiga Serrato | FI13: Pareja | FJ13: José Arcadio | FK13: Canceló | FL13: Morelos C1 | FM13: 600 | FO13: Que ellos se volvían a comunicar | HX13: S | HY13: Particular | HZ13: Zaid Eliseo López | IA13: Infantil | IB13: Gloria Sarmiento | IC13: Asistió | ID13: Guanajuato C3 | IE13: 500 | IF13: Tarjeta | KP13: S | KQ13: Particular | KR13: Dora Luz Monsivais Martinez | KS13: Individual | KT13: José Arcadio | KU13: Asistió | KV13: Morelos C1 | KW13: 420 | KX13: Transf - 1872
A14: 0.45833333 | CN14: S | CO14: Particular | CP14: Dora Luz Monsiváis Martínez | CQ14: Individual 2025 | CR14: José Arcadio | CS14: Asistió | CT14: Morelos C3 | CU14: $420 | CV14: Transf - 1872 | FO14: Px quiso cambiar a virtual | KP14: S | KQ14: Particular | KR14: Dora Alicia Martinez | KS14: Individual 2025 | KT14: Enrique Luna | KU14: Asistió | KV14: Guanajuato C2 | KW14: 650 | KX14: Transf - 1872
A15: 0.45833333 | CN15: S | CO15: Particular | CP15: Valeria Monserrat López Mata | CQ15: Individual 2025 | CR15: Javier Martínez | CS15: Asistió | CT15: Guanajuato C1 | CU15: $420 | CV15: Tarjeta | FF15: N | FG15: Particular | FH15: Esteffani Magali Donias Alvarez | FI15: Individual | FJ15: Gloria Sarmiento | FK15: No llegó | FL15: Guanajuato C2 | FM15: $450 | FO15: No llegó, pidió reagendaro | HX15: S | HY15: Particular | HZ15: Isaías Hernández Lara | IA15: Médica psiquiatrica | IB15: Enrique Luna | IC15: Incidente | ID15: Guanajuato C1 | IE15: 850 | KP15: S | KQ15: Particular | KR15: Zaid Eliseo López | KS15: Infantil | KT15: Gloria Sarmiento | KU15: Asistió | KV15: Guanajuato C1 | KW15: 500 | KX15: Transf - 1872
A16: 0.45833333 | HZ16: RENTA ESPACIO ENRIQUE LUNA
A17: 0.5 | V17: S | W17: Particular | X17: Dora Luz Monsivais Martinez | Y17: Médica psiquiatrica | Z17: Enrique Luna | AA17: Asistió | AB17: Guanajuato C1 | AC17: 850 | AD17: Transf - 1872 | AP17: N | AQ17: Particular | AR17: Carlos Armando Coutiño Martinez | AS17: Individual | AT17: Lucía Sánchez | AU17: Asistió | AV17: Guanajuato C1 | AW17: $480 | AX17: Efectivo | AZ17: S | BA17: GIASA | BB17: Juan Antonio Guerrero Ramírez | BC17: Individual 2025 | BD17: Maricela Sena | BF17: ZOOM C1 | BG17: 0 | BH17: Pase | BI17: No se le mandó link ofrecerle otra fecha | BT17: N | BU17: Particular | BV17: Luis Carlos Reyes | BW17: Individual | BX17: Lucía Sánchez | BY17: Asistió | BZ17: ZOOM C1 | CA17: 450 | CB17: Transf - 1872 | CC17: De Louisiana | CN17: S | CO17: Particular | CP17: Fatima Valeria Nolasco | CQ17: Individual 2025 | CR17: Enrique Luna | CS17: Asistió | CT17: Guanajuato C1 | CU17: 510 | CV17: Efectivo | CW17: CUENTA CON ESTUDIO SE | EL17: S | EM17: Particular | EN17: Luis Carlos Reyes | EO17: Individual | EP17: Lucía Sánchez | EQ17: Asistió | ER17: WhereBy 1 | ES17: 450 | ET17: Transf - 1872 | FF17: S | FG17: Particular | FH17: Angel Mateo García González y Nicole García | FI17: Infantil | FJ17: Fabiola Fragoso | FK17: Asistió | FL17: Guanajuato C1 | FM17: 400 | FN17: Tarjeta | HD17: S | HE17: Particular | HF17: Luis Carlos Reyes | HG17: Individual | HH17: Lucía Sánchez | HI17: Asistió | HJ17: WhereBy 1 | HK17: 450 | HL17: Transf - 1872 | HM17: PAGADO | HX17: S | HY17: Particular | HZ17: Pedro Alejandro Herrera González | IA17: Individual 2025 | IB17: Enrique Luna | IC17: Asistió | ID17: Guanajuato C1 | IE17: 680 | IF17: Efectivo | IG17: Llamarle a la mamá, no tiene whatsapp | IT17: RENTA LIC GLORIA | IW17: Confirmó | IX17: Morelos C1 | IY17: 125 | JV17: S | JW17: Particular | JX17: Luis Carlos Reyes | JY17: Individual | JZ17: Lucía Sánchez | KA17: Asistió | KB17: WhereBy 1 | KC17: 450 | KD17: Transf - 1872 | KE17: PAGADO | KP17: S | KQ17: Particular | KR17: Yessica Anahí Rodriguez Palacios | KS17: Individual | KT17: José Arcadio | KU17: Reagendó | KV17: Morelos C1 | KW17: 420
A18: 0.5 | V18: N | W18: Particular | X18: Luis Alberto Reyes Soto | Y18: Individual | Z18: José Arcadio | AA18: Asistió | AB18: Morelos C1 | AC18: 420 | CN18: S | CO18: Particular | CP18: Cecilia Noriega Arévalo | CQ18: Individual 2025 | CR18: José Arcadio | CS18: Asistió | CT18: Morelos C3 | CU18: $400 | CV18: Efectivo | FF18: N | FG18: Particular | FH18: Valeria Bacio Hernández | FI18: Individual | FJ18: Gloria Sarmiento | FK18: Reagendó | FL18: Guanajuato C3 | FM18: $0 | FO18: Ya habia pagado y no se le dio cita, la proxima es de 225 | HX18: S | HY18: Particular | HZ18: Cecilia Noriega Arévalo | IA18: Individual 2025 | IB18: José Arcadio | IC18: Asistió | ID18: Morelos C3 | IE18: $400 | IF18: Transf - 1872 | IG18: COSTO POR ANTIGÜEDAD | KP18: S | KQ18: Particular | KR18: Isaías Hernández Lara | KS18: Medica en salud mental | KT18: Enrique Luna | KU18: Asistió | KV18: Guanajuato C1 | KW18: 850 | KX18: Tarjeta | KY18: PAGADO
A19: 0.5 | CN19: N | CO19: Particular | CP19: Valeria Bacio Hernández | CQ19: Individual | CR19: Benjamin Villagomez | CS19: Incidente | CT19: Guanajuato C2 | CU19: 450 | CV19: Transf - 1872 | CW19: FALTO LIC BENJAMIN | FF19: S | FG19: Particular | FH19: Celic Garcia | FI19: Individual | FJ19: Javier Martínez | FK19: Reagendó | FL19: Guanajuato C2 | FM19: 280 | FO19: Tiene estudio SE | HX19: N | HY19: Particular | HZ19: Valeria Bacio Hernández | IA19: Individual | IB19: Gloria Sarmiento | IC19: Canceló | ID19: Guanajuato C3 | IE19: 450 | IG19: PAGADO | KP19: S | KQ19: Particular | KR19: Pedro Alejandro González Herrera | KS19: Individual | KT19: Javier Martínez | KU19: Asistió | KV19: Guanajuato C2 | KW19: 350 | KX19: Efectivo
A20: 0.5
A21: 0.5
A22: 0.041666667 | V22: N | W22: Particular | X22: Claudia Martínez Duron | Y22: Individual | Z22: Enrique Luna | AA22: Reagendó | AB22: Guanajuato C1 | AD22: Transf - 1872 | AE22: Para el mierc 7 enero a las 5.00 pm | AP22: N | AQ22: Particular | AR22: Javier Bustamante Martinez | AS22: Individual | AT22: Lucía Sánchez | AU22: Asistió | AV22: Guanajuato C1 | AW22: 450 | AX22: Efectivo | CN22: S | CO22: Particular | CP22: Celic Garcia | CQ22: Médica psiquiatrica | CR22: Enrique Luna | CS22: Asistió | CT22: Guanajuato C1 | CU22: 640 | CV22: Transf - 1872 | DH22: N | DI22: Particular | DJ22: Zaid Eliseo López Bautista | DK22: Infantil | DL22: Gloria Sarmiento | DM22: Asistió | DN22: Morelos C1 | DO22: 500 | DP22: Efectivo | EL22: S | EM22: Particular | EN22: Carlos Armando Coutiño Martinez | EO22: Individual | EP22: Lucía Sánchez | EQ22: No llegó | ER22: Guanajuato C1 | ES22: $480 | FF22: S | FG22: Particular | FH22: Mario Zamarripa | FI22: Individual | FJ22: Javier Martínez | FK22: Asistió | FL22: WhereBy 1 | FM22: 420 | FN22: Transf - 1872 | FO22: Px quiso cambiar a virtual | HX22: S | HY22: Particular | HZ22: Miriam Alejandra Argumedo García | IA22: Individual | IB22: Maria Amancio | IC22: Asistió | ID22: Guanajuato C1 | IE22: 450 | IF22: Tarjeta | IG22: Vieme de Terapia de pareja, pasa a individual | IR22: N | IS22: Particular | IT22: Francisca Moreno (del Lic. Siller de Morelos) | IU22: Individual | IV22: Gloria Sarmiento | IW22: Asistió | IX22: Morelos C1 | IY22: $0 | JA22: Primer consulta de cortesía. Caso especial | KP22: R | KQ22: Particular | KR22: María Fernanda Rodríguez Daniel | KS22: Familiar | KT22: José Arcadio | KU22: Canceló | KV22: Morelos C1 | KW22: 400 | KY22: COSTOS AUTORIZADOS: 150 Gloria, 350 Lic Mrtínez, 400 Familar Arcadio
A23: 0.041666667 | X23: Renta espacio (1:30 llegó) | Z23: Enrique Luna | AC23: 125 | AD23: Efectivo | AE23: Pagado | FF23: S | FG23: Particular | FH23: Yessica Anahí Rodriguez Palacios | FI23: Medica en salud mental | FJ23: Enrique Luna | FK23: Asistió | FL23: Guanajuato C3 | FM23: 680 | FN23: Transf - 1872 | FO23: PAGADO | HX23: S | HY23: Particular | HZ23: Juan Diego López Balderas | IA23: Individual 2025 | IB23: Benjamin Villagomez | IC23: Asistió | ID23: Guanajuato C2 | IE23: 380 | IF23: Tarjeta | IG23: 0.5625 | KP23: S | KQ23: Particular | KR23: Rocio Karina Mesquitic Mendoza | KS23: Medica en salud mental | KT23: Enrique Luna | KU23: Asistió | KV23: Guanajuato C1 | KW23: 850 | KX23: Transf - 1872
A24: 0.041666667 | KP24: S | KQ24: Particular | KR24: Ana Sofía Zapata | KS24: Infantil | KT24: Fabiola Fragoso | KU24: Asistió | KV24: Guanajuato C1 | KW24: 350 | KX24: Transf - 1872 | KY24: LA movió la terapeuta de las 11 a la 1
A25: 0.041666667
A26: 0.041666667
A27: 0.083333333 | V27: S | W27: NEAPCO | X27: Joksan Ishbak Cruz Torres | Y27: Individual 2025 | Z27: Daniela Sarmiento | AA27: Asistió | AB27: Morelos C2 | AC27: 0 | AD27: Pase | AZ27: N | BA27: Particular | BB27: Cecilia Lourdes González Carranza | BC27: Individual | BD27: Gloria Sarmiento | BE27: No llegó | BF27: Morelos C1 | BG27: 450 | BT27: N | BU27: NEAPCO | BV27: Karina Segovia Ramírez | BW27: Individual | BX27: Gloria Sarmiento | BY27: Asistió | BZ27: Morelos C1 | CA27: 0 | CB27: Pase | CC27: Es la mamá de la paciente | EL27: S | EM27: Particular | EN27: Daniela Huerta Ovalle | EO27: Individual 2025 | EP27: María de la Luz | EQ27: Asistió | ER27: Guanajuato C1 | ES27: 350 | ET27: Tarjeta | FZ27: N | GA27: Particular | GB27: Sofía Marinette Segura Viera | GC27: Infantil | GD27: Gloria Sarmiento | GE27: Asistió | GF27: Morelos C1 | GG27: 500 | GH27: Efectivo | HD27: S | HE27: Particular | HF27: Daniela Huerta Ovalle | HG27: Individual 2025 | HH27: María de la Luz | HI27: Incidente | HJ27: Guanajuato C1 | HK27: 350 | HM27: Canceló la Terapeuta | HN27: S | HO27: NEAPCO | HP27: Karina Segovia Ramírez (su mamá es la paciente) | HQ27: Individual | HR27: Gloria Sarmiento | HS27: Asistió | HT27: Morelos C1 | HU27: 0 | HV27: Pase | HX27: S | HY27: NEAPCO | HZ27: Derek Daniel Salas | IA27: Individual | IB27: Daniela Sarmiento | IC27: Confirmó | ID27: WhereBy 1 | IE27: 0 | IF27: Pase | IR27: S | IS27: Particular | IT27: Sofía Marinette Segura Viera | IU27: Infantil | IV27: Gloria Sarmiento | IW27: Asistió | IX27: Morelos C1 | IY27: 500 | IZ27: Efectivo | JL27: S | JM27: Particular | JN27: Rodrigo Alejandro Vázquez Cázares | JO27: Individual | JP27: Gloria Sarmiento | JQ27: Asistió | JR27: Morelos C1 | JS27: 675 | JT27: Transf - 1872 | JU27: Faltó a su anterior cita, el que se presentó fue su hermano Ángel Jaziel | JV27: S | JW27: Particular | JX27: Daniela Huerta Ovalle | JY27: Individual 2025 | JZ27: María de la Luz | KA27: Asistió | KB27: Guanajuato C1 | KC27: 350 | KD27: Tarjeta | KF27: S | KG27: NEAPCO | KH27: Karina Segovia Ramírez (mamá) | KI27: Individual | KJ27: Gloria Sarmiento | KK27: Confirmó | KL27: Morelos C1 | KM27: 0 | KN27: Pase | KP27: N | KQ27: Particular | KR27: María Cristina Domínguez | KS27: Individual | KT27: Daniela Sarmiento | KU27: No confirmó | KV27: Morelos C2 | KW27: 450 | KY27: PASAR SINTOMAS A LA LIC DANIEL
A28: 0.083333333 | BJ28: S | BK28: Particular | BL28: Carlos Joel Santos Nuncio | BM28: Individual | BN28: Gloria Sarmiento | BO28: Asistió | BP28: Morelos C1 | BQ28: 420 | BR28: Efectivo | BT28: S | BU28: Particular | BV28: Daniela Huerta Ovalle | BW28: Individual 2025 | BX28: María de la Luz | BY28: Asistió | BZ28: Guanajuato C1 | CA28: 0 | CB28: Gratuito | EL28: N | EM28: NEAPCO | EN28: Karina Segovia Ramírez (su mamá es la paciente) | EO28: Individual | EP28: Gloria Sarmiento | EQ28: Asistió | ER28: Morelos C1 | ES28: 0 | ET28: Pase | EU28: Preguntar si la mama puede usar el pase de empleada de neapco | JV28: N | JW28: INSUNTE | JX28: Alondra Marisol García Medina | JY28: Individual | JZ28: Lucía Sánchez | KA28: Asistió | KB28: Guanajuato C2 | KC28: 300 | KD28: Efectivo | KR28: TENTATIVO KARINA PARA LIC FABIOLA
A29: 0.083333333 | CN29: N | CO29: Particular | CP29: Daniela Rafael Sifuentes | CQ29: Individual | CR29: Benjamin Villagomez | CS29: Confirmó | CT29: Guanajuato C1 | CU29: 450 | JV29: S | JW29: Particular | JX29: Carlos Arturo García Limón | JY29: Individual | JZ29: Gloria Sarmiento | KA29: Asistió | KB29: Morelos C1 | KC29: 340 | KD29: Efectivo
A30: 0.083333333
A31: 0.083333333
A32: 0.125 | V32: S | W32: Particular | X32: Isaías Hernández Lara | Y32: Individual 2025 | Z32: Daniela Sarmiento | AA32: Asistió | AB32: Morelos C1 | AC32: $420 | AD32: Efectivo | AE32: Se hizo 50% descuento ($210) | AP32: S | AQ32: Particular | AR32: Ricardo Guadalupe López Ramos | AS32: Individual 2025 | AT32: Lucía Sánchez | AU32: Asistió | AV32: Guanajuato C2 | AW32: 420 | AX32: Tarjeta | AZ32: S | BA32: INSUNTE | BB32: Alan Mitsael Flores Vazquez | BC32: Individual 2025 | BD32: Maricela Sena | BE32: Reagendó | BF32: Guanajuato C1 | BG32: 300 | BI32: Para el viernes 9 enero a las 3:00 | BJ32: S | BK32: Particular | BL32: Eva Isabel Valerdi Cortés | BM32: Infantil | BN32: Gloria Sarmiento | BO32: Asistió | BP32: Morelos C2 | BQ32: 360 | BR32: Efectivo | CD32: S | CE32: INSUNTE | CF32: Alan Mitsael Flores Vazquez | CG32: Individual | CH32: Maricela Sena | CI32: Asistió | CJ32: Guanajuato C1 | CK32: 300 | CL32: Tarjeta | CN32: N | CO32: Particular | CP32: Isabella Jocelin Borja Sifuentes | CQ32: Infantil | CR32: Fabiola Fragoso | CT32: Guanajuato C2 | CU32: 420 | EL32: S | EM32: Particular | EN32: Carlos Arturo García Limón | EO32: Individual | EP32: Gloria Sarmiento | EQ32: Asistió | ER32: Morelos C1 | ES32: 420 | ET32: Efectivo | EU32: Dice en la bitácora que él mandará mensaje nuevamente | FF32: S | FG32: Particular | FH32: Isaías Hernández Lara | FI32: Individual 2025 | FJ32: Daniela Sarmiento | FL32: WhereBy 1 | FM32: $420 | FN32: Transf - 1872 | FO32: PAGADO canceló por enfermedad | FZ32: S | GA32: Particular | GB32: Ricardo Guadalupe López Ramos | GC32: Individual 2025 | GD32: Lucía Sánchez | GE32: Asistió | GF32: Guanajuato C2 | GG32: 420 | GH32: Tarjeta | GT32: S | GU32: Particular | GV32: Eva Isabel Valerdi Cortés | GW32: Infantil | GX32: Gloria Sarmiento | GY32: Reagendó | GZ32: Morelos C2 | HA32: 300 | HC32: PARA MIERC 28 ENERO POR ENFERMEDAD DE LA NIÑA | HN32: S | HO32: Particular | HP32: Fernanda Diaz Ortega | HQ32: Individual | HR32: Maricela Sena | HS32: Asistió | HT32: Guanajuato C1 | HU32: 350 | HV32: Tarjeta | HX32: S | HY32: Particular | HZ32: Dora Alicia Martinez | IA32: Individual 2025 | IB32: Javier Martínez | ID32: Guanajuato C2 | IE32: 0 | IF32: Gratuito | IG32: PENDIENTE PASAR HORARIO | IR32: S | IS32: GIASA | IT32: Marco Antonio Hinojosa Hernández | IU32: Individual | IV32: Maricela Sena | IW32: No llegó | IX32: Guanajuato C1 | IY32: 0 | IZ32: Pase | JB32: S | JC32: NEAPCO | JD32: Fe Garay | JE32: Individual | JF32: Gloria Sarmiento | JG32: Asistió | JH32: Morelos C1 | JJ32: Pase | JL32: S | JM32: Particular | JN32: Eva Isabel Valerdi Cortés | JO32: Infantil | JP32: Gloria Sarmiento | JQ32: Asistió | JR32: Morelos C1 | JS32: 300 | JT32: Efectivo | JU32: PARA MIERC 28 ENERO POR ENFERMEDAD DE LA NIÑA | KH32: RENTA ALISSON BERMAN | KJ32: Alisson Berman | KK32: Confirmó | KL32: Guanajuato C1 | KM32: 125 | KP32: S | KQ32: Particular | KR32: Isaías Hernández Lara | KS32: Individual 2025 | KT32: Daniela Sarmiento | KU32: Asistió | KV32: Morelos C1 | KW32: $420 | KX32: Transf - 1872 | KY32: PAGADO canceló por enfermedad la lic la cita pasada
A33: 0.125 | V33: N | W33: Particular | X33: Mario Alberto Martinez Lozano | Y33: Individual | Z33: Enrique Luna | AA33: No llegó | AB33: Guanajuato C1 | AC33: 850 | CD33: S | CE33: NEAPCO | CF33: Fe Garay | CG33: Individual 2025 | CH33: Gloria Sarmiento | CI33: Asistió | CJ33: Morelos C1 | CK33: 0 | CL33: Pase | CN33: S | CO33: Particular | CP33: Samuel y Adin Valles | CQ33: Familiar | CR33: Daniela Sarmiento | CS33: Confirmó | CT33: Morelos C1 | CU33: 550 | EV33: S | EW33: NEAPCO | EX33: Fe Garay | EY33: Individual 2025 | EZ33: Gloria Sarmiento | FA33: No confirmó | FB33: Morelos C1 | FC33: 0 | FD33: Pase | FE33: Dice en bitácora que ellá volverá a mandar mensaje | FF33: S | FG33: Particular | FH33: Valeria Janeth Márquez Muñiz | FI33: Medica en salud mental | FJ33: Enrique Luna | FK33: Asistió | FL33: Guanajuato C1 | FM33: 850 | FN33: Transf - 1872 | FO33: Cambio de hora ,"que sea seguro" dice Px. | HX33: N | HY33: Particular | HZ33: José Francisco Rodríguez Pérez | IA33: Individual | IB33: Daniela Sarmiento | IC33: Incidente | ID33: Morelos C1 | IE33: 450 | IG33: ENVIAR ANTECEDENTE QUE MANDÓ LA PX | KF33: S | KG33: Particular | KH33: Fernanda Diaz Ortega | KI33: Individual | KJ33: Maricela Sena | KL33: Guanajuato C1 | KM33: 350 | KO33: AGENDÓ EN ESCRITORIO DE RECEPCIÓN ALICIA PARA LAS DOS 13 DE FEB y ALICIA CON DR 14 FEB | KR33: RENTA ESPACIO DR LUNA | KT33: Enrique Luna | KU33: Confirmó | KV33: Guanajuato C1
A34: 0.125 | CP34: RENTA DE ESPACIO | CR34: Enrique Luna | CS34: Confirmó | CU34: 125 | CW34: PROBABLE CHRISTIAN BARRIOS
A35: 0.125
A36: 0.125
A37: 0.16666667 | L37: N | M37: Particular | N37: Nayelli Monserrat Reyna De Leon | O37: Individual | P37: Gloria Sarmiento | Q37: Asistió | R37: Morelos C1 | S37: 450 | T37: Efectivo | V37: S | W37: NEAPCO | X37: Derek Daniel Salas | Y37: Individual | Z37: Daniela Sarmiento | AA37: Asistió | AB37: Morelos C1 | AC37: 0 | AD37: Pase | AP37: S | AQ37: Particular | AR37: Anayansi Rincón Patiño | AS37: Individual | AT37: Javier Martínez | AU37: Asistió | AV37: Guanajuato C1 | AW37: 420 | AX37: Efectivo | BJ37: S | BK37: Particular | BL37: Ana Sofia Zapata | BM37: Consulta psiquiatrica | BN37: Enrique Luna | BO37: Asistió | BP37: Guanajuato C1 | BQ37: 700 | BR37: Tarjeta | BT37: S | BU37: Particular | BV37: Jonas Alejandro Morales | BW37: Individual 2025 | BX37: José Arcadio | BY37: Confirmó | BZ37: ZOOM C1 | CA37: $420 | CD37: S | CE37: Particular | CF37: Cristian Gómez | CG37: Individual 2025 | CH37: Maricela Sena | CI37: No confirmó | CJ37: Guanajuato C1 | CK37: 420 | CN37: N | CO37: Particular | CP37: Jhonatan Alexander de la Peña Sandate | CQ37: Individual | CR37: Daniela Sarmiento | CS37: No llegó | CT37: Morelos C1 | CU37: 450 | CV37: Transf - 1872 | DH37: N | DI37: Particular | DJ37: Maria Fernanda Rodriguez Daniel | DL37: Gloria Sarmiento | DM37: Asistió | DN37: Morelos C1 | DO37: 150 | DP37: Efectivo | DQ37: Tiene costos autorizados por whatsapp | EB37: S | EC37: Particular | ED37: Devany Alejandra Acosta Reyes | EE37: Consulta psiquiatrica | EF37: Enrique Luna | EG37: Asistió | EH37: Guanajuato C1 | EI37: 850 | EJ37: Efectivo | EL37: S | EM37: Particular | EN37: Jorge Arturo Rodríguez Perales | EO37: Medica en salud mental | EP37: Enrique Luna | EQ37: Confirmó | ER37: Guanajuato C1 | ES37: $680 | EU37: Recuperación | EV37: N | EW37: Particular | EX37: Angelica Berenice Dogart Urbina | EY37: Individual | EZ37: Maricela Sena | FA37: No confirmó | FB37: Guanajuato C1 | FC37: 450 | FF37: S | FG37: NEAPCO | FH37: Derek Daniel Salas | FI37: Individual | FJ37: Daniela Sarmiento | FK37: Incidente | FL37: WhereBy 1 | FM37: 0 | FN37: Pase | FO37: Se enfermó la Lic Daniela, reagenda Px para el sig. sabado virtual | FZ37: N | GA37: Particular | GB37: Ángel Gaciel Vázquez Cázares | GC37: Individual | GD37: Gloria Sarmiento | GE37: Asistió | GF37: Morelos C1 | GG37: 450 | GH37: Efectivo | GI37: MAndar confirmacion 8444941798 | GJ37: N | GK37: Particular | GL37: Dante Jaziel Armas de la Peña | GM37: Infantil | GN37: Gloria Sarmiento | GO37: Asistió | GP37: Morelos C2 | GQ37: $460 | GR37: Efectivo | GS37: paga 460 porque se le debieron 20 de cambio | GT37: S | GU37: Particular | GV37: Devany Alejandra Acosta Reyes | GW37: Individual | GX37: Lucía Sánchez | GY37: Asistió | GZ37: Guanajuato C1 | HA37: 420 | HB37: Efectivo | HC37: Me lo pasó por whats Valery | HN37: S | HO37: INSUNTE | HP37: Alan Mitsael Flores Vazquez | HQ37: Individual | HR37: Maricela Sena | HS37: Asistió | HT37: Guanajuato C1 | HU37: 300 | HV37: Tarjeta | HX37: N | HY37: Particular | HZ37: María Fernanda García Rodríguez y Carlos Aurelio Duarte Trejo | IA37: Pareja | IB37: Daniela Sarmiento | IC37: Confirmó | ID37: Morelos C1 | IE37: 600 | IR37: S | IS37: Particular | IT37: Ángel Jaciel Vázquez Cázares | IU37: Individual | IV37: Gloria Sarmiento | IW37: Asistió | IX37: Morelos C1 | IY37: 450 | IZ37: Transf - 1872 | JA37: MAndar confirmacion 8444941798 | JB37: S | JC37: Particular | JD37: Dante Jaziel Armas de la Peña | JE37: Infantil | JF37: Gloria Sarmiento | JG37: Asistió | JH37: Morelos C2 | JI37: 480 | JK37: PENDIENTE COMPROBANTE PAGO | JL37: S | JM37: Particular | JN37: María de la Luz Ruiz Armendáriz | JO37: Individual | JP37: Lucía Sánchez | JQ37: Asistió | JR37: Guanajuato C1 | JS37: 450 | JT37: Transf - 1872 | JV37: N | JW37: Dorothea | JX37: Melissa Estefanía Gonzalez Ortiz | JY37: Individual | JZ37: Gloria Sarmiento | KA37: No confirmó | KB37: Morelos C1 | KC37: 350 | KF37: S | KG37: INSUNTE | KH37: Alan Mitsael Flores Vazquez | KI37: Individual | KJ37: Maricela Sena | KK37: Asistió | KL37: Guanajuato C1 | KM37: 300 | KN37: Transf - 1872 | KP37: S | KQ37: NEAPCO | KR37: Derek Daniel Salas | KS37: Individual | KT37: Daniela Sarmiento | KU37: Asistió | KV37: WhereBy 1 | KW37: 0 | KX37: Pase
A38: 0.16666667 | BJ38: S | BK38: Particular | BL38: María de Lourdes Martinez Reyna | BM38: Individual 2025 | BN38: Rosy Macias | BP38: Morelos C1 | BQ38: 350 | BR38: Efectivo | BS38: Se omitió día que no iba a laborar la terapeuta y se agendó a paciente | BT38: S | BU38: Particular | BV38: Frida Sofía Sánchez Sánchez | BW38: Individual | BX38: Lucía Sánchez | BZ38: Guanajuato C1 | CA38: 420 | CD38: N | CE38: Particular | CF38: Juan Antonio Izquierdo Treviño | CG38: Individual | CH38: Maricela Sena | CI38: Asistió | CJ38: Guanajuato C1 | CK38: 450 | CL38: Efectivo | CN38: S | CO38: NEAPCO | CP38: Julio Alejandro Moreno Moncada | CQ38: Médica psiquiatrica | CR38: Enrique Luna | CS38: Confirmó | CT38: Guanajuato C1 | CU38: 0 | CV38: Pase | DR38: N | DS38: Particular | DT38: Dante Jaziel Armas de la Peña | DU38: Infantil | DV38: Gloria Sarmiento | DW38: Asistió | DX38: Morelos C2 | DY38: 480 | DZ38: Efectivo | EA38: Nuevo ingreso; se respetó costo que vio en publicación | EB38: N | EC38: Particular | ED38: María de la Luz Ruiz Armendáriz | EE38: Individual | EF38: Lucía Sánchez | EG38: Asistió | EH38: Guanajuato C2 | EI38: 450 | EJ38: Transf - 1872 | EK38: PAGADO | EL38: S | EM38: Particular | EN38: Eva Isabel Valerdi Cortés | EO38: Infantil | EP38: Gloria Sarmiento | EQ38: Asistió | ER38: Morelos C2 | ES38: 300 | ET38: Efectivo | EU38: Canceló mierc 13 Lic por contratiempo/ Autorizan estudio SE | FF38: S | FG38: Particular | FH38: Luis Alberto Reyes Soto | FI38: Medica en salud mental | FJ38: Enrique Luna | FK38: Canceló | FL38: Guanajuato C1 | FM38: 850 | GT38: S | GU38: Particular | GV38: Vivían Yoselin Valdez Sifuentes | GW38: Individual | GX38: Gloria Sarmiento | GY38: Asistió | GZ38: Morelos C1 | HA38: 300 | HC38: Referida de la Fundación Érika/ La lic canceló el 13 por contratiempo | HN38: S | HO38: Particular | HP38: Carlos Arturo García Limón | HQ38: Individual | HR38: Gloria Sarmiento | HS38: Asistió | HT38: Morelos C1 | HU38: 340 | HV38: Transf - 1872 | HW38: REVISAR COSTO | HZ38: RENTA ESPACIO ALISSON BERMEA | IC38: Confirmó | ID38: Guanajuato C1 | IE38: 125 | JB38: S | JC38: Particular | JD38: Dora Alicia Martinez Juarez | JE38: Individual | JF38: Javier Martínez | JG38: Confirmó | JH38: Guanajuato C1 | JI38: 0 | JJ38: Pase | JL38: N | JM38: Particular | JN38: Raymundo Damian Tovar García | JO38: Infantil | JP38: Gloria Sarmiento | JQ38: Reagendó | JR38: Morelos C1 | JS38: 500 | KF38: N | KG38: Particular | KH38: María Teresa Agin Hernández | KI38: Individual | KJ38: Lucía Sánchez | KK38: No confirmó | KL38: Guanajuato C2 | KM38: 450 | KR38: RENTA ESPACIO LIC ALISSON BERMAN | KT38: Alisson Berman | KU38: Confirmó | KV38: Guanajuato C1
A39: 0.16666667 | BJ39: S | BK39: Particular | BL39: Alberto de Jesús Ramos Barrientos | BM39: Individual 2025 | BN39: Gloria Sarmiento | BO39: Confirmó | BP39: Morelos C2 | BQ39: 340 | BT39: S | BU39: Particular | BV39: Maria de Lourdes Martínez | BW39: Individual | BX39: Rosy Macias | BY39: Asistió | BZ39: Morelos C1 | CA39: 350 | CB39: Transf - 1872 | JL39: S | JM39: Fundación Erika | JN39: Vivían Yoselin Valdez Sifuentes | JO39: Individual | JP39: Gloria Sarmiento | JQ39: No confirmó | JR39: Morelos C1 | JS39: 300
A40: 0.16666667 | BJ40: S | BK40: Particular | BL40: Devany Alejandra Acosta Reyes | BM40: Individual | BN40: Lucía Sánchez | BO40: Reagendó | BP40: Guanajuato C2 | BQ40: 420 | BS40: Para el 21 de enero a las 4 | BV40: RENTA DE ESPACIO | BX40: Maria Amancio | BZ40: Guanajuato C2 | CA40: 125
A41: 0.16666667
A42: 0.20833333 | L42: S | M42: Particular | N42: Damian Berlanga Hidrogo | O42: Pareja | P42: José Arcadio | Q42: Asistió | R42: Colinas C1 | S42: 500 | T42: Transf - 1872 | AZ42: S | BA42: Particular | BB42: Oscar Jesus Sanchez Muñoz | BC42: Individual 2025 | BD42: José Arcadio | BE42: Reagendó | BF42: Colinas C1 | BG42: $420 | BI42: 5:30 se pasó al lunes 12 a las 6:30 pm | BJ42: S | BK42: Particular | BL42: Guadalupe Alejandra Aldaco Moya | BM42: Evaluación neuropsicológica (Sesión) | BN42: Javier Martínez | BO42: No confirmó | BP42: Guanajuato C3 | BQ42: 420 | BT42: S | BU42: Particular | BV42: Carlos Martinez | BW42: Individual | BX42: José Arcadio | BZ42: Morelos C3 | CA42: 420 | CC42: 0.22916667 | CD42: S | CE42: Particular | CF42: Braulio Raziel Rico Cervantes | CG42: Individual 2025 | CH42: Gloria Sarmiento | CI42: Asistió | CJ42: Morelos C1 | CK42: 420 | CM42: A la espera de que mande comprobante transfer | CP42: RENTA DE ESPACIO | CR42: Enrique Luna | CS42: Confirmó | CU42: 125 | DR42: N | DS42: Particular | DT42: Carlos Zúñiga | DU42: Individual | DV42: Rosy Macias | DW42: Asistió | DX42: Morelos C1 | DY42: 450 | DZ42: Transf - 1872 | EA42: Tienen cita como pareja el proximo 17 de enero con Lic. Arcadio | EB42: S | EC42: Particular | ED42: Victoria Aldaco Martínez | EE42: Pareja | EF42: Rosy Macias | EG42: Reagendó | EH42: Morelos C2 | EI42: $520 | EL42: N | EM42: Particular | EN42: Imelda Noemi Rosales Tijerina | EO42: Medica en salud mental | EP42: Enrique Luna | EQ42: Confirmó | ER42: Guanajuato C1 | ES42: 750 | EU42: Tiene estudio | FF42: S | FG42: Particular | FH42: Felipe de Jesús Carreón López | FI42: Individual 2025 | FJ42: Fabiola Fragoso | FK42: Canceló | FL42: Guanajuato C2 | FM42: 420 | FZ42: S | GA42: Particular | GB42: Damian Berlanga Hidrogo | GC42: Pareja | GD42: José Arcadio | GE42: Confirmó | GF42: Morelos C1 | GG42: 550 | GI42: 5:30 Ya pagó adeudos, pendiente esta | GJ42: S | GK42: Particular | GL42: Jonás Alejandro Morales | GM42: Individual | GN42: José Arcadio | GO42: Asistió | GP42: Colinas C1 | GQ42: 420 | GR42: Transf - 1872 | GS42: 0.22916667 | GT42: S | GU42: Particular | GV42: Carlos Miguel Fernández Reyna | GW42: Infantil | GX42: Esmeralda Colunga | GY42: Asistió | GZ42: Morelos C1 | HA42: $500 | HB42: Transf - 1872 | HC42: PAGADO | HD42: S | HE42: Particular | HF42: Jonás Alejandro Morales | HG42: Medica en salud mental | HH42: Enrique Luna | HI42: Asistió | HJ42: Guanajuato C1 | HK42: 850 | HL42: Transf - 1872 | HM42: Px también de Lic. Arcadio | HN42: S | HO42: Particular | HP42: Daniel Emiliano Martínez González | HQ42: Individual | HR42: Gloria Sarmiento | HS42: Asistió | HT42: Morelos C1 | HU42: 420 | HV42: Efectivo | HX42: S | HY42: Particular | HZ42: Isaías Hernández Lara | IA42: Individual 2025 | IB42: Daniela Sarmiento | IC42: Confirmó | ID42: Morelos C1 | IE42: $420 | IF42: Transf - 1872 | IG42: PAGADO canceló por enfermedad la lic la cita pasada | IR42: S | IS42: Particular | IT42: Damián Berlanga Hidrogo | IU42: Pareja | IV42: José Arcadio | IW42: Confirmó | IX42: Colinas C1 | IY42: 550 | JA42: 0.22916667 | JB42: S | JC42: Particular | JD42: Valeria Janeth Márquez Muñiz | JE42: Individual | JF42: José Arcadio | JG42: Reagendó | JH42: Colinas C1 | JI42: 420 | JK42: 0.22916667 | JL42: S | JM42: Particular | JN42: Jonás Alejandro Morales | JO42: Individual | JP42: José Arcadio | JQ42: Asistió | JR42: Colinas C1 | JS42: 420 | JT42: Transf - 1872 | JU42: 0.22916667 | JV42: S | JW42: Particular | JX42: Rocio Karina Mesquitic Mendoza | JY42: Individual | JZ42: José Arcadio | KA42: Asistió | KB42: Morelos C1 | KC42: 420 | KD42: Efectivo | KE42: 5:30 SE LE DEBEN 80 DE CAMBIO SE VA A REFERIR PARA EVALUACIÓN CON JAVIER MTZ | KF42: S | KG42: Particular | KH42: Daniel Emiliano Martínez González | KI42: Individual | KJ42: Gloria Sarmiento | KK42: Asistió | KL42: Morelos C1 | KM42: 420 | KN42: Efectivo | KP42: S | KQ42: Particular | KR42: Ángel Alejandro Robles Peralta | KS42: Medica en salud mental | KT42: Enrique Luna | KU42: Reagendó | KV42: Guanajuato C1 | KW42: 850 | KY42: CHECAR COSTO DE INGRESADO DR
A43: 0.20833333 | L43: S | M43: Particular | N43: Braulio Raziel Rico Cervantes | O43: Individual 2025 | P43: Gloria Sarmiento | Q43: Asistió | R43: Morelos C1 | S43: 420 | BJ43: N | BK43: Particular | BL43: Claudia Martínez Duron | BN43: Enrique Luna | BO43: Asistió | BP43: Guanajuato C1 | BQ43: 450 | BR43: Efectivo | BS43: Se le corrigió costo por whats pero no contestó | CD43: N | CE43: Particular | CF43: Fernanda Gloria Pérez | CG43: Individual | CH43: Rosy Macias | CI43: No llegó | CJ43: Morelos C1 | CK43: 450 | DH43: N | DI43: Particular | DJ43: Olivia del Rosario Malacara Mata | DK43: Individual | DL43: Gloria Sarmiento | DM43: Reagendó | DN43: Morelos C1 | DO43: 450 | DP43: Efectivo | DQ43: La Lic. Gloria pidió pasarla para el día siguiente a las 6:00 | DR43: N | DS43: Particular | DT43: Carmen Montiel | DU43: Individual | DV43: Gloria Sarmiento | DW43: Asistió | DX43: Morelos C1 | DY43: 450 | DZ43: Efectivo | EA43: Tienen cita como pareja el proximo 17 de enero con Lic. Arcadio | EB43: S | EC43: Particular | ED43: Hugo Torres | EE43: Consulta psiquiatrica | EF43: Enrique Luna | EG43: Asistió | EH43: Guanajuato C1 | EI43: 850 | EJ43: Tarjeta | EL43: N | EM43: Particular | EN43: Vivían Yoselin Valdez Sifuentes | EO43: Individual | EP43: Gloria Sarmiento | EQ43: Asistió | ER43: Morelos C1 | ES43: 300 | ET43: Efectivo | EU43: Referida de la Fundación Érika/ La lic canceló el 13 por contratiempo | EV43: S | EW43: Particular | EX43: Braulio Raziel Rico Cervantes | EY43: Individual 2025 | EZ43: Gloria Sarmiento | FA43: No confirmó | FB43: Morelos C1 | FC43: 420 | FE43: A la espera de que pase comprobante de la consulta del 9 de enero | FF43: S | FG43: Particular | FH43: Erik José Alfredo Medina Saucedo | FI43: Medica en salud mental | FJ43: Enrique Luna | FK43: Asistió | FL43: Guanajuato C1 | FM43: 850 | FN43: Efectivo | FZ43: N | GA43: Particular | GB43: Rodrigo Alejandro Vázquez Cázares | GC43: Individual | GD43: Gloria Sarmiento | GE43: Asistió | GF43: Morelos C2 | GG43: 450 | GH43: Efectivo | GI43: MAndar confirmacion 8444941798 | GJ43: S | GK43: Particular | GL43: Carlos Zúñiga | GM43: Individual | GN43: Rosy Macias | GO43: Canceló | GP43: Morelos C1 | GQ43: 450 | GS43: Paciente dice que él se comunica nuevamente | GT43: S | GU43: Particular | GV43: María de la Luz Ruiz Armendáriz | GW43: Individual | GX43: Lucía Sánchez | GY43: Asistió | GZ43: Guanajuato C1 | HA43: 450 | HB43: Transf - 1872 | HC43: PAGADO | HD43: N | HE43: Particular | HF43: Devany Araceli Domínguez Aguilar | HG43: Individual | HH43: José Arcadio | HI43: Asistió | HJ43: Morelos C1 | HK43: 450 | HL43: Efectivo | HM43: 0.22916667 | IR43: S | IS43: Particular | IT43: Angel Daniel Garcia Ruvalcaba T Alondra E. | IU43: Individual | IV43: Javier Martínez | IW43: No llegó | IX43: Guanajuato C3 | IY43: 420 | JA43: Se le agendará sólo sobre multa de 200 pesos | JB43: S | JC43: Particular | JD43: Maria Fernanda Rodriguez Daniel y FERNANDO JOSÉ | JF43: Gloria Sarmiento | JG43: Canceló | JH43: Morelos C1 | JI43: 150 | JK43: Tiene costos autorizados por whatsapp | JL43: S | JM43: Particular | JN43: Devany Alejandra Acosta Reyes | JO43: Individual | JP43: Lucía Sánchez | JQ43: No confirmó | JR43: Guanajuato C1 | JS43: 420 | KP43: S | KQ43: NEAPCO | KR43: Joksan Ishbak Cruz Torres | KS43: Individual | KT43: Daniela Sarmiento | KU43: Asistió | KV43: Morelos C1 | KW43: 0 | KX43: Pase | KY43: OFRECERLE ESPACIO DON DR LUNA
A44: 0.20833333 | BJ44: S | BK44: Particular | BL44: Damian Berlanga Hidrogo | BM44: Pareja | BN44: José Arcadio | BO44: Reagendó | BP44: Colinas C1 | BQ44: 500 | BS44: 5:30 reagendo para el lunes 12 a las 5:30 | DH44: S | DI44: Particular | DJ44: Damian Berlanga Hidrogo | DK44: Pareja | DL44: José Arcadio | DM44: Asistió | DN44: Colinas C1 | DO44: 500 | DQ44: 0.22916667 | DR44: S | DS44: Particular | DT44: Jonás Alejandro Morales | DU44: Individual | DV44: José Arcadio | DW44: Asistió | DX44: Colinas C1 | DY44: 420 | DZ44: Transf - 1872 | EA44: 0.22916667 | EB44: N | EC44: Particular | ED44: Blanca Araceli Zamora Soto | EE44: Individual | EF44: José Arcadio | EG44: Asistió | EH44: Colinas C1 | EI44: 450 | EJ44: Transf - 1872 | EK44: 0.22916667 | EX44: NO AGENDAR A LAS 5:00 A LIC MARISELA | FZ44: S | GA44: Particular | GB44: Celic Garcia | GC44: Individual | GD44: Javier Martínez | GE44: Confirmó | GF44: Guanajuato C3 | GG44: 280 | GI44: Tiene estudio SE | GJ44: S | GK44: Particular | GL44: Carlos Miguel Fernández Reina | GM44: Infantil | GN44: Esmeralda Colunga | GO44: Confirmó | GP44: Morelos C2 | GQ44: 500 | HF44: RENTA ALISSON BERMEA | HI44: Incidente | HJ44: Guanajuato C2 | HK44: 125 | IR44: S | IS44: Particular | IT44: Rodrigo Alejandro Vázquez Cázares | IU44: Individual | IV44: Gloria Sarmiento | IW44: No llegó | IX44: Morelos C2 | IY44: 450 | JA44: MAndar confirmacion 8444941798 | JB44: S | JC44: Particular | JD44: Carlos Miguel Fernandez Reyna | JE44: Infantil | JF44: Esmeralda Colunga | JG44: Reagendó | JH44: Morelos C2 | JI44: 500 | JK44: Para el prox martes | JL44: R | JM44: Particular | JN44: Julio Cesar Medellin | JO44: Individual | JP44: Gloria Sarmiento | JQ44: Asistió | JR44: Morelos C1 | JS44: 300 | JT44: Efectivo | JU44: REFERIDO DE LA FUNDACION ERIKA
A45: 0.20833333 | DR45: S | DS45: Particular | DT45: Jonathan Barrera | DU45: Individual 2025 | DV45: Esmeralda Colunga | DW45: Asistió | DX45: Morelos C2 | DY45: $200 | DZ45: Efectivo | JB45: S | JC45: Particular | JD45: Jonathan Barrera | JE45: Individual 2025 | JF45: Esmeralda Colunga | JG45: Reagendó | JH45: Morelos C2 | JI45: $200 | JK45: A la espera de respuesta por horario
A46: 0.20833333
A47: 0.25 | AP47: S | AQ47: Particular | AR47: Omar Guadalupe Contreras Sánchez | AS47: Individual 2025 | AT47: Lucía Sánchez | AU47: Reagendó | AV47: Guanajuato C1 | AW47: 420 | AY47: Para el lunes 12 a las 6:00 pm | BJ47: S | BK47: Cáritas de Saltillo | BL47: Vladimir Ilich García Santana | BM47: Individual 2025 | BN47: Enrique Luna | BO47: Canceló | BP47: Guanajuato C1 | BQ47: 0 | BT47: S | BU47: Particular | BV47: Hugo Torres | BW47: Individual 2025 | BX47: José Arcadio | BY47: Asistió | BZ47: Morelos C3 | CA47: 500 | CB47: Transf - 1872 | CC47: 0.27083333 | DH47: S | DI47: GIASA | DJ47: Antonio de Jesus Jara Esquivel | DK47: Consulta nutricional | DL47: Carolina Gonzalez | DM47: Reagendó | DN47: Guanajuato C1 | DO47: 0 | DP47: Pase | DQ47: Pide fecha para la próxima semana | DR47: S | DS47: Particular | DT47: Magaly Fernanda Martinez Martinez | DU47: Individual | DV47: Esmeralda Colunga | DW47: Confirmó | DX47: Morelos C1 | DY47: 360 | EB47: S | EC47: Particular | ED47: Evelyn Estefania Rios Vasquez | EE47: Individual 2025 | EF47: Rosy Macias | EG47: Asistió | EH47: Morelos C1 | EI47: $420 | EK47: Que no pagó porque es "colaborador" puso la lic en bitacora | EN47: Pendiente la hora para el | EV47: N | EW47: Particular | EX47: Laura Arias | EY47: Individual 2025 | EZ47: Maricela Sena | FA47: Canceló | FB47: Guanajuato C1 | FC47: 450 | FE47: OFreció a Juan Antonio Izquierdo, a la espera de respuesta | FZ47: S | GA47: GIASA | GB47: Antonio de Jesus Jara Esquivel | GC47: Consulta nutricional | GD47: Carolina Gonzalez | GE47: Canceló | GF47: Guanajuato C1 | GG47: 0 | GH47: Pase | GI47: SEGUNDA VEZ QUE REAGENDA Y/O CANCELA | GJ47: S | GK47: Particular | GL47: Oscar Jesús Sánchez Muñoz | GM47: Individual | GN47: José Arcadio | GO47: Reagendó | GP47: Colinas C1 | GQ47: 420 | GS47: 6:30 se tomó fecha de bitácora, pero dice paciente que le tocaba dentro de 15 días, se movió al martes 27 | GT47: N | GU47: Particular | GV47: Blanca Araceli Zamora Soto | GW47: Individual | GX47: José Arcadio | GY47: Asistió | GZ47: Colinas C1 | HA47: 450 | HB47: Transf - 1872 | HC47: 0.27083333 | HD47: S | HE47: Particular | HF47: Hugo Torres | HG47: Individual 2025 | HH47: José Arcadio | HI47: Asistió | HJ47: Morelos C1 | HK47: 500 | HM47: 6:30 CHECAR COSTO 500 | HN47: S | HO47: Particular | HP47: Maria de Lourdes Martínez | HQ47: Individual | HR47: Rosy Macias | HS47: Reagendó | HT47: Morelos C1 | HU47: 350 | HW47: REAGENDÓ PARA LA PROXIMA SEMANA | HX47: S | HY47: Particular | HZ47: Sofía Holguín Muñiz | IA47: Individual 2025 | IB47: Fabiola Fragoso | IC47: Reagendó | ID47: Guanajuato C1 | IE47: 420 | IG47: debe $20 pesos | IR47: S | IS47: Particular | IT47: Juan de Dios Enriquez | IU47: Individual 2025 | IV47: Daniel Salazar | IW47: Confirmó | IX47: Morelos C1 | IY47: $420 | JB47: S | JC47: Particular | JD47: Maria Fernanda Rodriguez Daniel Y FERNANDO JOSÉ | JF47: Gloria Sarmiento | JG47: Canceló | JH47: Morelos C1 | JI47: 150 | JK47: Tiene costos autorizados por whatsapp | JL47: S | JM47: Particular | JN47: Evelyn Estefania Rios Vasquez | JO47: Individual 2025 | JP47: Rosy Macias | JQ47: No confirmó | JR47: Morelos C1 | JS47: $420 | JU47: Que no pagó porque es "colaborador" puso la lic en bitacora | JV47: R | JW47: Particular | JX47: Sandra Yudith García Dávila | JY47: Individual | JZ47: Maria Amancio | KA47: Asistió | KB47: Guanajuato C2 | KC47: 480 | KE47: PENDIENTE TRANSFERENCIA | KF47: R | KG47: Particular | KH47: Erik José Alfredo Medina Saucedo | KI47: Individual | KJ47: Benjamin Villagomez | KK47: Asistió | KL47: Guanajuato C1 | KM47: 420 | KN47: Efectivo | KO47: Dr. Luna ve también al px
A48: 0.25 | AP48: N | AQ48: Particular | AR48: Isabella Jocelin Borja Sifuentes | AS48: Infantil | AT48: Fabiola Fragoso | AU48: Reagendó | AV48: Guanajuato C2 | AW48: 420 | AY48: Reagendo para el 10 enero a las 3:00 pm | BJ48: S | BK48: Particular | BL48: Yessica Anahí Rodríguez Palacios | BM48: Consulta psiquiatrica | BN48: Enrique Luna | BO48: Reagendó | BP48: Guanajuato C1 | BQ48: 850 | BS48: Quedó sábado 10 a las 10:00 | BT48: S | BU48: Particular | BV48: Johana Bustamante (Javier Bustamante papá) | BW48: Individual | BX48: Lucía Sánchez | BY48: Reagendó | BZ48: Guanajuato C1 | CA48: 450 | CC48: Pal miercoles 14 de enero a las 7:00 pm | DH48: S | DI48: Particular | DJ48: Omar Guadalupe Contreras Sánchez | DK48: Individual 2025 | DL48: Lucía Sánchez | DM48: No llegó | DN48: Guanajuato C1 | DO48: 420 | DP48: Efectivo | DR48: S | DS48: Particular | DT48: Ernesto Lobo | DU48: Individual | DV48: José Arcadio | DW48: Confirmó | DX48: Colinas C1 | DY48: 420 | EA48: 0.27083333 | EB48: N | EC48: Particular | ED48: Carlos Miguel Fernández Reina | EE48: Infantil | EF48: Esmeralda Colunga | EG48: Asistió | EH48: Morelos C2 | EI48: 500 | EJ48: Efectivo | EL48: S | EM48: Particular | EN48: Emilio Alejandro Hernádez Montes | EO48: Individual 2025 | EP48: Javier Martínez | ER48: Guanajuato C3 | ES48: 200 | EU48: Ofrecerle espacio porque se agendó fuera de disponibilidad del Lic | EV48: N | EW48: Particular | EX48: Guillermo Flores Dávila y Miriam Alejandra Argumedo García | EY48: Pareja | EZ48: Rosy Macias | FA48: Reagendó | FB48: Morelos C1 | FC48: 600 | FE48: Se pasaron al sábado 17 con Lic. Amancio | FZ48: S | GA48: Particular | GB48: Angel Daniel Garcia Ruvalcaba T Alondra E. | GC48: Individual | GD48: Javier Martínez | GE48: Reagendó | GF48: Guanajuato C3 | GG48: 420 | GJ48: S | GK48: Particular | GL48: Daniela Rafael Sifuentes | GM48: Individual | GN48: Benjamin Villagomez | GO48: Reagendó | GP48: Guanajuato C1 | GQ48: 450 | GS48: Para el 21 | GT48: S | GU48: Particular | GV48: Daniela Rafael Sifuentes | GW48: Individual | GX48: Benjamin Villagomez | GY48: Asistió | GZ48: Guanajuato C1 | HA48: 450 | HB48: Tarjeta | HN48: N | HO48: Particular | HP48: Aileen Andrea Eguia Moreno | HQ48: Individual | HR48: Benjamin Villagomez | HS48: Asistió | HT48: Guanajuato C1 | HU48: 450 | HW48: La perxona preguntó directamente por el Lic. Benjamin | IR48: S | IS48: Particular | IT48: Emilio Alejandro Hernández Montes | IU48: Individual | IV48: Javier Martínez | IW48: Confirmó | IX48: Guanajuato C1 | IY48: 200 | JA48: PENDIENTE COSTO CON DR LUNA | JB48: S | JC48: Particular | JD48: Oscar Jesús Sánchez Muñoz | JE48: Individual | JF48: José Arcadio | JG48: Asistió | JH48: Colinas C1 | JI48: 420 | JK48: 0.27083333 | JL48: N | JM48: Particular | JN48: Blanca Araceli Zamora Soto | JO48: Individual | JP48: José Arcadio | JQ48: Asistió | JR48: Colinas C1 | JS48: 450 | JT48: Transf - 1872 | JU48: 0.27083333 | JV48: S | JW48: Particular | JX48: Daniela Rafael Sifuentes | JY48: Individual | JZ48: Benjamin Villagomez | KA48: Asistió | KB48: Guanajuato C1 | KC48: 450 | KD48: Tarjeta | KE48: CONFIRMO TARDE | KF48: S | KG48: NEAPCO | KH48: Antonio De Jesús Jara Esquivel | KI48: Individual | KJ48: Carolina Gonzalez | KK48: Confirmó | KL48: Guanajuato C2 | KM48: 0 | KN48: Pase
A49: 0.25 | AP49: S | AQ49: Particular | AR49: Sandra Yudith García Dávila | AS49: Individual 2025 | AT49: Javier Martínez | AU49: Confirmó | AV49: Guanajuato C3 | AW49: 350 | AX49: Efectivo | AY49: Pagará 380 | BJ49: S | BK49: NEAPCO | BL49: Julio Alejandro Moreno Moncada | BM49: Individual 2025 | BN49: Benjamin Villagomez | BO49: No llegó | BP49: Guanajuato C1 | BQ49: 0 | BR49: Pase | BS49: 6:30pm Si confirmó y no llegó, mandó whats terapeuta, que se atendió el jueves | BT49: S | BV49: Julio Alejandro Moreno | BX49: Benjamin Villagomez | BY49: Asistió | CC49: 6.30 Dice el doc que lo atendió | CD49: S | CE49: Particular | CF49: Nayelli Monserrat Reyna De Leon | CG49: Individual | CH49: Gloria Sarmiento | CI49: Asistió | CJ49: Morelos C1 | CK49: 450 | CL49: Transf - 1872 | DH49: S | DI49: Particular | DJ49: Oscar Jesús Sánchez Muñoz | DK49: Individual | DL49: José Arcadio | DM49: Asistió | DN49: Colinas C1 | DO49: 420 | DP49: Transf - 1872 | DQ49: 6:00 Pidió Lic. Arcadio mover a las 6, en vez de 6:30 | DR49: N | DS49: Particular | DT49: Daniela Rafael Sifuentes | DU49: Individual | DV49: Benjamin Villagomez | DW49: Asistió | DX49: Guanajuato C1 | DY49: 225 | DZ49: Efectivo | EA49: 6:30 Se le hizo descuento porque el sabado Lic Benjamin llegó tarde | EB49: S | EC49: Particular | ED49: Violeta Berenice Meza Dominguez | EE49: Medica en salud mental | EF49: Enrique Luna | EG49: Asistió | EH49: Guanajuato C1 | EI49: 750 | EJ49: Transf - 1872 | EL49: S | EM49: Particular | EN49: Fernando Jose Rodriguez Daniel (mamá Ma Fernanda Rodríguez Daniel | EO49: Infantil | EP49: Gloria Sarmiento | EQ49: Asistió | ER49: Morelos C1 | ES49: 150 | ET49: Efectivo | EU49: Dice bitacora mamá se comunicará, mandarle instrumento BAI | EW49: Particular | EX49: Nayelli Monserrat Reyna De Leon | EY49: Individual | EZ49: Gloria Sarmiento | FA49: Asistió | FB49: Morelos C2 | FC49: S | FD49: Transf - 1872 | GB49: NO AGENDAR A LIC LUCÍA A PARTIR DE LAS 6:00 | GJ49: S | GK49: UTS | GL49: Carlos Amauri García Peña | GM49: Individual 2025 | GN49: Rosy Macias | GO49: No confirmó | GP49: Morelos C1 | GQ49: $300 | GT49: N | GU49: Particular | GV49: Kevin Orlando Fuentes Guerrero | GW49: Individual | GX49: Gloria Sarmiento | GY49: Asistió | GZ49: Morelos C1 | HA49: 450 | HB49: Efectivo | HC49: SE AGENDO EL MISMO DIA PORQUE EL PX PIDIO HOY MISMO | HN49: S | HO49: Particular | HP49: Nayelli Monserrat Reyna De Leon | HQ49: Individual | HR49: Gloria Sarmiento | HS49: Asistió | HT49: Morelos C2 | HU49: 500 | HV49: Transf - 1872 | IR49: S | IS49: Particular | IT49: Katherine Isabel Garcia Hernandez | IU49: Infantil | IV49: Perla Realme | IW49: Confirmó | IX49: Guanajuato C2 | IY49: 200 | JB49: S | JC49: Particular | JD49: Valeria Guevara Rodríguez | JE49: Individual 2025 | JF49: Benjamin Villagomez | JG49: Asistió | JH49: WhereBy 2 | JI49: 420 | JJ49: Transf - 1872 | JL49: N | JM49: Particular | JN49: Gabriela Fabiola Bustillo | JO49: Individual | JP49: Fabiola Fragoso | JQ49: Asistió | JR49: WhereBy 1 | JS49: 450 | JT49: Transf - 1872 | JU49: Pareja de Luis Carlos Reyes de Lucía | JV49: S | JW49: Particular | JX49: Braulio Raziel Rico Cervantes | JY49: Individual 2025 | JZ49: Gloria Sarmiento | KB49: Morelos C2 | KC49: 420 | KE49: A la espera de que pase comprobante de la consulta del 9 de enero y del 26 de diciembre, se le avisó que se volverá a agendar cuando pague | KF49: S | KG49: Particular | KH49: Maria de Lourdes Martínez | KI49: Individual | KJ49: Rosy Macias | KK49: No confirmó | KL49: Morelos C1 | KM49: 350
A50: 0.25 | DH50: S | DI50: Particular | DJ50: Katherine Isabel Garcia Hernandez | DK50: Infantil | DL50: Perla Realme | DM50: Asistió | DN50: Guanajuato C2 | DO50: 200 | DP50: Transf - 1872 | DR50: S | DS50: UTS | DT50: Carlos Amauri García Peña | DU50: Individual 2025 | DV50: Rosy Macias | DW50: Asistió | DX50: Morelos C1 | DY50: $300 | DZ50: Efectivo | EA50: Px cambio hora de 4:00 a 6:00 | EV50: S | EW50: INSUNTE | EX50: Alan Mitsael Flores Vazquez | EY50: Individual | EZ50: Maricela Sena | FA50: Asistió | FB50: Guanajuato C1 | FC50: 300 | FD50: Transf - 1872 | FE50: 0.27083333 | FZ50: S | GA50: Particular | GB50: María del Socorro Salazar | GC50: Individual | GD50: Fabiola Fragoso | GE50: Canceló | GF50: Guanajuato C3 | GG50: 450 | GI50: Que ella se comunicaba para volver a agendar | HN50: S | HO50: GIASA | HP50: Juan Antonio Guerrero Ramírez | HQ50: Individual 2025 | HR50: Maricela Sena | HS50: Asistió | HT50: Guanajuato C2 | HU50: 0 | HV50: Pase | HW50: Pide mucho esta hora porque es cuando puede, por trabajo | IR50: S | IS50: Particular | IT50: Jonás Alejandro Morales | IU50: Individual | IV50: José Arcadio | IW50: Confirmó | IX50: Colinas C1 | IY50: 420 | JA50: 0.27083333 | JV50: S | JW50: Particular | JX50: Alejandro Lozano Garcia | JY50: Individual | JZ50: José Arcadio | KA50: Asistió | KB50: Morelos C1 | KC50: 420 | KD50: Transf - 1872 | KE50: 0.27083333 | KF50: S | KG50: Particular | KH50: Nayelli Monserrat Reyna De Leon | KI50: Individual | KJ50: Gloria Sarmiento | KK50: No confirmó | KL50: Morelos C2 | KM50: 500 | KN50: Transf - 1872
A51: 0.25 | DR51: S | DS51: Particular | DT51: Olivia del Rosario Malacara Mata (Contacto: Ángela Renatta Prado Malacara) | DU51: Individual | DV51: Gloria Sarmiento | DW51: Canceló | DX51: Morelos C1 | EA51: Lic. Gloria pidió reagendar, pero paciente canceló | JB51: S | JC51: Particular | JD51: Ryan García Lara | JE51: Individual | JF51: Fabiola Fragoso | JG51: Reagendó | JH51: Guanajuato C1 | JI51: 420 | JK51: Para martes 3 de febrero
A52: 0.29166667 | AZ52: S | BA52: Particular | BB52: Maria Magdalena Salcido Morales | BC52: Individual 2025 | BD52: Fabiola Fragoso | BE52: Asistió | BF52: Guanajuato C1 | BG52: 420 | BH52: Tarjeta | BJ52: S | BK52: Particular | BL52: Miriam González Gil | BM52: Consulta psiquiatrica | BN52: Enrique Luna | BO52: Asistió | BP52: Guanajuato C1 | BQ52: 750 | BR52: Efectivo | CD52: S | CE52: Particular | CF52: Goretty Rodriguez Lopez | CG52: Individual 2025 | CH52: Fabiola Fragoso | CI52: Asistió | CJ52: Guanajuato C1 | CK52: 420 | CL52: Efectivo | DH52: S | DI52: Particular | DJ52: Juan Manuel Fernández Castañeda | DK52: Individual 2025 | DL52: Fabiola Fragoso | DM52: Reagendó | DN52: Guanajuato C1 | DO52: 420 | DQ52: Para el lunes 19 misma hora | DR52: S | DS52: Particular | DT52: Isidro Emmanuel Jimenez Casas y Gabriela Santana Ibarra | DU52: Pareja | DV52: Rosy Macias | DW52: Asistió | DX52: Morelos C2 | DY52: 520 | DZ52: Transf - 1872 | EB52: S | EC52: Particular | ED52: Jose Guillermo Ballesteros Mora | EE52: Consulta psiquiatrica | EF52: Enrique Luna | EG52: Reagendó | EI52: 850 | EK52: Pendiente pasarle disponibilidad | EL52: S | EM52: NEAPCO | EN52: Julio Alejandro Moreno Moncada | EO52: Individual 2025 | EP52: Benjamin Villagomez | EQ52: Confirmó | ER52: Guanajuato C1 | ES52: 0 | ET52: Pase | EU52: 0.3125 | EV52: S | EW52: Particular | EX52: María García Pineda y Héctor Alexis T.Daniel Salazar | EY52: Pareja | EZ52: Rosy Macias | FA52: Asistió | FB52: Morelos C1 | FC52: 600 | FD52: Transf - 1872 | FE52: Fue el error del martes de las 7:00, buscar descuento | FZ52: S | GA52: Particular | GB52: Juan Manuel Fernández Castañeda | GC52: Individual 2025 | GD52: Fabiola Fragoso | GE52: Canceló | GF52: Guanajuato C1 | GG52: 420 | GI52: Pide reagendar para el próximo | HD52: R | HE52: Particular | HF52: Sandra Yudith García Dávila | HG52: Individual | HH52: Maria Amancio | HI52: Canceló | HJ52: Guanajuato C2 | HK52: 480 | HM52: Que no va a poder venir /1:50) reagenda para la prox semana | HN52: S | HO52: Particular | HP52: Axel Hiram Recio | HQ52: Individual 2025 | HR52: Fabiola Fragoso | HS52: Asistió | HT52: Guanajuato C1 | HU52: 350 | HV52: Transf - 1872 | HW52: PAGADO CHECAR COSTO NO HAY ESTUDIO SE | IR52: S | IS52: Particular | IT52: Juan Manuel Fernández Castañeda | IU52: Individual 2025 | IV52: Fabiola Fragoso | IW52: Confirmó | IX52: Guanajuato C1 | IY52: 420 | JA52: Canceló y pidió reagendar | JB52: S | JC52: Particular | JD52: Maria Magdalena Salcido Morales | JE52: Individual 2025 | JF52: Fabiola Fragoso | JG52: Asistió | JH52: Guanajuato C1 | JI52: 420 | JJ52: Transf - 1872 | JL52: N | JM52: GIASA | JN52: Perla Divina Gutierrez Aguirre | JO52: Individual | JP52: Fabiola Fragoso | JQ52: Canceló | JS52: 0 | JT52: Pase | JU52: Ella se volverá a comunicar cuando quiera agendar cita | JV52: S | JW52: Particular | JX52: Martin Rodríguez | JY52: Individual 2025 | JZ52: Fabiola Fragoso | KA52: Canceló | KB52: Guanajuato C2 | KC52: 420 | KF52: S | KG52: Particular | KH52: Goretty Rodríguez y Fabián Reyna | KI52: Pareja | KJ52: Fabiola Fragoso | KK52: Asistió | KL52: Guanajuato C2 | KM52: 420 | KN52: Transf - 1872
A53: 0.29166667 | BJ53: S | BK53: Trabajo social | BL53: José Francisco Gomez Coronado y Angélica María Marín Loera | BM53: Infantil | BN53: Fabiola Fragoso | BO53: Reagendó | BP53: Guanajuato C3 | BQ53: 350 | BS53: Para el miercoles 14 a las 7:00 | BT53: S | BU53: Particular | BV53: Martin Rodríguez | BW53: Individual 2025 | BX53: Fabiola Fragoso | BY53: Asistió | BZ53: Guanajuato C2 | CA53: 420 | CB53: Tarjeta | DH53: N | DI53: Particular | DJ53: María del Rosario García Pineda y Héctor Alexis Martínez | DK53: Pareja | DL53: Daniel Salazar | DM53: Incidente | DN53: Morelos C1 | DO53: 600 | DP53: Efectivo | DQ53: 0.3125 | EB53: S | EC53: Trabajo social | ED53: José Francisco Gomez Coronado y Angélica María Marín Loera | EE53: Pareja | EF53: Fabiola Fragoso | EG53: Reagendó | EH53: Guanajuato C3 | EI53: 350 | EK53: Lic Fabiola pidió moverlos al viernes | EL53: N | EM53: NEAPCO | EN53: Mario Eduardo Sánchez Molina | EO53: Individual | EP53: Ana Juarez | EQ53: Asistió | ER53: Guanajuato C2 | ES53: 0 | ET53: Pase | EV53: S | EW53: Trabajo social | EX53: José Francisco Gomez Coronado y Angélica María Marín Loera | EY53: Pareja | EZ53: Fabiola Fragoso | FA53: No llegó | FB53: Guanajuato C3 | FC53: 350 | FE53: Sólo se trabajará con Angélica | GJ53: S | GK53: Particular | GL53: Ryan García Lara | GM53: Individual 2025 | GN53: Fabiola Fragoso | GO53: Incidente | GP53: Guanajuato C1 | GQ53: 420 | HN53: S | HO53: Particular | HP53: Juan Antonio Izquierdo Treviño | HQ53: Individual | HR53: Maricela Sena | HS53: Canceló | HT53: Guanajuato C2 | HU53: 450 | HW53: DICE LA ESPOSA QUE YA NO VA A VENIR PORQUE LE VAN A DAR LA ATENCIÓN EN EL TRAB_AJO | JB53: S | JC53: Particular | JD53: Isidro Emmanuel Jimenez Casas y Gabriela Santana Ibarra | JE53: Pareja | JF53: Rosy Macias | JG53: No confirmó | JH53: Morelos C2 | JI53: 520 | JL53: S | JM53: Particular | JN53: María Fernanda Medina y Hugo Torres | JO53: Pareja | JP53: Maria Amancio | JQ53: Asistió | JR53: Guanajuato C2 | JS53: 600 | JV53: S | JW53: NEAPCO | JX53: Mario Eduardo Sánchez Molina | JY53: Individual | JZ53: Ana Juarez | KA53: Confirmó | KB53: Guanajuato C2 | KC53: 0 | KD53: Pase
A54: 0.29166667 | BJ54: S | BK54: Particular | BL54: Violeta Berenice Meza Dominguez | BM54: Individual 2025 | BN54: Enrique Luna | BO54: Reagendó | BP54: Guanajuato C1 | BQ54: 750 | BS54: Reagendó para el miércoles 14 a las 6:00 | DR54: N | DS54: GIASA | DT54: Perla Divina Gutierrez Aguirre | DU54: Individual | DV54: Fabiola Fragoso | DW54: Asistió | DX54: WhereBy 1 | DY54: 0 | DZ54: Pase | EA54: No. Empleado 8611 | EB54: S | EC54: Particular | ED54: Johana Bustamante (Javier Bustamante papá) | EE54: Individual | EF54: Lucía Sánchez | EG54: No confirmó | EH54: Guanajuato C1 | EI54: 450 | EK54: Tenía el jueves 8 de enero y reagendó/ dijo que e de comunicaba para hacer cita porque su hija no quiere asistir | EL54: N | EM54: GIASA | EN54: Karina Rivera | EO54: Individual | EP54: David Bermejo | EQ54: No llegó | ER54: WhereBy 1 | ES54: 0 | ET54: Pase | GJ54: N | GK54: Particular | GL54: Mario Alberto García Gámez y Melva Nelia Puente Siller | GM54: Pareja | GN54: Benjamin Villagomez | GO54: Canceló | GP54: Colinas C1 | GQ54: 600 | GS54: 7:30 Que ellos se comunicaban
A55: 0.29166667 | DR55: N | DS55: Particular | DT55: Mario Alberto García Gámez y Melva Nelia Puente Siller | DU55: Pareja | DV55: Benjamin Villagomez | DW55: Asistió | DX55: Guanajuato C1 | DY55: 600 | DZ55: Transf - 1872 | EB55: S | EC55: Particular | ED55: María Fernanda Medina y Hugo Torres | EE55: Pareja | EF55: Maria Amancio | EG55: Asistió | EH55: Guanajuato C2 | EI55: 600 | EJ55: Tarjeta | EK55: Tenian el 8 de enero pero faltaron y se les mandó mensaje de recargo por $300
A56: 0.29166667
A57: 0.33333333 | BJ57: S | BK57: Particular | BL57: F | BM57: Individual 2025 | BN57: Enrique Luna | BO57: Canceló | BP57: Guanajuato C1 | BQ57: 680 | DR57: S | DS57: Particular | DT57: Valeria Guevara Rodríguez | DU57: Individual 2025 | DV57: Benjamin Villagomez | DW57: Asistió | DX57: WhereBy 2 | DY57: 420 | DZ57: Transf - 1872 | EA57: 8:30 PAGADO | EB57: N | EC57: Particular | ED57: Yessica Anahí Rodriguez Palacios | EE57: Medica en salud mental | EF57: Enrique Luna | EG57: Reagendó | EH57: Guanajuato C1 | EK57: PEDIR DESCUENTO PARA ELLA POR DOBLE CANCELACION | GJ57: S | GK57: Particular | GL57: Valeria Guevara Rodríguez | GM57: Individual 2025 | GN57: Benjamin Villagomez | GO57: Reagendó | GP57: WhereBy 2 | GQ57: 420 | GS57: 0.35416667 | GV57: BLOQUEADO LIC BENJAMIN | HF57: BLOQUEADO LIC BENJAMIN | HI57: Confirmó | HN57: S | HO57: Particular | HP57: María García Pineda y Héctor Alexis T.Daniel Salazar | HQ57: Pareja | HR57: Rosy Macias | HS57: Canceló | HT57: Morelos C1 | HU57: 600 | HW57: EXCEPCIÓN PARA PACIENTES POR PARTE DE LA LIC | JD57: RENTA FABIOLA | JG57: Confirmó | JH57: Guanajuato C1 | JV57: N | JW57: Particular | JX57: José Francisco Rodríguez Pérez | JY57: Individual | JZ57: Rosa María Gómez | KA57: Asistió | KB57: Guanajuato C1 | KC57: 450 | KD57: Efectivo | KE57: INICDENCIA EN MORELOS DEL SÁBADO 24
A58: 0.33333333
A59: 0.33333333
A60: 0.33333333
A61: 0.33333333

Sheet Nov 25
B1: 45962 | L1: =B1+1 -> 45963 | V1: =L1+1 -> 45964 | AF1: =V1+1 -> 45965 | AP1: =AF1+1 -> 45966 | AZ1: =AP1+1 -> 45967 | BJ1: =AZ1+1 -> 45968 | BT1: =BJ1+1 -> 45969 | CD1: =BT1+1 -> 45970 | CN1: =CD1+1 -> 45971 | CX1: =CN1+1 -> 45972 | DH1: =CX1+1 -> 45973 | DR1: =DH1+1 -> 45974 | EB1: =DR1+1 -> 45975 | EL1: =EB1+1 -> 45976 | EV1: =EL1+1 -> 45977 | FF1: =EV1+1 -> 45978 | FP1: =FF1+1 -> 45979 | FZ1: =FP1+1 -> 45980 | GJ1: =FZ1+1 -> 45981 | GT1: =GJ1+1 -> 45982 | HD1: =GT1+1 -> 45983 | HN1: =HD1+1 -> 45984 | HX1: =HN1+1 -> 45985 | IH1: =HX1+1 -> 45986 | IR1: =IH1+1 -> 45987 | JB1: =IR1+1 -> 45988 | JL1: =JB1+1 -> 45989 | JV1: =JL1+1 -> 45990 | KF1: =JV1+1 -> 45991
A2: Hora | B2: Tipo | C2: División | D2: Paciente | E2: Servicio | F2: Terapeuta | G2: Situación | H2: Consultorio | I2: $ / Pase | J2: Tipo pago | K2: Notas | L2: Tipo | M2: División | N2: Paciente | O2: Servicio | P2: Terapeuta | Q2: Situación | R2: Consultorio | S2: $ / Pase | T2: Tipo pago | U2: Notas | V2: Tipo | W2: División | X2: Paciente | Y2: Servicio | Z2: Terapeuta | AA2: Situación | AB2: Consultorio | AC2: $ / Pase | AD2: Tipo pago | AE2: Notas | AF2: Tipo | AG2: División | AH2: Paciente | AI2: Servicio | AJ2: Terapeuta | AK2: Situación | AL2: Consultorio | AM2: $ / Pase | AN2: Tipo pago | AO2: Notas | AP2: Tipo | AQ2: División | AR2: Paciente | AS2: Servicio | AT2: Terapeuta | AU2: Situación | AV2: Consultorio | AW2: $ / Pase | AX2: Tipo pago | AY2: Notas | AZ2: Tipo | BA2: División | BB2: Paciente | BC2: Servicio | BD2: Terapeuta | BE2: Situación | BF2: Consultorio | BG2: $ / Pase | BH2: Tipo pago | BI2: Notas | BJ2: Tipo | BK2: División | BL2: Paciente | BM2: Servicio | BN2: Terapeuta | BO2: Situación | BP2: Consultorio | BQ2: $ / Pase | BR2: Tipo pago | BS2: Notas | BT2: Tipo | BU2: División | BV2: Paciente | BW2: Servicio | BX2: Terapeuta | BY2: Situación | BZ2: Consultorio | CA2: $ / Pase | CB2: Tipo pago | CC2: Notas | CD2: Tipo | CE2: División | CF2: Paciente | CG2: Servicio | CH2: Terapeuta | CI2: Situación | CJ2: Consultorio | CK2: $ / Pase | CL2: Tipo pago | CM2: Notas | CN2: Tipo | CO2: División | CP2: Paciente | CQ2: Servicio | CR2: Terapeuta | CS2: Situación | CT2: Consultorio | CU2: $ / Pase | CV2: Tipo pago | CW2: Notas | CX2: Tipo | CY2: División | CZ2: Paciente | DA2: Servicio | DB2: Terapeuta | DC2: Situación | DD2: Consultorio | DE2: $ / Pase | DF2: Tipo pago | DG2: Notas | DH2: Tipo | DI2: División | DJ2: Paciente | DK2: Servicio | DL2: Terapeuta | DM2: Situación | DN2: Consultorio | DO2: $ / Pase | DP2: Tipo pago | DQ2: Notas | DR2: Tipo | DS2: División | DT2: Paciente | DU2: Servicio | DV2: Terapeuta | DW2: Situación | DX2: Consultorio | DY2: $ / Pase | DZ2: Tipo pago | EA2: Notas | EB2: Tipo | EC2: División | ED2: Paciente | EE2: Servicio | EF2: Terapeuta | EG2: Situación | EH2: Consultorio | EI2: $ / Pase | EJ2: Tipo pago | EK2: Notas | EL2: Tipo | EM2: División | EN2: Paciente | EO2: Servicio | EP2: Terapeuta | EQ2: Situación | ER2: Consultorio | ES2: $ / Pase | ET2: Tipo pago | EU2: Notas | EV2: Tipo | EW2: División | EX2: Paciente | EY2: Servicio | EZ2: Terapeuta | FA2: Situación | FB2: Consultorio | FC2: $ / Pase | FD2: Tipo pago | FE2: Notas | FF2: Tipo | FG2: División | FH2: Paciente | FI2: Servicio | FJ2: Terapeuta | FK2: Situación | FL2: Consultorio | FM2: $ / Pase | FN2: Tipo pago | FO2: Notas | FP2: Tipo | FQ2: División | FR2: Paciente | FS2: Servicio | FT2: Terapeuta | FU2: Situación | FV2: Consultorio | FW2: $ / Pase | FX2: Tipo pago | FY2: Notas | FZ2: Tipo | GA2: División | GB2: Paciente | GC2: Servicio | GD2: Terapeuta | GE2: Situación | GF2: Consultorio | GG2: $ / Pase | GH2: Tipo pago | GI2: Notas | GJ2: Tipo | GK2: División | GL2: Paciente | GM2: Servicio | GN2: Terapeuta | GO2: Situación | GP2: Consultorio | GQ2: $ / Pase | GR2: Tipo pago | GS2: Notas | GT2: Tipo | GU2: División | GV2: Paciente | GW2: Servicio | GX2: Terapeuta | GY2: Situación | GZ2: Consultorio | HA2: $ / Pase | HB2: Tipo pago | HC2: Notas | HD2: Tipo | HE2: División | HF2: Paciente | HG2: Servicio | HH2: Terapeuta | HI2: Situación | HJ2: Consultorio | HK2: $ / Pase | HL2: Tipo pago | HM2: Notas | HN2: Tipo | HO2: División | HP2: Paciente | HQ2: Servicio | HR2: Terapeuta | HS2: Situación | HT2: Consultorio | HU2: $ / Pase | HV2: Tipo pago | HW2: Notas | HX2: Tipo | HY2: División | HZ2: Paciente | IA2: Servicio | IB2: Terapeuta | IC2: Situación | ID2: Consultorio | IE2: $ / Pase | IF2: Tipo pago | IG2: Notas | IH2: Tipo | II2: División | IJ2: Paciente | IK2: Servicio | IL2: Terapeuta | IM2: Situación | IN2: Consultorio | IO2: $ / Pase | IP2: Tipo pago | IQ2: Notas | IR2: Tipo | IS2: División | IT2: Paciente | IU2: Servicio | IV2: Terapeuta | IW2: Situación | IX2: Consultorio | IY2: $ / Pase | IZ2: Tipo pago | JA2: Notas | JB2: Tipo | JC2: División | JD2: Paciente | JE2: Servicio | JF2: Terapeuta | JG2: Situación | JH2: Consultorio | JI2: $ / Pase | JJ2: Tipo pago | JK2: Notas | JL2: Tipo | JM2: División | JN2: Paciente | JO2: Servicio | JP2: Terapeuta | JQ2: Situación | JR2: Consultorio | JS2: $ / Pase | JT2: Tipo pago | JU2: Notas | JV2: Tipo | JW2: División | JX2: Paciente | JY2: Servicio | JZ2: Terapeuta | KA2: Situación | KB2: Consultorio | KC2: $ / Pase | KD2: Tipo pago | KE2: Notas | KF2: Tipo | KG2: División | KH2: Paciente | KI2: Servicio | KJ2: Terapeuta | KK2: Situación | KL2: Consultorio | KM2: $ / Pase | KN2: Tipo pago | KO2: Notas
A3: 0.375 | B3: S | C3: Particular | D3: Gerardo Dominguez Mendez | E3: Individual 2025 | F3: José Arcadio | G3: Asistió | H3: Morelos C1 | I3: $380 | J3: Efectivo | K3: 0.39583333 | AF3: S | AG3: Particular | AH3: Antony Bernardo Hernández Durán | AI3: Individual 2025 | AJ3: Maricela Sena | AK3: No llegó | AL3: Guanajuato C1 | AM3: 350 | AN3: Efectivo | CX3: N | CY3: Particular | CZ3: Patricia Angel Luna | DA3: Individual 2025 | DB3: Maricela Sena | DC3: Asistió | DD3: Guanajuato C1 | DE3: 420 | DF3: Efectivo | DH3: N | DI3: Particular | DJ3: Fernando Martinez Sosa | DK3: Individual 2025 | DL3: Maricela Sena | DM3: Asistió | DN3: Guanajuato C2 | DO3: 420 | DP3: Tarjeta | EL3: S | EM3: Particular | EN3: Gerardo Dominguez Mendez | EO3: Individual 2025 | EP3: José Arcadio | EQ3: Canceló | ER3: Morelos C1 | ES3: $380 | ET3: Efectivo | EU3: 0.39583333 | FP3: S | FQ3: Particular | FR3: Patricia Angel Luna | FS3: Individual 2025 | FT3: Maricela Sena | FU3: Reagendó | FV3: Guanajuato C1 | FW3: 420 | FZ3: S | GA3: Particular | GB3: Fernando Martinez Sosa | GC3: Individual 2025 | GD3: Maricela Sena | GE3: Asistió | GF3: Guanajuato C2 | GG3: 420 | GH3: Efectivo
A4: 0.375 | HF4: Renta de espacio | HG4: Renta de espacios - Asociados | HH4: Daniel Salazar | HI4: Canceló | HJ4: Guanajuato C1 | HK4: 125 | IH4: S | II4: Particular | IJ4: Alan Eduardo Mora Serrano | IK4: Individual 2025 | IL4: Maricela Sena | IM4: Asistió | IN4: Guanajuato C1 | IO4: 420 | IP4: Tarjeta | IR4: S | IS4: Particular | IT4: Imelda Noemi Rosales Tijerina | IU4: Evaluación neuropsicológica | IV4: Javier Martínez | IW4: Reagendó | IX4: Guanajuato C3 | IY4: 380 | IZ4: Efectivo
A5: 0.375 | IR5: S | IS5: Particular | IT5: Fernando Martinez Sosa | IU5: Individual 2025 | IV5: Maricela Sena | IW5: Asistió | IX5: Guanajuato C2 | IY5: 420 | IZ5: Tarjeta
A6: 0.375
A7: 0.41666667 | B7: S | C7: Particular | D7: Lorenzo Mario Soto Sanchez | E7: Individual 2025 | F7: José Arcadio | G7: Asistió | H7: Morelos C1 | I7: 420 | J7: Transf - 1872 | K7: 0.4375 | AF7: S | AG7: Particular | AH7: Alicia Minerva Ordóñez Hernandez | AI7: Individual 2025 | AJ7: Maricela Sena | AK7: Asistió | AL7: Guanajuato C1 | AM7: $350 | AN7: Efectivo | AP7: N | AQ7: Particular | AR7: Armando Rodríguez Hernández | AS7: Individual 2025 | AT7: Lucía Sánchez | AU7: Asistió | AV7: Guanajuato C1 | AW7: 420 | AX7: Efectivo | AY7: 0.4375 | AZ7: S | BA7: GIASA | BB7: Karina Rivera | BC7: Individual 2025 | BD7: Javier Martínez | BE7: No llegó | BF7: ZOOM | BG7: $0 | BH7: Pase | CX7: S | CY7: Particular | CZ7: José Antonio Bautista | DA7: Individual 2025 | DB7: Maricela Sena | DC7: Reagendó | DD7: Guanajuato C1 | DE7: 420 | DH7: N | DI7: Particular | DJ7: Oliver Enrique Rivera Rodríguez | DK7: Individual 2025 | DL7: Maricela Sena | DM7: Asistió | DN7: Guanajuato C1 | DO7: 420 | DP7: Efectivo | DR7: N | DS7: Particular | DT7: Armando Rodríguez Hernández | DU7: Individual 2025 | DV7: María de la Luz | DW7: Reagendó | DX7: Guanajuato C1 | DY7: 420 | DZ7: Efectivo | EA7: 0.4375 | FP7: S | FQ7: Particular | FR7: José Antonio Bautista | FS7: Individual 2025 | FT7: Maricela Sena | FU7: Reagendó | FV7: Guanajuato C1 | FW7: 420 | FX7: Tarjeta | FZ7: S | GA7: Particular | GB7: Patricia Angel Luna | GC7: Individual 2025 | GD7: Maricela Sena | GE7: Asistió | GF7: Guanajuato C1 | GG7: 420 | GH7: Efectivo | GI7: se le cobraran $600,por lapso de tiempo | GT7: S | GU7: Particular | GV7: Maria Fernanda y Hugo | GW7: Pareja | GX7: Maria Amancio | GY7: Confirmó | GZ7: Guanajuato C2 | HA7: 600 | HB7: Tarjeta | HC7: 0.4375 | HD7: S | HE7: Particular | HF7: Alejandro Lozano | HG7: Individual 2025 | HH7: José Arcadio | HI7: Confirmó | HJ7: Morelos C1 | HK7: $420 | IH7: S | II7: Particular | IJ7: José Antonio Bautista | IK7: Individual 2025 | IL7: Maricela Sena | IM7: Asistió | IN7: Guanajuato C1 | IO7: 420 | IP7: Tarjeta | IR7: S | IS7: Particular | IT7: Patricia Angel Luna | IU7: Individual 2025 | IV7: Maricela Sena | IW7: Pendiente REAG | IX7: Guanajuato C1 | IY7: 420 | JV7: S | JW7: Particular | JX7: Dora Luz Monsivais Martinez | JY7: Individual 2025 | JZ7: José Arcadio | KA7: Asistió | KB7: Morelos C1 | KC7: $420 | KD7: Efectivo
A8: 0.41666667 | B8: S | C8: Particular | D8: Cesar Erubiel Rodriguez | E8: Individual | F8: Javier Martínez | G8: Asistió | H8: Guanajuato C3 | I8: 300 | J8: Efectivo | K8: pago pendiente | BT8: S | BU8: Particular | BV8: Lorenzo Mario Soto Sanchez | BW8: Individual 2025 | BX8: José Arcadio | BY8: Reagendó | BZ8: Morelos C1 | CA8: 420 | DH8: N | DI8: Particular | DJ8: Maria Fernanda y Hugo | DK8: Pareja | DL8: Maria Amancio | DM8: Asistió | DN8: Guanajuato C2 | DO8: 600 | DP8: Tarjeta | EL8: S | EM8: Particular | EN8: Lorenzo Mario Soto | EO8: Individual 2025 | EP8: José Arcadio | EQ8: Canceló | ER8: Morelos C1 | ES8: 420 | ET8: Transf - 1872 | FP8: N | FQ8: Particular | FR8: Alan Eduardo Mora Serrano | FS8: Individual 2025 | FT8: Maricela Sena | FU8: Asistió | FV8: Guanajuato C1 | FW8: 420 | FX8: Tarjeta
A9: 0.41666667 | B9: N | C9: Particular | D9: Marijose Pelaez Arias | E9: Individual 2025 | F9: Daniel Salazar | G9: No llegó | H9: Morelos C2 | I9: 420 | J9: Efectivo | DS9: Colaboradores | DT9: ONBOARDING ZOOM GIOVANNA | DX9: ZOOM C1
A10: 0.41666667
A11: 0.41666667
A12: 0.45833333 | B12: S | C12: Particular | D12: Alicia Minerva Ordónez Hernandez | E12: Individual 2025 | F12: Enrique Luna | G12: Asistió | H12: Guanajuato C1 | I12: $550 | J12: Tarjeta | K12: 11:30pm | V12: S | W12: Particular | X12: Emmanuel Jimenez Maqueda | Y12: Individual 2025 | Z12: Lucía Sánchez | AA12: Reagendó | AB12: Guanajuato C2 | AC12: 420 | AZ12: S | BA12: Particular | BB12: Ricardo Gaytan Carranza | BC12: Individual 2025 | BD12: Lucía Sánchez | BE12: Confirmó | BF12: Guanajuato C2 | BG12: 200 | BH12: Efectivo | BT12: S | BU12: NEAPCO | BV12: Luis Contreras | BW12: Médica psiquiatrica | BX12: Enrique Luna | BY12: Pendiente REAG | BZ12: Guanajuato C1 | CA12: 0 | CB12: Pase | CX12: S | CY12: Particular | CZ12: Beatriz Camarena | DA12: Individual 2025 | DB12: Maricela Sena | DC12: Asistió | DD12: Guanajuato C1 | DE12: 200 | DF12: Transf - 1872 | DH12: S | DI12: Particular | DJ12: Ma. Antonia Martinez Urrea | DK12: Individual 2025 | DL12: Maricela Sena | DM12: Asistió | DN12: Guanajuato C2 | DO12: 420 | DP12: Transf - 1872 | DR12: N | DS12: Particular | DT12: Rosa Elva Hernández Martínez | DU12: Individual 2025 | DV12: Lucía Sánchez | DW12: No confirmó | DX12: Guanajuato C1 | DY12: 400 | EB12: S | EC12: Particular | ED12: Mario Zamarripa | EE12: Individual 2025 | EF12: Javier Martínez | EG12: Confirmó | EH12: Guanajuato C3 | EI12: 420 | EJ12: Efectivo | EL12: S | EM12: Particular | EN12: Dora Luz Monsivais Martinez | EO12: Individual 2025 | EP12: José Arcadio | EQ12: Asistió | ER12: Morelos C1 | ES12: $420 | ET12: Transf - 1872 | FP12: S | FQ12: Particular | FR12: Ricardo Gaytan Carranza | FS12: Individual 2025 | FT12: Lucía Sánchez | FU12: Reagendó | FV12: Guanajuato C2 | FW12: 250 | FX12: Efectivo | FZ12: S | GA12: Particular | GB12: Ma. Antonia Martinez Urrea | GC12: Individual 2025 | GD12: Maricela Sena | GE12: Reagendó | GF12: Guanajuato C2 | GG12: 420 | GJ12: S | GK12: Particular | GL12: Ricardo Gaytan Carranza | GM12: Individual 2025 | GN12: Lucía Sánchez | GO12: Confirmó | GP12: Guanajuato C2 | GQ12: 250 | GR12: Efectivo | HD12: S | HE12: Particular | HF12: Cecilia Noriega Arévalo | HG12: Individual 2025 | HH12: José Arcadio | HI12: Confirmó | HJ12: Morelos C1 | HK12: $400 | HL12: Efectivo | IH12: S | II12: Particular | IJ12: Ricardo Gaytan Carranza | IK12: Individual 2025 | IL12: Lucía Sánchez | IM12: Reagendó | IN12: Guanajuato C2 | IO12: 250 | IR12: S | IS12: Particular | IT12: Ma. Antonia Martinez Urrea | IU12: Individual 2025 | IV12: Maricela Sena | IW12: Asistió | IX12: Guanajuato C1 | IY12: 420 | IZ12: Efectivo | JB12: S | JC12: Particular | JD12: Ricardo Gaytan Carranza | JE12: Individual 2025 | JF12: Lucía Sánchez | JG12: Reagendó | JH12: Guanajuato C2 | JI12: 250 | JJ12: Efectivo | JV12: N | JW12: Particular | JX12: Daniel Emiliano Valdes Herrera | JY12: Individual 2025 | JZ12: Fabiola Fragoso | KA12: Asistió | KB12: Guanajuato C2 | KC12: 420 | KD12: Efectivo
A13: 0.45833333 | B13: S | C13: Particular | D13: Alejandro Lozano | E13: Individual 2025 | F13: José Arcadio | G13: Asistió | H13: Morelos C1 | I13: $420 | J13: Transf - 1872 | K13: 0.47916667 | V13: S | W13: Particular | X13: Ricardo Gaytan Carranza | Y13: Individual 2025 | Z13: Lucía Sánchez | AA13: Reagendó | AB13: Guanajuato C2 | AC13: 200 | AD13: Efectivo | AF13: S | AG13: Particular | AH13: Beatriz Camarena | AI13: Individual 2025 | AJ13: Maricela Sena | AK13: Asistió | AL13: Guanajuato C1 | AM13: $420 | AN13: Transf - 1872 | BT13: S | BU13: Particular | BV13: Cecilia Noriega Arévalo | BW13: Individual 2025 | BX13: José Arcadio | BY13: Confirmó | BZ13: Morelos C1 | CA13: $400 | CB13: Efectivo | CX13: S | CY13: Particular | CZ13: Ricardo Gaytan Carranza | DA13: Individual 2025 | DB13: Lucía Sánchez | DC13: Asistió | DD13: Guanajuato C2 | DE13: 250 | DF13: Efectivo | DH13: S | DI13: GIASA | DJ13: Karina Gomez | DK13: Individual 2025 | DL13: Rosa María Gómez | DM13: Asistió | DN13: ZOOM C1 | DO13: 0 | DP13: Pase | EL13: S | EM13: Particular | EN13: Habid Asael Rojas Nuncio | EO13: Individual 2025 | EP13: José Arcadio | EQ13: Reagendó | ER13: Morelos C1 | ES13: 420 | FP13: S | FQ13: Particular | FR13: Beatriz Camarena | FS13: Individual 2025 | FT13: Maricela Sena | FU13: Asistió | FV13: Guanajuato C1 | FW13: 200 | FX13: Transf - 1872 | HD13: S | HE13: Particular | HF13: Alicia Minerva Ordónez Hernandez | HG13: Individual 2025 | HH13: Enrique Luna | HI13: Asistió | HJ13: Guanajuato C1 | HK13: $550 | HL13: Tarjeta | IH13: S | II13: Particular | IJ13: Beatriz Camarena | IK13: Individual 2025 | IL13: Maricela Sena | IM13: Asistió | IN13: Guanajuato C1 | IO13: 200 | IP13: Transf - 1872 | JV13: S | JW13: Particular | JX13: Maria Concepción Muñiz Saucedo | JY13: Individual 2025 | JZ13: Daniel Salazar | KA13: Asistió | KB13: Poniente C1 | KC13: $100 | KD13: Efectivo | KE13: 1/3, a la 4 cita se cobarara $180
A14: 0.45833333 | BT14: S | BU14: Particular | BV14: Valeria Monserrat Martinez | BW14: Individual 2025 | BX14: Javier Martínez | BY14: Confirmó | BZ14: Guanajuato C1 | CA14: $420 | CB14: Transf - 1872 | DS14: Colaboradores | DT14: ONBOARDING ZOOM GIOVANNA | DX14: ZOOM C1 | EL14: S | EM14: Particular | EN14: Leonel Abraham Galindo Garay | EO14: Individual | EP14: Javier Martínez | EQ14: Reagendó | ER14: Guanajuato C1 | ES14: $350 | EU14: NEURO | HD14: S | HE14: GIASA | HF14: Karina Rivera | HG14: Individual 2025 | HH14: Javier Martínez | HI14: Asistió | HJ14: ZOOM C1 | HK14: 0 | HL14: Pase
A15: 0.45833333 | BT15: S | BU15: Particular | BV15: Dora Luz Monsivais Martinez | BW15: Médica psiquiatrica | BX15: Enrique Luna | BY15: Confirmó | BZ15: Guanajuato C1 | CA15: 850 | EL15: N | EM15: Particular | EN15: Glenda Núñez Juárez | EO15: Individual 2025 | EP15: Benjamin Villagomez | EQ15: Pendiente REAG | HD15: N | HE15: Particular | HF15: Glenda Núñez Juárez | HG15: Individual 2025 | HH15: Benjamin Villagomez | HI15: Pendiente REAG
A16: 0.45833333 | EL16: S | EM16: NEAPCO | EN16: Luis Contreras | EO16: Médica psiquiatrica | EP16: Enrique Luna | EQ16: Asistió | ER16: Guanajuato C1 | ES16: 0 | ET16: Pase
A17: 0.5 | B17: S | C17: GIASA | D17: Evelyn saldivar | E17: Individual 2025 | F17: José Arcadio | G17: Asistió | H17: ZOOM C1 | I17: Pase | K17: 0.52083333 | AP17: S | AQ17: Particular | AR17: Emmanuel Jimenez Maqueda | AS17: Individual 2025 | AT17: Lucía Sánchez | AU17: Confirmó | AV17: Guanajuato C2 | AW17: 420 | AX17: Efectivo | CX17: S | CY17: GIASA | CZ17: Fabiola Soto Ortíz | DA17: Consulta nutricional | DB17: Carolina Gonzalez | DC17: No confirmó | DD17: Guanajuato C1 | DE17: 0 | DF17: Pase | EB17: S | EC17: Particular | ED17: Mario Zamarripa | EE17: Individual 2025 | EF17: Carolina Gonzalez | EG17: Confirmó | EH17: Guanajuato C3 | EI17: 425 | EJ17: Efectivo | EL17: S | EM17: Particular | EN17: Alejandro Lozano | EO17: Individual 2025 | EP17: José Arcadio | EQ17: Reagendó | ER17: Morelos C1 | ES17: $420 | FP17: S | FQ17: NEAPCO | FR17: Marco Antonio Hinojosa Hernández | FS17: Individual 2025 | FT17: Maricela Sena | FU17: No llegó | FV17: Guanajuato C1 | FW17: 0 | FX17: Pase | HD17: S | HE17: Particular | HF17: Pedro Alejandro Herrera González | HG17: Individual 2025 | HH17: Enrique Luna | HI17: Asistió | HJ17: Guanajuato C1 | HK17: 680 | IH17: S | II17: Particular | IJ17: Carlos Enrique Escobar Pérez | IK17: Individual 2025 | IL17: Maricela Sena | IM17: Asistió | IN17: Guanajuato C1 | IO17: 280 | IP17: Transf - 1872 | JB17: S | JC17: Particular | JD17: Dora Luz Monsivais Martinez | JE17: Medica | JF17: Enrique Luna | JG17: Canceló | JH17: Guanajuato | JI17: $850 | JV17: N | JW17: Particular | JX17: Teresita Garza | JY17: Individual | JZ17: José Arcadio | KA17: Asistió | KB17: Morelos C1 | KC17: 420 | KD17: Transf - 1872
A18: 0.5 | B18: N | C18: Particular | D18: Brayan Osiel De La peña | E18: Individual 2025 | F18: Daniel Salazar | G18: No llegó | H18: Morelos C2 | I18: 420 | BT18: S | BU18: Particular | BV18: Leonel Abraham Galindo Garay | BW18: Evaluación neuropsicológica | BX18: Javier Martínez | BY18: Confirmó | BZ18: Guanajuato C1 | CA18: 350 | EL18: S | EM18: Particular | EN18: Braulio Liam Galvan Martinez | EO18: Evaluación neuropsicológica | EP18: Javier Martínez | EQ18: Asistió | ER18: Guanajuato C2 | ES18: 380 | ET18: Efectivo | HD18: S | HE18: Particular | HF18: Angel Daniel Garcia Ruvalcaba | HG18: Individual 2025 | HH18: Javier Martínez | HI18: Reagendó | HJ18: Morelos C1 | HK18: $420 | JB18: S | JC18: Particular | JD18: Emmanuel Jimenez Maqueda | JE18: Individual 2025 | JF18: Lucía Sánchez | JG18: Pendiente REAG | JH18: ZOOM C1 | JI18: 420 | JV18: S | JW18: Particular | JX18: Leonel Abraham Galindo Garay | JY18: Individual 2025 | JZ18: Enrique Luna | KA18: No llegó | KB18: Guanajuato C1 | KC18: $500
A19: 0.5 | B19: S | C19: Particular | D19: Leonel Abraham Galindo Garay | E19: Individual 2025 | F19: Enrique Luna | G19: Asistió | H19: Guanajuato C1 | I19: $500 | J19: Transf - 1872 | K19: 12:30pm | JV19: S | JW19: Particular | JX19: Damian Ávalos | JY19: Individual 2025 | JZ19: Javier Martínez | KA19: No llegó | KB19: ZOOM C1
A20: 0.5 | BT20: N | BU20: Particular | BV20: Teresita Garza | BW20: Individual | BX20: José Arcadio | BY20: Confirmó | BZ20: Morelos C1 | CA20: 420 | CB20: Transf - 1872
A21: 0.5
A22: 0.041666667 | B22: S | C22: Particular | D22: Edson Alejandro Cabello Sanchez | E22: Individual 2025 | F22: Daniela Sarmiento | G22: Reagendó | H22: Morelos C2 | I22: $420 | BJ22: N | BK22: Particular | BL22: Issac Everardo Lopez De La Peña | BM22: Infantil | BN22: Gloria Sarmiento | BO22: Confirmó | BP22: Morelos C1 | BQ22: 480 | BR22: Efectivo | BT22: S | BU22: Particular | BV22: Fatima Valeria Nolasco | BW22: Individual 2025 | BX22: Enrique Luna | BY22: Confirmó | BZ22: Guanajuato C1 | CA22: 850 | EB22: S | EC22: Particular | ED22: Daniel Emiliano Martinez González | EE22: Individual 2025 | EF22: Gloria Sarmiento | EG22: No llegó | EH22: Morelos C2 | EI22: $420 | EJ22: Efectivo | EL22: N | EM22: Particular | EN22: Juan Diego López Balderas | EO22: Individual 2025 | EP22: Benjamin Villagomez | EQ22: Asistió | ER22: Guanajuato C3 | ES22: 380 | ET22: Efectivo | EU22: 0.0625 | GT22: S | GU22: GIASA | GV22: Marco Antonio Hinojosa Hernández | GW22: Individual 2025 | GX22: Maricela Sena | GY22: Confirmó | GZ22: Guanajuato C1 | HA22: 0 | HB22: Pase | HD22: S | HE22: Particular | HF22: Jorge Torres | HG22: Individual 2025 | HH22: Enrique Luna | HI22: Reagendó | HJ22: Guanajuato C1 | HK22: 850 | HX22: N | HY22: Particular | HZ22: Elizabeth Jaimes Quiroz | IA22: Infantil | IB22: Gloria Sarmiento | IC22: Asistió | ID22: Morelos C1 | IE22: 480 | IF22: Efectivo | JV22: S | JW22: Particular | JX22: Edson Alejandro Cabello Sanchez | JY22: Individual 2025 | JZ22: Daniela Sarmiento | KA22: Asistió | KB22: Morelos C2 | KC22: $420 | KD22: Transf - 1872
A23: 0.041666667 | B23: N | C23: Particular | D23: Marco Antonio Orta Barrera | E23: Consulta psiquiatrica | F23: Enrique Luna | G23: No llegó | H23: Guanajuato C1 | I23: 850 | J23: Efectivo | K23: 1:30pm | BT23: S | BU23: Particular | BV23: Jorge Torres | BW23: Individual 2025 | BX23: Javier Martínez | BY23: Confirmó | BZ23: Guanajuato C1 | CA23: 400 | CB23: Efectivo | EL23: S | EM23: Particular | EN23: Edson Alejandro Cabello Sanchez | EO23: Individual 2025 | EP23: Daniela Sarmiento | EQ23: Reagendó | ER23: Morelos C2 | ES23: $420 | HD23: S | HE23: Particular | HF23: Edson Alejandro Cabello Sanchez | HG23: Individual 2025 | HH23: Daniela Sarmiento | HI23: Asistió | HJ23: Morelos C2 | HK23: $420 | HL23: Transf - 1872 | JV23: N | JW23: Particular | JX23: Juan Diego López Balderas | JY23: Individual 2025 | JZ23: Benjamin Villagomez | KA23: Asistió | KB23: Guanajuato C3 | KC23: 380 | KD23: Tarjeta | KE23: 0.0625
A24: 0.041666667 | B24: S | C24: Particular | D24: Miguel Ángel Torres Mata | E24: Individual 2025 | F24: Benjamin Villagomez | G24: Asistió | H24: Guanajuato C3 | I24: 420 | J24: Efectivo | K24: 1:30pm | BT24: S | BU24: Particular | BV24: Jorge Alejandro Salazar Oyervides | BW24: Individual 2025 | BX24: José Arcadio | BY24: Confirmó | BZ24: Morelos C1 | CA24: $420 | CB24: Efectivo | EL24: S | EM24: Particular | EN24: Jorge Torres | EO24: Individual 2025 | EP24: Enrique Luna | EQ24: Asistió | ER24: Guanajuato C1 | ES24: 850 | ET24: Efectivo | JV24: S | JW24: Particular | JX24: Jorge Torres | JY24: Individual 2025 | JZ24: Enrique Luna | KA24: Asistió | KB24: Guanajuato C1 | KC24: 850 | KD24: Tarjeta
A25: 0.041666667 | B25: S | C25: Particular | D25: Felipe de Jesús Carreón López | E25: Individual 2025 | F25: Fabiola Fragoso | G25: Asistió | H25: Guanajuato C2 | I25: 420 | J25: Tarjeta | K25: 1:15pm | EL25: N | EM25: Particular | EN25: Miguel Ángel Torres Mata | EO25: Individual 2025 | EP25: Benjamin Villagomez | EQ25: Canceló | ER25: Guanajuato C3 | ES25: 420 | EU25: 0.0625
A26: 0.041666667 | EL26: S | EM26: Particular | EN26: Felipe de Jesús Carreón López | EO26: Individual 2025 | EP26: Fabiola Fragoso | EQ26: Canceló | ER26: Guanajuato C2 | ES26: 420
A27: 0.083333333 | B27: S | C27: GIASA | D27: Diego Armando Onofre Montalvo | E27: Individual 2025 | F27: Benjamin Villagomez | G27: Asistió | H27: Guanajuato C3 | I27: 0 | J27: Pase | K27: 2:30pm | AF27: S | AG27: Particular | AH27: Isaac Santiago Arriaga Lozano | AI27: Infantil | AJ27: Gloria Sarmiento | AK27: Asistió | AL27: Morelos C1 | AM27: $350 | AN27: Efectivo | BJ27: N | BK27: Particular | BL27: Ángela Sofía Sánchez Guardiola | BM27: Infantil | BN27: Gloria Sarmiento | BO27: Confirmó | BP27: Morelos C1 | BQ27: 480 | BR27: Efectivo | BT27: N | BU27: Particular | BV27: Daniel Emiliano Valdes Herrera | BW27: Individual 2025 | BX27: Fabiola Fragoso | BY27: Confirmó | BZ27: Guanajuato C1 | CA27: 420 | CN27: S | CO27: NEAPCO | CP27: Santiago de Jesús Romero Almaguer | CQ27: Individual 2025 | CR27: Gloria Sarmiento | CS27: Asistió | CT27: Morelos C2 | CU27: 0 | CV27: Pase | CX27: S | CY27: Particular | CZ27: Isaac Santiago Arriaga Lozano | DA27: Infantil | DB27: Gloria Sarmiento | DC27: Asistió | DD27: Morelos C2 | DE27: $350 | DF27: Transf - 1872 | EB27: N | EC27: Particular | ED27: Isaac Everardo López | EE27: Infantil | EF27: Gloria Sarmiento | EH27: Morelos C2 | EI27: 480 | EL27: N | EM27: Particular | EN27: Hugo Torres | EO27: Individual 2025 | EP27: Enrique Luna | EQ27: Confirmó | ER27: Guanajuato C1 | ES27: 850 | ET27: Tarjeta | FP27: S | FQ27: Particular | FR27: Isaac Santiago Arriaga Lozano | FS27: Infantil | FT27: Gloria Sarmiento | FU27: Confirmó | FV27: Morelos C2 | FW27: $350 | GT27: S | GU27: Particular | GV27: Neithan Sebastián flores Rangel | GW27: Infantil | GX27: Gloria Sarmiento | GY27: Reagendó | GZ27: Morelos C2 | HA27: 480 | HD27: S | HE27: Particular | HF27: Felipe de Jesús Carreón López | HG27: Individual 2025 | HH27: Fabiola Fragoso | HI27: Confirmó | HJ27: Guanajuato C2 | HK27: 420 | HL27: Tarjeta | IH27: S | II27: Dorothea | IJ27: Carla Reynosa Siller | IK27: Individual 2025 | IL27: Lucía Sánchez | IM27: Asistió | IN27: Guanajuato C2 | IO27: 350 | IP27: Transf - 1872 | JB27: N | JC27: Particular | JD27: Daniela Huerta Ovalle | JE27: Individual 2025 | JF27: María de la Luz | JG27: Confirmó | JH27: Guanajuato C1 | JI27: 0 | JJ27: Gratuito | JK27: 45717 | JL27: S | JM27: Particular | JN27: Neithan Sebastián flores Rangel | JO27: Infantil | JP27: Gloria Sarmiento | JQ27: No confirmó | JR27: Morelos C2 | JS27: 480 | JV27: S | JW27: GIASA | JX27: Diego Armando Onofre Montalvo | JY27: Individual 2025 | JZ27: Benjamin Villagomez | KA27: Pendiente REAG | KB27: Guanajuato C3 | KC27: 0 | KD27: Pase
A28: 0.083333333 | B28: N | C28: Particular | D28: Gerardo Dominguez Mendez | E28: Individual 2025 | F28: Enrique Luna | G28: Asistió | H28: Guanajuato C1 | I28: $700 | J28: Efectivo | K28: 2:30pm | BL28: Renta de espacio | BM28: Renta de espacios - Asociados | BN28: Alondra Escalon | BO28: Confirmó | BP28: Morelos C2 | BQ28: $125 | BS28: 0.10416667 | BT28: S | BU28: NEAPCO | BV28: Derek Daniel Salas | BW28: Infantil | BX28: Daniela Sarmiento | BY28: Confirmó | BZ28: Morelos C2 | CA28: 0 | CB28: Pase | FP28: S | FQ28: Dorothea | FR28: Carla Reynosa Siller | FS28: Individual 2025 | FT28: Lucía Sánchez | FU28: Confirmó | FV28: Guanajuato C2 | FW28: 350 | FX28: Efectivo | GT28: N | GU28: Particular | GV28: Carlos Enrique Escobar Pérez | GW28: Individual 2025 | GX28: Maricela Sena | GY28: Confirmó | GZ28: Guanajuato C1 | HA28: 420 | HD28: S | HE28: NEAPCO | HF28: Derek Daniel Salas | HG28: Infantil | HH28: Daniela Sarmiento | HI28: Confirmó | HJ28: Morelos C2 | HK28: 0 | HL28: Pase | IH28: N | II28: Particular | IJ28: Isaac Santiago Arriaga Lozano | IK28: Infantil | IL28: Gloria Sarmiento | IM28: Asistió | IN28: Morelos C2 | IO28: 350 | IP28: Efectivo | IQ28: lo paga Arcadio $350 | JV28: S | JW28: Dorothea | JX28: Carla Reynosa Siller | JY28: Individual 2025 | JZ28: Enrique Luna | KA28: Reagendó | KB28: Guanajuato C1 | KC28: 770
A29: 0.083333333 | B29: S | C29: Cáritas de Saltillo | D29: Victoria Valentina Velázquez Vazquez | E29: Individual 2025 | F29: Daniela Sarmiento | G29: Asistió | H29: Morelos C1 | I29: 249 | J29: Transf - 1872 | BT29: S | BU29: Particular | BV29: Maria Fernanda Medina | BW29: Individual 2025 | BX29: Javier Martínez | BY29: Confirmó | BZ29: Guanajuato C1 | CA29: 420 | EB29: N | EC29: Particular | ED29: Eder Isarael Magallanes VIllanueva | EE29: Individual 2025 | EF29: Fabiola Fragoso | EH29: Guanajuato C2 | EI29: 350 | EK29: 0.10416667 | JV29: N | JW29: Particular | JX29: Angel Mateo García González y Nicole García González | JY29: Infantil | JZ29: Fabiola Fragoso | KA29: Asistió | KB29: Guanajuato C2 | KC29: 400 | KD29: Efectivo
A30: 0.083333333 | B30: S | C30: Particular | D30: Farid y Karim Valenzuela Celestino | E30: Infantil | F30: Perla Realme | G30: No llegó | H30: Guanajuato C2 | I30: 480 | J30: Efectivo | K30: 2:30pm | BT30: N | BU30: UTS | BV30: Carlos Amauri Garcia Peña | BW30: Médica psiquiatrica | BX30: Enrique Luna | BY30: Confirmó | BZ30: Guanajuato C1 | CA30: 770 | JV30: N | JW30: NEAPCO | JX30: Joksan Ishbak Cruz Torres | JY30: Individual 2025 | JZ30: Daniela Sarmiento | KA30: Asistió | KB30: Morelos C2 | KC30: 0 | KD30: Pase
A31: 0.083333333
A32: 0.125 | B32: N | C32: Dorothea | D32: Carla Reynosa Siller | E32: Individual 2025 | F32: Enrique Luna | G32: Asistió | H32: Guanajuato C1 | I32: 770 | J32: Transf - 1872 | K32: 3:30pm | V32: N | W32: Particular | X32: Kevin Alexander Reyes Herrera | Y32: Individual 2025 | Z32: Gloria Sarmiento | AA32: Asistió | AB32: Morelos C1 | AC32: 420 | AF32: N | AG32: Particular | AH32: Paola Nicole almanza García | AI32: Infantil | AJ32: Gloria Sarmiento | AK32: No llegó | AL32: Morelos C1 | AM32: 480 | AP32: S | AQ32: Particular | AR32: Ricardo Guadalupe López Ramos | AS32: Individual 2025 | AT32: Lucía Sánchez | AU32: Confirmó | AV32: Guanajuato C2 | AW32: 420 | AX32: Tarjeta | AZ32: S | BA32: Particular | BB32: Orlando Trejo Herrera | BC32: Individual 2025 | BD32: Gloria Sarmiento | BE32: Confirmó | BF32: Morelos C2 | BG32: 420 | BH32: Efectivo | BJ32: S | BK32: Particular | BL32: Ma. De Lourdes Reyes Rivera | BM32: Individual 2025 | BN32: Maricela Sena | BO32: Confirmó | BP32: Guanajuato C1 | BQ32: 0 | BR32: Gratuito | BT32: N | BU32: Cáritas de Saltillo | BV32: Victoria Valentina Velázquez Vazquez | BW32: Individual 2025 | BX32: Daniela Sarmiento | BY32: Reagendó | BZ32: Morelos C1 | CA32: 249 | CN32: N | CO32: Particular | CP32: Fabiola Alejandra Hernández Chacon | CQ32: Individual 2025 | CR32: Gloria Sarmiento | CS32: Asistió | CT32: Morelos C2 | CU32: 420 | CV32: Efectivo | CX32: S | CY32: Particular | CZ32: Orlando Trejo Herrera | DA32: Infantil | DB32: Gloria Sarmiento | DC32: Asistió | DD32: Morelos C2 | DE32: $380 | DF32: Efectivo | DG32: se le debían de la sesión pasada | DH32: S | DI32: Particular | DJ32: Diana Esthela De León Dueñaz | DK32: Individual 2025 | DL32: Rosy Macias | DM32: Pendiente REAG | DN32: Morelos C2 | DO32: 420 | DP32: Efectivo | EB32: N | EC32: Particular | ED32: Graman Gallegos Colunga | EE32: Individual 2025 | EF32: Alondra Escalon | EG32: Confirmó | EH32: Morelos C1 | EI32: $420 | EJ32: Transf - 1872 | EL32: S | EM32: Particular | EN32: Mario Zamarripa | EO32: Familiar | EP32: Maricela Sena | EQ32: Reagendó | ER32: Guanajuato C3 | ES32: 520 | FP32: N | FQ32: Particular | FR32: Kevin Alexander Reyes Herrera | FS32: Individual 2025 | FT32: Gloria Sarmiento | FU32: Reagendó | FV32: Morelos C1 | FW32: 420 | FZ32: S | GA32: Particular | GB32: Ricardo Guadalupe López Ramos | GC32: Individual 2025 | GD32: Lucía Sánchez | GE32: Asistió | GF32: Guanajuato C2 | GG32: 420 | GH32: Tarjeta | GT32: S | GU32: INSUNTE | GV32: Alan Mitsael Flores Vazquez | GW32: Individual 2025 | GX32: Maricela Sena | GY32: Confirmó | GZ32: Guanajuato C1 | HA32: 300 | HB32: Tarjeta | HD32: S | HE32: Cáritas de Saltillo | HF32: Victoria Valentina Velázquez Vazquez | HG32: Individual 2025 | HH32: Daniela Sarmiento | HI32: Confirmó | HJ32: Morelos C1 | HK32: 249 | HX32: N | HY32: Particular | HZ32: Kevin Alexander Reyes Herrera | IA32: Individual 2025 | IB32: Gloria Sarmiento | IC32: Reagendó | ID32: Morelos C1 | IE32: 420 | IH32: N | II32: Particular | IJ32: Karen Gabriela Morales Ortega | IK32: Individual 2025 | IL32: Gloria Sarmiento | IM32: Asistió | IN32: Morelos C2 | IO32: 420 | IP32: Transf - 1872 | IR32: S | IS32: Particular | IT32: Ricardo Guadalupe López Ramos | IU32: Individual 2025 | IV32: Lucía Sánchez | IW32: Reagendó | IX32: Guanajuato C2 | IY32: 420 | JB32: N | JC32: Particular | JD32: Graman Gallegos Colunga | JE32: Individual 2025 | JF32: Alondra Escalon | JG32: Reagendó | JH32: Morelos C1 | JI32: $420 | JL32: S | JM32: Particular | JN32: Alberto de Jesús Ramos Barrientos | JO32: Individual 2025 | JP32: Gloria Sarmiento | JQ32: Asistió | JR32: Morelos C2 | JS32: 340 | JT32: Efectivo | JV32: N | JW32: Particular | JX32: Yuritzy Lucero Mtz / Yaritza Sarahí Mtz | JY32: Infantil | JZ32: Daniela Sarmiento | KA32: Asistió | KB32: Morelos C1 | KC32: 550
A33: 0.125 | B33: S | C33: Particular | D33: Sandra Yudith García Dávila | E33: Familiar | F33: Daniela Sarmiento | G33: Pendiente REAG | H33: Morelos C2 | I33: 550 | AF33: N | AG33: Particular | AH33: Diana Esthela De León Dueñaz | AI33: Individual 2025 | AJ33: Rosy Macias | AK33: Asistió | AL33: Morelos C2 | AM33: 420 | AN33: Efectivo | AP33: N | AQ33: Particular | AR33: Alberto Gael Zavala Rios | AS33: Individual 2025 | AT33: Gloria Sarmiento | AU33: Confirmó | AV33: Morelos C1 | AW33: 480 | AX33: Efectivo | BJ33: N | BK33: NEAPCO | BL33: Santiago de Jesús Romero Almaguer | BM33: Infantil | BN33: Gloria Sarmiento | BO33: Confirmó | BP33: Morelos C1 | BQ33: 0 | BR33: Pase | BW33: Renta de espacios - Asociados | BX33: Enrique Luna | BY33: Confirmó | BZ33: Guanajuato C3 | CA33: 125 | CN33: S | CO33: Dorothea | CP33: Andrea Guadalupe Padilla Resendiz | CQ33: Individual 2025 | CR33: Alondra Escalon | CS33: Pendiente REAG | CT33: Morelos C1 | DH33: S | DI33: Particular | DJ33: Ricardo Guadalupe López Ramos | DK33: Individual 2025 | DL33: Lucía Sánchez | DM33: Reagendó | DN33: Guanajuato C2 | DO33: 420 | DP33: Tarjeta | EB33: S | EC33: Particular | ED33: Ma. De Lourdes Reyes Rivera | EE33: Individual 2025 | EF33: Maricela Sena | EG33: No llegó | EH33: Guanajuato C1 | EI33: 0 | EJ33: Gratuito | EL33: N | EM33: Particular | EN33: Alexis Reyes | EO33: Individual 2025 | EP33: Fabiola Fragoso | EQ33: Pendiente REAG | ER33: Guanajuato C1 | ES33: 420 | FZ33: N | GA33: NEAPCO | GB33: Fe Garay | GC33: Individual 2025 | GD33: Gloria Sarmiento | GE33: Confirmó | GF33: Morelos C1 | GG33: 0 | GH33: Pase | HD33: N | HE33: Particular | HF33: Nancy Guadalupe Gomez Resendiz | HG33: Individual 2025 | HH33: Rosa María Gómez | HI33: No llegó | HJ33: Morelos C1 | HK33: $420 | HL33: Efectivo | IR33: N | IS33: Particular | IT33: Carlos Arturo García Limón | IU33: Individual 2025 | IV33: Gloria Sarmiento | IW33: Asistió | IX33: Morelos C2 | IY33: 420 | IZ33: Efectivo | JV33: S | JW33: Particular | JX33: Rosita Ramirez Ramos | JY33: Individual 2025 | JZ33: Javier Martínez | KA33: Asistió | KB33: Guanajuato C2 | KC33: 420 | KD33: Tarjeta
A34: 0.125 | B34: S | C34: Particular | D34: Leticia Telles Rodriguez | E34: Individual 2025 | F34: Daniela Sarmiento | H34: Morelos C2 | I34: $380 | AF34: S | AG34: Particular | AH34: Ma. De Lourdes Reyes Rivera | AI34: Individual 2025 | AJ34: Maricela Sena | AK34: Pendiente REAG | AL34: Guanajuato C1 | AM34: 0 | AN34: Gratuito | BT34: N | BU34: Particular | BV34: Sandra Yudith García Dávila | BW34: Familiar | BX34: Daniela Sarmiento | BY34: Confirmó | BZ34: Morelos C2 | CA34: 550 | DH34: N | DI34: Particular | DJ34: Alberto Gael Zavala Rios | DK34: Individual 2025 | DL34: Gloria Sarmiento | DM34: No llegó | DN34: Morelos C1 | DO34: 480 | DP34: Efectivo | EB34: N | EC34: Particular | ED34: Neithan Sebastián flores Rangel | EE34: Infantil | EF34: Gloria Sarmiento | EG34: Confirmó | EH34: Morelos C2 | EI34: 480 | EJ34: Transf - 1872 | EL34: N | EM34: Particular | EN34: Sandra Yudith García Dávila | EO34: Familiar | EP34: Daniela Sarmiento | EQ34: No confirmó | ER34: Morelos C2 | ES34: 550 | JV34: S | JW34: GIASA | JX34: Marco Antonio Hinojosa Hernández | JY34: Consulta psiquiatrica | JZ34: Enrique Luna | KA34: Asistió | KB34: Guanajuato C1 | KC34: 0 | KD34: Pase
A35: 0.125 | EL35: S | EM35: Particular | EN35: Jorge Arturo Rodríguez Perales | EO35: Individual 2025 | EP35: Fabiola Fragoso | EQ35: Confirmó | ER35: Guanajuato C1 | ES35: 250 | JV35: N | JW35: Particular | JX35: Elizabeth Jaimes Quiroz | JY35: Infantil | JZ35: Gloria Sarmiento | KA35: Confirmó | KB35: Morelos C1 | KC35: 480 | KD35: Efectivo
A36: 0.125 | EL36: N | EM36: Particular | EN36: Damian Ávalos | EO36: Consulta psiquiatrica | EP36: Enrique Luna | EQ36: Confirmó | ER36: ZOOM C1 | EU36: No se el costo
A37: 0.16666667 | B37: S | C37: Particular | D37: Jimena Torres Herrera | E37: Individual 2025 | F37: Fabiola Fragoso | G37: Reagendó | H37: Guanajuato C2 | I37: 420 | V37: S | W37: Particular | X37: Daniel Emiliano Martinez González | Y37: Individual 2025 | Z37: Gloria Sarmiento | AA37: Reagendó | AB37: Morelos C2 | AC37: $420 | AF37: S | AG37: Particular | AH37: Celic Garcia | AI37: Individual 2025 | AJ37: Javier Martínez | AK37: Asistió | AL37: Guanajuato C3 | AM37: 280 | AN37: Transf - 1872 | AP37: S | AQ37: Particular | AR37: Isabel Salazar Contreras | AS37: Individual 2025 | AT37: Rosy Macias | AU37: Pendiente REAG | AV37: Morelos C1 | AW37: $420 | AZ37: S | BA37: Particular | BB37: Mervin | BC37: Individual 2025 | BD37: José Arcadio | BE37: Confirmó | BF37: zoom | BG37: $600 | BH37: Transf - 1872 | BJ37: S | BK37: Particular | BL37: Yuliana Rodriguez Vazquez | BM37: Individual 2025 | BN37: Rosy Macias | BO37: Reagendó | BP37: Morelos C1 | BQ37: 340 | CN37: N | CO37: Particular | CP37: Mateo Vázquez Pérez | CQ37: Individual | CR37: Gloria Sarmiento | CS37: Asistió | CT37: Morelos C2 | CU37: 480 | CV37: Efectivo | CX37: N | CY37: Particular | CZ37: Carlos Daniel Montes Reyes | DA37: Infantil | DB37: Gloria Sarmiento | DC37: No confirmó | DD37: Morelos C2 | DE37: 480 | DH37: N | DI37: Particular | DJ37: Adín Siddhartha Valles Aguirre | DK37: Individual 2025 | DL37: Lucía Sánchez | DM37: Asistió | DN37: Guanajuato C1 | DO37: $420 | DP37: Tarjeta | DR37: S | DS37: Particular | DT37: Mervin | DU37: Individual 2025 | DV37: José Arcadio | DW37: Confirmó | DX37: zoom | DY37: $600 | DZ37: Transf - 1872 | EB37: N | EC37: Particular | ED37: Ángel Alejandro Robles Peralta | EE37: Individual 2025 | EF37: Fabiola Fragoso | EG37: Confirmó | EH37: Guanajuato C2 | EI37: 450 | EJ37: Transf - 1872 | FP37: S | FQ37: Particular | FR37: Angela Abigail Juarez Hernández | FS37: Individual 2025 | FT37: Rosy Macias | FU37: Asistió | FV37: Morelos C1 | FW37: 400 | FZ37: S | GA37: Particular | GB37: Alberto de Jesús Ramos Barrientos | GC37: Individual 2025 | GD37: Gloria Sarmiento | GE37: Pendiente REAG | GF37: Morelos C2 | GG37: 340 | GH37: Efectivo | GT37: S | GU37: Particular | GV37: Carolina Medellín | GW37: Individual | GX37: Javier Martínez | GY37: Confirmó | GZ37: Guanajuato C3 | HA37: 420 | HB37: Tarjeta | HD37: N | HE37: Particular | HF37: Isaías Hernández Lara | HG37: Individual 2025 | HH37: Daniela Sarmiento | HI37: Confirmó | HJ37: Morelos C1 | HK37: 420 | HL37: Transf - 1872 | IH37: N | II37: Particular | IJ37: María de Lourdes Martinez Reyna | IK37: Individual 2025 | IL37: Rosy Macias | IM37: Asistió | IN37: Morelos C1 | IO37: 420 | IP37: Efectivo | IR37: S | IS37: Particular | IT37: Gerardo Dominguez Mendez | IU37: Individual 2025 | IV37: Enrique Luna | IW37: Reagendó | IX37: Guanajuato C1 | IY37: $700 | JB37: S | JC37: NEAPCO | JD37: Santiago de Jesús Romero Almaguer | JE37: Individual 2025 | JF37: Gloria Sarmiento | JG37: Confirmó | JH37: Morelos C2 | JI37: 0 | JJ37: Pase | JK37: 0.16666667 | JL37: S | JM37: Particular | JN37: Alejandro Lozano | JO37: Individual 2025 | JP37: Ana Juarez | JQ37: Canceló | JR37: Guanajuato C3 | JS37: 420 | JV37: N | JW37: NEAPCO | JX37: Julio Alejandro Moreno Moncada | JY37: Individual 2025 | JZ37: Rosa María Gómez | KA37: No llegó | KB37: Morelos C1 | KC37: 0 | KD37: Pase
A38: 0.16666667 | D38: Renta de espacio | E38: Renta de espacios - Asociados | F38: Enrique Luna | G38: Asistió | H38: Guanajuato C1 | I38: 125 | K38: 4:30pm | V38: N | W38: Particular | X38: Thelma Gabriela Sánchez Sánchez | Y38: Individual 2025 | Z38: Lucía Sánchez | AA38: Reagendó | AB38: Guanajuato C2 | AC38: 420 | AP38: S | AQ38: Particular | AR38: Alberto de Jesús Ramos Barrientos | AS38: Individual 2025 | AT38: Gloria Sarmiento | AU38: Confirmó | AV38: Morelos C2 | AW38: 340 | AX38: Efectivo | BJ38: S | BK38: Particular | BL38: Daniel Emiliano Martinez González | BM38: Individual 2025 | BN38: Gloria Sarmiento | BO38: Confirmó | BP38: Morelos C2 | BQ38: $420 | BR38: Efectivo | BT38: N | BU38: Particular | BV38: Martha Johana Torres Salinas | BW38: Consulta psiquiatrica | BX38: Enrique Luna | BY38: Confirmó | BZ38: Guanajuato C1 | CA38: $850 | CX38: S | CY38: Particular | CZ38: Angela Abigail Juarez Hernández | DA38: Individual 2025 | DB38: Rosy Macias | DC38: Asistió | DD38: Morelos C1 | DE38: 400 | DH38: N | DI38: Particular | DJ38: Ana Cristina Morales Martinez | DK38: Individual 2025 | DL38: Alondra Escalon | DM38: Asistió | DN38: Morelos C3 | DO38: 420 | DP38: Tarjeta | DR38: N | DS38: Dorothea | DT38: Carla Reynosa Siller | DU38: Individual 2025 | DV38: Lucía Sánchez | DW38: Pendiente REAG | DX38: Guanajuato C2 | DY38: 350 | EB38: S | EC38: Particular | ED38: Yuliana Rodríguez Vázquez | EE38: Individual 2025 | EF38: Rosy Macias | EG38: Confirmó | EH38: Morelos C1 | EI38: 340 | EJ38: Efectivo | EL38: N | EM38: GIASA | EN38: Juan Angel Martínez Tapia | EO38: Individual 2025 | EP38: David Bermejo | EQ38: No llegó | ER38: ZOOM C1 | ES38: 0 | ET38: Pase | FZ38: S | GA38: Particular | GB38: Diana Esthela De León Dueñaz | GC38: Individual 2025 | GD38: Rosy Macias | GE38: Confirmó | GF38: Morelos C2 | GG38: 420 | GH38: Efectivo | GT38: S | GU38: Particular | GV38: Daniel Emiliano Martinez González | GW38: Individual 2025 | GX38: Gloria Sarmiento | GY38: Confirmó | GZ38: Morelos C2 | HA38: $420 | HB38: Efectivo | HD38: S | HE38: Particular | HF38: Jimena Torres Herrera | HG38: Individual 2025 | HH38: Fabiola Fragoso | HI38: Confirmó | HJ38: Guanajuato C2 | HK38: 420 | HL38: Efectivo | IR38: N | IS38: Particular | IT38: Armando Adrián García Medina | IU38: Individual 2025 | IV38: Gloria Sarmiento | IW38: No llegó | IX38: Morelos C1 | IY38: 420 | IZ38: Transf - 1872 | JL38: S | JM38: Particular | JN38: Yuliana Rodríguez Vázquez | JO38: Individual 2025 | JP38: Rosy Macias | JQ38: Asistió | JR38: Morelos C1 | JS38: 420 | JT38: Efectivo | JX38: Renta de espacio | JY38: Individual 2025 | JZ38: Enrique Luna | KA38: Canceló | KB38: Guanajuato C1 | KC38: 125
A39: 0.16666667 | AP39: N | AQ39: Particular | AR39: Adín Siddhartha Valles Aguirre | AS39: Individual 2025 | AT39: Lucía Sánchez | AU39: Confirmó | AV39: Guanajuato C1 | AW39: $420 | AX39: Tarjeta | BJ39: N | BK39: Dorothea | BL39: Carla Reynosa Siller | BM39: Individual 2025 | BN39: Alondra Escalon | BO39: Pendiente REAG | BP39: Morelos C1 | BQ39: 350 | CX39: N | CY39: Particular | CZ39: Habid Asael Rojas Nuncio | DA39: Individual 2025 | DB39: Alondra Escalon | DC39: Asistió | DD39: Morelos C1 | DE39: 420 | DJ39: Renta de Espacio | DK39: Individual 2025 | DL39: Enrique Luna | DN39: Guanajuato C2 | DO39: 120 | EB39: S | EC39: INSUNTE | ED39: Alan Mitsael Flores Vazquez | EE39: Individual 2025 | EF39: Maricela Sena | EG39: Confirmó | EH39: Guanajuato C1 | EI39: 300 | EJ39: Tarjeta | FZ39: S | GA39: Particular | GB39: Adín Siddhartha Valles Aguirre | GC39: Individual 2025 | GD39: Lucía Sánchez | GE39: Confirmó | GF39: Guanajuato C1 | GG39: $420 | GH39: Tarjeta | GT39: N | GU39: Particular | GV39: Cirilo flores Hernández | GW39: Individual 2025 | GX39: Maricela Sena | GY39: No llegó | GZ39: Guanajuato C1 | HA39: $420 | IR39: S | IS39: Particular | IT39: Adín Siddhartha Valles Aguirre | IU39: Individual 2025 | IV39: Lucía Sánchez | IW39: No confirmó | IX39: Guanajuato C1 | IY39: $420
A40: 0.16666667 | AP40: N | AQ40: Particular | AR40: Ana Cristina Morales Martinez | AS40: Individual 2025 | AT40: Alondra Escalon | AU40: Confirmó | AV40: Morelos C3 | AW40: 420 | AX40: Transf - 1872 | BJ40: S | BK40: Particular | BL40: Alejandro Lozano | BM40: Individual 2025 | BN40: Ana Juarez | BO40: Reagendó | BP40: Guanajuato C2 | BQ40: 420 | EB40: S | EC40: Particular | ED40: Alejandro Lozano | EE40: Individual 2025 | EF40: Ana Juarez | EG40: Reagendó | EH40: Guanajuato C3 | EI40: 420 | EJ40: Transf - 1872 | EL40: S | EM40: Particular | EN40: Maria Fernanda Rodriguez Daniel | EO40: Consulta psiquiatrica | EP40: Enrique Luna | EQ40: Confirmó | ER40: Guanajuato C1 | ES40: 850 | ET40: Tarjeta | FP40: S | FQ40: NEAPCO | FR40: Santiago de Jesús Romero Almaguer | FS40: Individual 2025 | FT40: Gloria Sarmiento | FU40: Asistió | FV40: Morelos C2 | FW40: 0 | FX40: Pase | FZ40: N | GA40: Particular | GB40: Ana Cristina Morales Martinez | GC40: Individual 2025 | GD40: Alondra Escalon | GE40: Confirmó | GF40: Morelos C3 | GG40: 420 | IR40: N | IS40: Particular | IT40: Ana Cristina Morales Martinez | IU40: Individual 2025 | IV40: Alondra Escalon | IW40: Asistió | IX40: Morelos C3 | IY40: 420 | IZ40: Transf - 1872 | JL40: S | JM40: Particular | JN40: Daniel Emiliano Martinez González | JO40: Individual 2025 | JP40: Gloria Sarmiento | JQ40: Asistió | JR40: Morelos C2 | JS40: $420 | JT40: Efectivo
A41: 0.16666667 | AR41: Renta de espacio | AS41: Renta de espacios - Asociados | AT41: Enrique Luna | AU41: Confirmó | AV41: Guanajuato C1 | AW41: 125 | EB41: S | EC41: NEAPCO | ED41: Santiago de Jesús Romero Almaguer | EE41: Individual 2025 | EF41: Gloria Sarmiento | EG41: Confirmó | EH41: Morelos C2 | EI41: 0 | EJ41: Pase | EK41: 0.16666667 | FZ41: S | GA41: Particular | GB41: Samuel Valles Aguirre | GC41: Individual 2025 | GD41: Enrique Luna | GE41: Confirmó | GF41: Guanajuato C2 | GG41: 850 | GH41: Tarjeta | IR41: S | IS41: Particular | IT41: Angela Abigail Juarez Hernández | IU41: Individual 2025 | IV41: Rosy Macias | IW41: Reagendó | IX41: Morelos C1 | IY41: 400 | JL41: S | JM41: Particular | JN41: Graman Gallegos Colunga | JO41: Individual 2025 | JP41: Alondra Escalon | JQ41: Asistió | JR41: Morelos C1 | JS41: $420 | JT41: Transf - 1872
A42: 0.20833333 | D42: Renta de espacio | E42: Renta Abasolo- Independiente | F42: Enrique Luna | G42: Asistió | H42: Guanajuato C1 | I42: 125 | K42: 5:30pm | V42: S | W42: Particular | X42: Juan Felipe Castillo Reyna | Y42: Individual 2025 | Z42: Gloria Sarmiento | AA42: No llegó | AB42: Morelos C2 | AC42: 370 | AD42: Efectivo | AF42: S | AG42: NEAPCO | AH42: Guillermo Medina | AI42: Individual 2025 | AJ42: José Arcadio | AK42: Asistió | AL42: Colinas C1 | AM42: 0 | AN42: Pase | AO42: 0.22916667 | AP42: N | AQ42: Particular | AR42: Samuel valles | AS42: Infantil | AT42: Lucía Sánchez | AU42: Confirmó | AV42: Guanajuato C2 | AW42: $480 | AX42: Tarjeta | AZ42: S | BA42: Particular | BB42: Erika Delgado Villanueva | BC42: Individual 2025 | BD42: José Arcadio | BE42: Confirmó | BF42: Morelos C1 | BG42: $420 | BH42: Efectivo | BI42: 0.22916667 | BJ42: S | BK42: INSUNTE | BL42: Perla Veronica Flores Torres | BM42: Individual 2025 | BN42: Rosy Macias | BO42: Reagendó | BP42: Morelos C1 | BQ42: 300 | CN42: N | CO42: Particular | CP42: Ileana Daniela Muñoz Sánchez | CQ42: Individual 2025 | CR42: Fabiola Fragoso | CS42: Pendiente REAG | CT42: Guanajuato C1 | CU42: 420 | CZ42: Renta de espacio | DA42: Renta de espacios - Asociados | DB42: Rosy Macias | DC42: Asistió | DD42: Morelos C1 | DH42: S | DI42: Particular | DJ42: Jonas Alejandro Morales | DK42: Individual 2025 | DL42: José Arcadio | DM42: Reagendó | DN42: ZOOM C1 | DO42: $420 | DQ42: 0.22916667 | DR42: N | DS42: Particular | DT42: Ileana Daniela Muñoz Sánchez | DU42: Individual 2025 | DV42: Fabiola Fragoso | DW42: No llegó | DX42: Guanajuato C1 | DY42: 420 | DZ42: Transf - 1872 | FF42: S | FG42: Particular | FH42: Magaly Martínez | FI42: Individual | FJ42: José Arcadio | FK42: Asistió | FL42: Morelos C3 | FM42: $350 | FO42: 0.22916667 | FP42: S | FQ42: NEAPCO | FR42: Guillermo Neapco | FS42: Individual 2025 | FT42: José Arcadio | FU42: N | FV42: Particular | FW42: Monserrat Hernández | FX42: Individual 2025 | FY42: Javier Martínez | FZ42: Asistió | GA42: Guanajuato C1 | GB42: $420 | GC42: Pareja | GD42: Rosy Macias | GE42: Confirmó | GF42: Morelos C3 | GG42: $520 | GH42: Efectivo | GJ42: S | GK42: Particular | GL42: Jorge Alejandro Salazar Oyervides | GM42: Individual 2025 | GN42: José Arcadio | GO42: Reagendó | GP42: Morelos C1 | GQ42: $420 | GS42: 5.30 | GT42: S | GU42: INSUNTE | GV42: Perla Veronica Flores Torres | GW42: Individual 2025 | GX42: Rosy Macias | GY42: Reagendó | GZ42: Morelos C1 | HA42: 300 | HB42: Efectivo | HD42: S | HE42: Particular | HF42: Sofía Holguín Muñiz | HG42: Individual 2025 | HH42: Fabiola Fragoso | HI42: Confirmó | HJ42: Guanajuato C1 | HK42: 420 | HX42: S | HY42: Particular | HZ42: Thelma Gabriela Sánchez Sánchez | IA42: Individual 2025 | IB42: Lucía Sánchez | IC42: Reagendó | ID42: Guanajuato C2 | IE42: 420 | IF42: Transf - 1872 | IH42: S | II42: Particular | IJ42: Jorge Alejandro Salazar Oyervides | IK42: Individual 2025 | IL42: José Arcadio | IM42: No confirmó | IN42: Colinas C1 | IO42: 420 | IQ42: 0.22916667 | IR42: S | IS42: NEAPCO | IT42: Guillermo Neapco | IU42: Individual 2025 | IV42: José Arcadio | IW42: No confirmó | IX42: Colinas C1 | IY42: $0 | IZ42: Pase | JA42: 0.22916667 | JB42: S | JC42: Particular | JD42: Violeta Berenice Meza Dominguez | JE42: Individual 2025 | JF42: José Arcadio | JG42: Pendiente REAG | JH42: Morelos C1 | JI42: 420 | JK42: 5.30 | JL42: S | JM42: INSUNTE | JN42: Perla Veronica Flores Torres | JO42: Individual 2025 | JP42: Rosy Macias | JQ42: Asistió | JR42: Morelos C1 | JS42: 300 | JT42: Efectivo | JX42: Renta de espacio | JY42: Individual 2025 | JZ42: Enrique Luna | KA42: Confirmó | KB42: Guanajuato C1 | KC42: 125
A43: 0.20833333 | V43: N | W43: Particular | X43: Violeta Berenice Meza Domínguez | Y43: Individual 2025 | Z43: Alondra Escalon | AA43: Asistió | AB43: Morelos C1 | AC43: 420 | AD43: Efectivo | AF43: N | AG43: Particular | AH43: Angela Abigail Juarez Hernández | AI43: Individual 2025 | AJ43: Rosy Macias | AK43: Asistió | AL43: Morelos C1 | AM43: 400 | AN43: Efectivo | AP43: N | AQ43: Particular | AR43: Braulio Liam Galvan Martinez | AS43: Consulta psiquiatrica | AT43: Enrique Luna | AU43: Confirmó | AV43: Guanajuato C1 | AW43: 650 | AZ43: N | BA43: Particular | BB43: Eder Isarael Magallanes VIllanueva | BC43: Individual 2025 | BD43: Fabiola Fragoso | BE43: Confirmó | BF43: Guanajuato C1 | BG43: 420 | BH43: Efectivo | BJ43: S | BK43: Particular | BL43: Jorge Arturo Rodríguez Perales | BM43: Individual 2025 | BN43: Fabiola Fragoso | BO43: Confirmó | BP43: Guanajuato C1 | BQ43: 500 | BR43: Efectivo | CN43: N | CO43: Particular | CP43: Emmanuel Jimenez Maqueda | CQ43: Individual 2025 | CR43: José Arcadio | CS43: Asistió | CT43: Morelos C2 | CU43: $500 | CV43: Efectivo | CW43: EMDR 5:30 | CX43: S | CY43: Particular | CZ43: Jonathan Barrera | DA43: Individual 2025 | DB43: Esmeralda Colunga | DC43: Asistió | DD43: Morelos C3 | DE43: 200 | DF43: Efectivo | DH43: S | DI43: Particular | DJ43: Yael Surisadday Malacara Oviedo | DK43: Individual 2025 | DL43: Alondra Escalon | DM43: Asistió | DN43: Morelos C1 | DO43: 420 | DP43: Efectivo | DR43: S | DS43: Particular | DT43: Gerardo Dominguez Mendez | DU43: Individual 2025 | DV43: José Arcadio | DW43: Reagendó | DX43: Morelos C1 | DY43: $380 | EA43: 0.22916667 | EB43: S | EC43: INSUNTE | ED43: Perla Veronica Flores Torres | EE43: Individual 2025 | EF43: Rosy Macias | EG43: Confirmó | EH43: Morelos C1 | EI43: 300 | EJ43: Efectivo | FP43: S | FQ43: Particular | FR43: Ryan García Lara | FS43: Individual 2025 | FT43: Fabiola Fragoso | FU43: Asistió | FV43: Guanajuato C1 | FW43: 420 | FX43: Tarjeta | FZ43: S | GA43: Particular | GB43: Francisco Andrés García Rangel | GC43: Individual 2025 | GD43: Gloria Sarmiento | GE43: Pendiente REAG | GF43: Morelos C2 | GG43: 420 | GT43: N | GU43: Particular | GV43: Maria Fernanda Rodriguez Daniel | GW43: Evaluación neuropsicológica | GX43: Javier Martínez | GY43: Confirmó | GZ43: Guanajuato C3 | HA43: 420 | HB43: Tarjeta | HD43: N | HE43: Particular | HF43: Yulissa Alvarez Ovalle | HG43: Individual 2025 | HH43: Daniela Sarmiento | HI43: Pendiente REAG | HJ43: Morelos C1 | HK43: 420 | HX43: S | HY43: Particular | HZ43: Ileana Daniela Muñoz Sánchez | IA43: Individual 2025 | IB43: Fabiola Fragoso | IC43: Reagendó | ID43: Guanajuato C1 | IE43: 420 | IF43: Transf - 1872 | IH43: N | II43: Particular | IJ43: Sofia Berenice Martínez | IK43: Infantil | IM43: No confirmó | IN43: Poniente C1 | IO43: 480 | IR43: S | IS43: UTS | IT43: Carlos Amauri García Peña | IU43: Individual 2025 | IV43: Rosy Macias | IW43: Asistió | IX43: Morelos C1 | IY43: $300 | IZ43: Efectivo | JB43: N | JC43: Particular | JD43: Eiren Alejandro Zavala Gallegos | JE43: Individual 2025 | JF43: Gloria Sarmiento | JH43: Morelos C1 | JI43: 480 | JL43: S | JM43: INSUNTE | JN43: Luis Donaldo Sandoval López | JO43: Individual 2025 | JP43: Gloria Sarmiento | JQ43: Asistió | JR43: Morelos C2 | JS43: 300 | JT43: Efectivo
A44: 0.20833333 | V44: N | W44: Particular | X44: Ángel Alejandro Robles Peralta | Y44: Individual 2025 | Z44: Fabiola Fragoso | AA44: Asistió | AB44: Guanajuato C2 | AC44: 450 | AD44: Transf - 1872 | AF44: S | AG44: Particular | AH44: Ryan García Lara | AI44: Individual 2025 | AJ44: Fabiola Fragoso | AK44: Asistió | AL44: Guanajuato C1 | AM44: 420 | AN44: Tarjeta | AP44: N | AQ44: Trabajo social | AR44: Angélica María Marin Loera y José Francisco Gomez Coronado | AS44: Pareja | AT44: Fabiola Fragoso | AU44: Confirmó | AV44: Guanajuato C3 | AW44: 350 | AX44: Efectivo | AZ44: N | BA44: Particular | BB44: Angel Daniel Garcia Ruvalcaba | BC44: Individual 2025 | BD44: Alondra Escalon | BE44: Confirmó | BF44: Morelos C1 | BG44: $420 | BH44: Transf - 1872 | BJ44: N | BK44: Particular | BL44: Marco Antonio Sánchez Pérez | BM44: Individual 2025 | BN44: Gloria Sarmiento | BO44: No llegó | BP44: Morelos C1 | BQ44: $420 | CN44: S | CO44: GIASA | CP44: Karina Rivera | CQ44: Individual 2025 | CR44: Javier Martínez | CS44: Asistió | CT44: ZOOM C1 | CU44: 0 | CV44: Pase | CX44: N | CY44: Particular | CZ44: Fabiola Alejandra Hernández Chacon | DA44: Individual 2025 | DB44: Gloria Sarmiento | DC44: Asistió | DD44: Morelos C2 | DE44: 420 | DF44: Efectivo | DH44: N | DI44: Particular | DJ44: Francisco Andrés García Rangel | DK44: Individual 2025 | DL44: Gloria Sarmiento | DM44: Asistió | DN44: Morelos C2 | DO44: 420 | DP44: Transf - 1872 | DQ44: Paga el Viernes | DR44: S | DS44: Particular | DT44: Juliantla | DU44: Individual 2025 | DV44: José Arcadio | DW44: Confirmó | DX44: Morelos C1 | DY44: $600 | DZ44: Efectivo | FP44: S | FQ44: Particular | FR44: Mariana Denisse Conchis | FS44: Individual 2025 | FT44: Esmeralda Colunga | FU44: Canceló | FV44: Morelos C2 | FW44: 400 | FX44: Efectivo | FZ44: S | GA44: Particular | GB44: Mateo Vázquez Pérez | GC44: Individual | GD44: Gloria Sarmiento | GF44: Morelos C2 | GG44: 480 | GI44: pagara $460 | GT44: S | GU44: INSUNTE | GV44: Luis Donaldo Sandoval López | GW44: Individual 2025 | GX44: Gloria Sarmiento | GY44: Reagendó | GZ44: Morelos C2 | HA44: 300 | HB44: Efectivo | HX44: N | HY44: Particular | HZ44: Zoe Renata Sifuentes Hernández | IA44: Infantil | IB44: Gloria Sarmiento | IC44: Asistió | ID44: Morelos C1 | IE44: 480 | IF44: Efectivo | IH44: N | II44: Particular | IJ44: Fabián Reyna Hipólito y Goretty Rodriguez Lopez | IK44: Pareja | IL44: Fabiola Fragoso | IM44: Confirmó | IN44: Guanajuato C1 | IO44: $520 | IP44: Efectivo | IT44: Renta de espacio | IU44: Renta de espacios - Asociados | IV44: Daniel Salazar | IW44: Canceló | IX44: Guanajuato C2 | IY44: 125 | JB44: N | JC44: Particular | JD44: Mayra Elena Cedillo | JE44: Individual 2025 | JF44: Fabiola Fragoso | JG44: Confirmó | JH44: Guanajuato C1 | JI44: 420 | JL44: S | JM44: INSUNTE | JN44: Alan Mitsael Flores Vazquez | JO44: Individual 2025 | JP44: Maricela Sena | JQ44: Asistió | JR44: Guanajuato C1 | JS44: 300 | JT44: Tarjeta
A45: 0.20833333 | AF45: N | AG45: Particular | AH45: Diego Olivas De La Peña | AI45: Individual 2025 | AJ45: Esmeralda Colunga | AK45: Asistió | AL45: Morelos C1 | AM45: $480 | AP45: S | AQ45: Particular | AR45: Yael Surisadday Malacara Oviedo | AS45: Individual 2025 | AT45: Alondra Escalon | AU45: Confirmó | AV45: Morelos C1 | AW45: 420 | AX45: Transf - 1872 | BJ45: N | BK45: INSUNTE | BL45: Alan Mitsael Flores Vazquez | BM45: Individual 2025 | BN45: Maricela Sena | BO45: Confirmó | BP45: Guanajuato C1 | BQ45: 300 | BR45: Tarjeta | CN45: N | CO45: Particular | CP45: Thelma Gabriela Sánchez Sánchez | CQ45: Individual 2025 | CR45: Lucía Sánchez | CS45: Pendiente REAG | CT45: Guanajuato C2 | CU45: 420 | CX45: S | CY45: NEAPCO | CZ45: Guillermo Neapco | DA45: Individual 2025 | DB45: José Arcadio | DC45: Asistió | DD45: Colinas C1 | DE45: $0 | DF45: Pase | DG45: 0.22916667 | DH45: N | DI45: Particular | DJ45: Miriam Roca Montes | DK45: Individual 2025 | DL45: Enrique Luna | DM45: Pendiente REAG | DN45: Guanajuato C1 | DO45: 850 | DR45: N | DS45: Particular | DT45: Thelma Gabriela Sánchez Sánchez | DU45: Individual 2025 | DV45: Lucía Sánchez | DW45: Reagendó | DX45: Guanajuato C2 | DY45: 420 | DZ45: Transf - 1872 | EB45: S | EC45: INSUNTE | ED45: Luis Donaldo Sandoval López | EE45: Individual 2025 | EF45: Gloria sarmiento | EG45: Confirmó | EH45: Morelos C2 | EI45: 420 | EJ45: Efectivo | FP45: N | FQ45: Particular | FR45: María de Lourdes Martinez Reyna y José Eduardo Martinez Alvarez | FS45: Pareja | FT45: Rosy Macias | FU45: Asistió | FV45: Morelos C2 | FW45: 520 | FX45: Efectivo | FZ45: S | GA45: Particular | GB45: Jonas Alejandro Morales | GC45: Individual 2025 | GD45: José Arcadio | GE45: Confirmó | GF45: ZOOM C1 | GG45: $420 | GI45: 5.30 | HX45: S | HY45: Particular | HZ45: Angel Daniel Garcia Ruvalcaba | IA45: Individual 2025 | IB45: Javier Martínez | IC45: Pendiente REAG | ID45: Guanajuato C3 | IE45: $420 | IJ45: Renta de espacio | IK45: Renta de espacios - Asociados | IL45: Rosy Macias | IM45: Confirmó | IN45: Morelos C1 | IO45: 125 | IT45: Renta de espacio | IU45: Renta de espacios - Asociados | IV45: Enrique Luna | IW45: Confirmó | IX45: Guanajuato C1 | IY45: 125 | JL45: N | JM45: Particular | JN45: Alan Agustín Estrada García, | JO45: Individual 2025 | JP45: Alondra Escalon | JQ45: No llegó | JR45: Morelos C1 | JS45: 450 | JT45: Efectivo
A46: 0.20833333 | AP46: N | AQ46: Particular | AR46: Francisco Andrés García Rangel | AS46: Individual 2025 | AT46: Gloria Sarmiento | AU46: Confirmó | AV46: Morelos C2 | AW46: 420 | AX46: Transf - 1872 | DH46: S | DI46: Trabajo social | DJ46: José Francisco Gomez Coronado | DK46: Individual 2025 | DL46: Fabiola Fragoso | DM46: Asistió | DN46: Guanajuato C3 | DO46: 300 | DP46: Efectivo | DR46: N | DS46: Particular | DT46: Mirna Hinojosa | DU46: Individual 2025 | EB46: S | EC46: Particular | ED46: Jonathan Barrera | EE46: Individual 2025 | EF46: Maricela Sena | EG46: Confirmó | EH46: Guanajuato C1 | EI46: 200 | EJ46: Efectivo | FZ46: S | GA46: Trabajo social | GB46: José Francisco Gomez Coronado | GC46: Individual 2025 | GD46: Fabiola Fragoso | GE46: Confirmó | GF46: Guanajuato C3 | GG46: 350 | GH46: Efectivo | HX46: N | HY46: Particular | HZ46: Carlos Martinez | IA46: Individual | IB46: José Arcadio | IC46: Confirmó | ID46: Morelos C2 | IE46: 420 | IF46: Transf - 1872 | IH46: S | II46: Particular | IJ46: Mariana Denisse Conchis | IK46: Individual 2025 | IL46: Esmeralda Colunga | IM46: Confirmó | IN46: Morelos C2 | IO46: 400 | IP46: Efectivo | JL46: N | JM46: Particular | JN46: Angel Daniel Garcia Ruvalcaba | JO46: Individual 2025 | JP46: Javier Martínez | JQ46: Asistió | JR46: Morelos C1 | JS46: $420 | JT46: Efectivo
A47: 0.20833333 | ED47: renta de espacio | EE47: Renta de espacios - Asociados | EF47: Enrique Luna | EG47: Confirmó | EH47: Guanajuato C2 | EI47: $125 | FZ47: N | GA47: Particular | GB47: Eduardo Herrera Valdez | GC47: Médica psiquiatrica | GD47: Enrique Luna | GE47: Canceló | GF47: Guanajuato C1 | GG47: 850
A48: 0.20833333 | AP48: N | AQ48: Particular | AR48: Victoria Aldaco Martínez | AS48: Pareja | AT48: Rosy Macias | AU48: Confirmó | AV48: Morelos C3 | AW48: $520 | CX48: N | CZ48: Mireya Tello | DA48: Individual | DC48: Asistió | DD48: Guanajuato C1 | DE48: 350 | DF48: Efectivo | DG48: Academia | DH48: N | DI48: Particular | DJ48: Samuel Valles | DK48: Infantil | DL48: Lucía Sánchez | DM48: Asistió | DN48: Guanajuato C2 | DO48: $480
A49: 0.25 | V49: S | W49: Particular | X49: Carlos Alberto Martinez Gaona | Y49: Individual 2025 | Z49: José Arcadio | AA49: Asistió | AB49: Morelos C1 | AC49: $340 | AE49: 6:30, dejó $500 la pasada | AF49: S | AG49: Particular | AI49: Pareja | AJ49: Rosy Macias | AK49: Asistió | AL49: Morelos C1 | AM49: 520 | AN49: Transf - 1872 | BT49: N | BU49: Particular | BV49: Sofía Holguín Muñiz | BW49: Individual 2025 | BX49: Fabiola Fragoso | BY49: Confirmó | BZ49: Guanajuato C1 | CA49: 420 | CB49: Tarjeta | CX49: S | CY49: Particular | CZ49: Ernesto Lobo | DA49: Individual 2025 | DB49: José Arcadio | DC49: Asistió | DD49: Colinas C1 | DE49: $340 | DF49: Efectivo | DG49: 0.27083333 | DH49: S | DI49: Particular | DJ49: Angela Regina Galindo | DK49: Individual 2025 | DL49: José Arcadio | DM49: Asistió | DN49: Colinas C1 | DO49: $350 | DP49: Transf - 1872 | DQ49: 0.27083333 | DR49: S | DS49: GIASA | DT49: Antonio de Jesus Jara Esquivel | DU49: Consulta nutricional | DV49: Carolina Gonzalez | DW49: Confirmó | DX49: Guanajuato C1 | DY49: 0 | DZ49: Pase | EB49: N | EC49: Particular | ED49: Evelyn Estefania Rios Vasquez | EE49: Individual 2025 | EF49: Rosy Macias | EG49: Pendiente REAG | EH49: Morelos C1 | EI49: $420 | EJ49: Transf - 1872 | FF49: N | FG49: Particular | FH49: Ramiro Campos | FI49: Individual 2025 | FJ49: Fabiola Fragoso | FK49: No confirmó | FL49: Guanajuato C1 | FM49: 420 | FP49: S | FQ49: Particular | FR49: Ricardo Garay Garcia y Ariadna Vera Morales | FS49: Pareja | FT49: Rosy Macias | FU49: Asistió | FV49: Morelos C1 | FW49: 520 | FX49: Transf - 1872 | FZ49: S | GA49: Particular | GB49: Thelma Gabriel Sanchez | GC49: Individual 2025 | GD49: Lucía Sánchez | GE49: Reagendó | GF49: Guanajuato C2 | GG49: 420 | GJ49: S | GK49: Particular | GL49: Violeta Berenice Meza Dominguez | GM49: Individual 2025 | GN49: José Arcadio | GO49: Confirmó | GP49: Morelos C1 | GQ49: 420 | GR49: Efectivo | GS49: 6.30 | GT49: N | GU49: Particular | GV49: Oliver Enrique Rivera Rodríguez | GW49: Individual 2025 | GX49: Maricela Sena | GY49: Reagendó | GZ49: Guanajuato C1 | HA49: 420 | HB49: Efectivo | HX49: S | HY49: Particular | HZ49: Katherine Isabel Garcia Hernandez | IA49: Infantil | IB49: Perla Realme | IC49: Asistió | ID49: Guanajuato C2 | IE49: 200 | IF49: Efectivo | IH49: S | II49: Particular | IJ49: Mireya Tello | IK49: Individual | IL49: Alejandra Durán | IM49: Confirmó | IN49: Guanajuato C2 | IO49: 350 | IP49: Efectivo | IQ49: Academia | IR49: S | IS49: GIASA | IT49: Marco Antonio Hinojosa Hernández | IU49: Médica psiquiatrica | IV49: Enrique Luna | IW49: No llegó | IX49: Guanajuato C1 | IY49: 0 | IZ49: Pase | JB49: N | JC49: Particular | JD49: Maria del Rosario Casas | JE49: Individual | JF49: José Arcadio | JG49: Confirmó | JH49: Morelos C1 | JI49: 350 | JK49: 6;30 | JL49: S | JM49: Particular | JN49: Alberto de Jesús Ramos Barrientos | JO49: Individual 2025 | JP49: Gloria Sarmiento | JQ49: Asistió | JR49: Morelos C2 | JS49: 340 | JT49: Transf - 1872
A50: 0.25 | V50: N | W50: Particular | X50: Oscar Antonio Saucedo Pérez | Y50: Individual 2025 | Z50: Daniel Salazar | AA50: No llegó | AB50: Morelos C2 | AC50: 420 | AD50: Efectivo | AF50: S | AG50: Particular | AH50: Ernesto Lobo | AI50: Individual 2025 | AJ50: José Arcadio | AK50: Asistió | AL50: Colinas C1 | AM50: $420 | AN50: Efectivo | AO50: 0.27083333 | AP50: S | AQ50: Particular | AR50: Jorge Alejandro Salazar Oyervides | AS50: Individual 2025 | AT50: José Arcadio | AU50: Reagendó | AV50: Colinas C1 | AW50: $420 | AX50: Efectivo | AZ50: S | BA50: Particular | BB50: Edgar Alonso Puga Rasgado | BC50: Individual 2025 | BD50: José Arcadio | BE50: Confirmó | BF50: Morelos C1 | BG50: $360 | BH50: Efectivo | BI50: 6.30 | BJ50: N | BK50: Particular | BL50: Evelyn Estefania Rios Vasquez | BM50: Individual 2025 | BN50: Rosy Macias | BO50: Confirmó | BP50: Morelos C1 | BQ50: $420 | BR50: Transf - 1872 | BS50: EMDR | CN50: S | CO50: Particular | CP50: Maria Magdalena Davila | CQ50: Individual 2025 | CR50: José Arcadio | CS50: Asistió | CT50: Morelos C1 | CU50: $420 | CW50: 0.27083333 | CX50: S | CY50: Particular | CZ50: Cynthia Perez | DA50: Individual 2025 | DB50: Benjamin Villagomez | DC50: Asistió | DD50: Guanajuato C2 | DE50: 420 | DF50: Efectivo | DR50: N | DS50: Particular | DT50: Maria Fernanda Rodriguez Daniel | DU50: Infantil | DV50: Javier Martínez | DW50: Confirmó | DX50: Guanajuato C3 | DY50: 420 | DZ50: Efectivo | EB50: N | EC50: Particular | ED50: Cecilia González Martinez | EE50: Individual 2025 | EF50: Maricela Sena | EG50: Confirmó | EH50: Guanajuato C1 | EI50: 420 | EJ50: Efectivo | FF50: S | FG50: Particular | FH50: Carlos Alberto Martinez Gaona | FI50: Individual 2025 | FJ50: José Arcadio | FK50: No llegó | FL50: Morelos C1 | FM50: 340 | FO50: 6:30 pm | FP50: S | FQ50: Particular | FR50: Yessica Anahí Rodriguez | FS50: Individual 2025 | FT50: José Arcadio | FU50: Asistió | FV50: ZOOM C1 | FW50: $420 | FX50: Transf - 1872 | FY50: 0.27083333 | FZ50: N | GA50: Particular | GB50: Carlos Daniel Muñoz Alvizo | GC50: Individual 2025 | GD50: Fabiola Fragoso | GE50: No confirmó | GF50: Guanajuato C1 | GG50: 420 | GJ50: S | GK50: Particular | GL50: Rosita Ramirez Ramos | GM50: Individual 2025 | GN50: Javier Martínez | GO50: Reagendó | GP50: Guanajuato C1 | GQ50: 420 | GR50: Efectivo | GT50: N | GU50: Particular | GV50: Cecilia González Martinez | GW50: Individual 2025 | GX50: Maricela Sena | GY50: Pendiente REAG | GZ50: Guanajuato C1 | HA50: 420 | HX50: N | HY50: Particular | HZ50: Juan Alberto Cisineros Cárdenas | IA50: Individual 2025 | IB50: Daniel Salazar | IC50: Asistió | ID50: Morelos C1 | IE50: 420 | IH50: N | II50: Particular | IJ50: Joana castillo | IK50: Individual | IL50: José Arcadio | IM50: No confirmó | IN50: Colinas C1 | IO50: 420 | IQ50: 6.30 pm | IR50: S | IS50: Particular | IT50: Jonas Alejandro Morales | IU50: Individual 2025 | IV50: José Arcadio | IW50: Asistió | IX50: ZOOM C1 | IY50: $420 | IZ50: Transf - 1872 | JA50: 0.27083333 | JL50: S | JM50: Particular | JN50: Sandra Yudith García Dávila | JO50: Individual 2025 | JP50: Javier Martínez | JQ50: Asistió | JR50: Guanajuato C3 | JS50: 350 | JT50: Efectivo
A51: 0.25 | AD51: Transf - 1872 | AF51: S | AG51: Particular | AH51: Mariana Denisse Conchis | AI51: Individual 2025 | AJ51: Esmeralda Colunga | AK51: Asistió | AL51: Morelos C2 | AM51: 400 | AN51: Efectivo | AZ51: S | BA51: Particular | BB51: Isabel Mata | BC51: Individual 2025 | BD51: Benjamin Villagomez | BE51: Confirmó | BF51: Guanajuato C1 | BG51: 420 | BJ51: N | BK51: UTS | BL51: Carlos Amauri García Peña | BM51: Individual 2025 | BN51: Rosy Macias | BO51: Pendiente REAG | BP51: Morelos C1 | BQ51: $300 | CN51: S | CO51: Particular | CP51: Juan de Dios Enriquez | CQ51: Individual 2025 | CR51: Daniel Salazar | CS51: No llegó | CT51: Morelos C1 | CU51: $420 | CX51: N | CY51: Particular | CZ51: Diego Olivas De La Peña | DA51: Individual 2025 | DB51: Esmeralda Colunga | DC51: Pendiente REAG | DD51: Morelos C3 | DE51: 400 | DF51: Efectivo | DR51: N | DS51: Particular | DT51: Mirna Hinojosa | DU51: Pareja | DV51: José Arcadio | DW51: Confirmó | DX51: ZOOM C1 | DY51: 550 | EB51: N | EC51: Particular | ED51: Nicole García González | EE51: Infantil | EF51: Fabiola Fragoso | EG51: Confirmó | EH51: Guanajuato C2 | EI51: 480 | EJ51: Efectivo | FF51: S | FG51: Particular | FH51: Juan de Dios Enriquez | FI51: Individual 2025 | FJ51: Daniel Salazar | FK51: Asistió | FL51: Morelos C1 | FM51: $420 | FP51: S | FQ51: Particular | FR51: José Miguel Trejo | FS51: Infantil | FT51: Esmeralda Colunga | FU51: Asistió | FV51: Morelos C3 | FW51: $480 | FX51: Efectivo | FZ51: S | GA51: Particular | GB51: Oscar Jesus Sanchez Muñoz | GC51: Individual 2025 | GD51: José Arcadio | GE51: Confirmó | GF51: Colinas C1 | GG51: $420 | GI51: 6.30 | GT51: S | GU51: Particular | GV51: Luis Gerardo Padilla Cuellar | GW51: Individual 2025 | GX51: Rosy Macias | GY51: No confirmó | GZ51: Morelos C1 | HA51: 420 | HX51: S | HY51: Particular | HZ51: Ernesto Lobo | IA51: Individual 2025 | IB51: José Arcadio | IC51: No llegó | ID51: Colinas C1 | IE51: $340 | IG51: 0.27083333 | IH51: S | II51: Particular | IJ51: José Miguel Trejo | IK51: Infantil | IL51: Esmeralda Colunga | IM51: Confirmó | IN51: Morelos C1 | IO51: $480 | IP51: Efectivo | JL51: S | JM51: NEAPCO | JN51: Fe Garay | JO51: Individual 2025 | JP51: Gloria Sarmiento | JQ51: Asistió | JR51: Morelos C1 | JS51: 0 | JT51: Pase
A52: 0.25 | AP52: S | AQ52: Particular | AR52: Angela Regina Galindo Garay | AS52: Individual 2025 | AT52: José Arcadio | AU52: Confirmó | AV52: Colinas C1 | AW52: 350 | AX52: Transf - 1872 | BJ52: S | BK52: Particular | BL52: Juan Felipe Castillo Reyna | BM52: Individual 2025 | BN52: Gloria Sarmiento | BO52: Confirmó | BP52: Morelos C2 | BQ52: 370 | BR52: Efectivo | CX52: N | CY52: Particular | CZ52: Paloma Verástegui | DA52: Individual 2025 | DB52: Fabiola Fragoso | DC52: No llegó | DD52: Guanajuato C1 | DE52: 420 | DF52: Tarjeta | EB52: N | EC52: Particular | ED52: Maximiliano Ramos Fuentes | EE52: Individual 2025 | EF52: Benjamin Villagomez | EG52: No llegó | EH52: Guanajuato C3 | EI52: 360 | EJ52: Tarjeta | FZ52: N | GA52: Particular | GB52: Evelyn Estefania Rios Vasquez | GC52: Individual 2025 | GD52: Rosy Macias | GE52: Confirmó | GF52: Morelos C1 | GG52: $420 | GH52: Transf - 1872 | GT52: S | GU52: Particular | GV52: Emilio Alejandro Hernádez Montes | GW52: Individual 2025 | GX52: Javier Martínez | GY52: Confirmó | GZ52: Guanajuato C3 | HA52: 200 | IH52: N | II52: Particular | IJ52: Juan Antonio Saucedo Mancha | IK52: Individual 2025 | IL52: Rosy Macias | IM52: Canceló | IN52: Morelos C1 | IO52: 420 | IR52: N | IS52: Particular | IT52: Evelyn Estefania Rios Vasquez | IU52: Individual 2025 | IV52: Rosy Macias | IW52: Reagendó | IX52: Morelos C1 | IY52: $420
A53: 0.25 | AP53: N | AQ53: Particular | AR53: Cesar Erubiel Rodriguez | AS53: Individual 2025 | AT53: Enrique Luna | AU53: Confirmó | AV53: Guanajuato C1 | CX53: N | CY53: Particular | CZ53: Juan Antonio Saucedo Mancha | DA53: Individual 2025 | DB53: Rosy Macias | DC53: Asistió | DD53: Morelos C1 | DE53: 420 | DF53: Efectivo | FZ53: N | GA53: Particular | GB53: Evelyn Maricruz Ledezma Rodríguez | GC53: Individual 2025 | GD53: Benjamin Villagomez | GE53: Confirmó | GF53: Guanajuato C2 | GG53: 420 | JB53: N | JC53: Particular | JD53: Evelyn Maricruz Ledezma Rodríguez | JE53: Individual 2025 | JF53: Benjamin Villagomez | JG53: Confirmó | JH53: Guanajuato C2 | JI53: 420 | JJ53: Transf - 1872
A54: 0.29166667 | V54: N | W54: Particular | X54: Juan Manuel Fernández Castañeda | Y54: Individual 2025 | Z54: Fabiola Fragoso | AA54: Reagendó | AB54: Guanajuato C1 | AC54: 420 | AF54: N | AG54: Particular | AH54: Orlando Vazquez Leos | AI54: Individual 2025 | AJ54: Rosy Macias | AK54: No llegó | AL54: Morelos C1 | AM54: 420 | AO54: Se le cobraran $340 | AP54: S | AQ54: Particular | AR54: Fabiola Alejandra Navarro Agustince | AS54: Consulta psiquiatrica | AT54: Enrique Luna | AU54: Pendiente REAG | AV54: Guanajuato | AW54: 850 | AZ54: S | BA54: Particular | BB54: Jesus Berlanga | BC54: Individual 2025 | BD54: José Arcadio | BE54: Confirmó | BF54: Morelos C1 | BG54: 400 | BH54: Efectivo | BI54: 7.30 | BJ54: S | BK54: GIASA | BL54: Marco Antonio Hinojosa Hernández | BM54: Individual 2025 | BN54: Maricela Sena | BO54: Confirmó | BP54: Guanajuato C1 | BQ54: 0 | BR54: Pase | CN54: S | CO54: Particular | CP54: Juan Manuel Fernández Castañeda | CQ54: Individual 2025 | CR54: Fabiola Fragoso | CS54: Asistió | CT54: Guanajuato C1 | CU54: 420 | CV54: Tarjeta | CX54: N | CY54: Particular | CZ54: Carlos Alberto Trejo | DA54: Infantil | DB54: Esmeralda Colunga | DC54: Asistió | DD54: Morelos C3 | DE54: $480 | DF54: Efectivo | DH54: N | DI54: Particular | DJ54: Angel Daniel Garcia Ruvalcaba | DK54: Médica psiquiatrica | DL54: Enrique Luna | DM54: Reagendó | DN54: Guanajuato C1 | DO54: 850 | DP54: Efectivo | DR54: N | DS54: Particular | DT54: Ximena Alejandra Esquivel rocha | DU54: Individual 2025 | DV54: Benjamin Villagomez | DW54: No confirmó | DX54: Guanajuato C1 | DY54: 420 | EA54: Cita 7:30 | EB54: S | EC54: NEAPCO | ED54: Marco Antonio Hinojosa Hernández | EE54: Individual 2025 | EF54: Maricela Sena | EG54: No llegó | EH54: Guanajuato C1 | EI54: 0 | EJ54: Pase | FF54: S | FG54: Particular | FH54: Maria Magdalena Davila | FI54: Individual 2025 | FJ54: José Arcadio | FK54: Asistió | FL54: Morelos C1 | FM54: $420 | FO54: 0.3125 | FP54: S | FQ54: Particular | FR54: Carlos Alberto Trejo | FS54: Infantil | FT54: Esmeralda Colunga | FU54: Asistió | FV54: Morelos C3 | FW54: $480 | FX54: Efectivo | FZ54: S | GA54: Particular | GB54: Emilio Alejandro Hernádez Montes | GC54: Individual 2025 | GD54: Javier Martínez | GE54: Reagendó | GF54: Guanajuato C3 | GG54: 200 | GJ54: S | GK54: Particular | GL54: Hugo Torres | GM54: Individual 2025 | GN54: José Arcadio | GO54: Confirmó | GP54: Morelos C2 | GQ54: 500 | GR54: Efectivo | GS54: 7.30 | GT54: S | GU54: Particular | GV54: Alejandra Ornelas | GW54: Individual 2025 | GX54: Benjamin Villagomez | GY54: Confirmó | GZ54: Guanajuato C2 | HA54: $420 | HB54: Tarjeta | HC54: 0.3125 | HX54: S | HY54: Particular | HZ54: Maria Magdalena Davila | IA54: Individual 2025 | IB54: José Arcadio | IC54: Confirmó | ID54: Morelos C1 | IE54: $420 | IG54: 0.3125 | IH54: N | II54: Particular | IJ54: Isidro Emmanuel Jimenez Casas y Gabriela Santana Ibarra | IK54: Pareja | IL54: Rosy Macias | IM54: Pendiente REAG | IN54: Morelos C2 | IO54: 520 | IR54: N | IS54: Particular | IT54: Damian Ávalos | IU54: Consulta psiquiatrica | IV54: Enrique Luna | IW54: Asistió | IX54: ZOOM C2 | IY54: 50 CAD | IZ54: Pase | JB54: S | JC54: Particular | JD54: Hugo Torres | JE54: Individual 2025 | JF54: José Arcadio | JG54: Confirmó | JH54: Morelos C2 | JI54: 500 | JJ54: Efectivo | JK54: 7.30 | JL54: S | JM54: NEAPCO | JN54: Marco Antonio Hinojosa Hernández | JO54: Individual 2025 | JP54: Maricela Sena | JQ54: No llegó | JR54: Guanajuato C1 | JS54: 0 | JT54: Pase
A55: 0.29166667 | V55: S | W55: Particular | X55: Yuritza Mendoza | Y55: Individual 2025 | Z55: José Arcadio | AA55: Pendiente REAG | AB55: Morelos C1 | AC55: $420 | AF55: N | AG55: Particular | AP55: S | AQ55: Particular | AR55: Eduardo Gael Garcia Davila | AS55: Individual 2025 | AT55: Benjamin Villagomez | AU55: Confirmó | AV55: Guanajuato C1 | AW55: 420 | AX55: Efectivo | AZ55: S | BA55: Particular | BB55: Alejandra Ornelas | BC55: Individual 2025 | BD55: Benjamin Villagomez | BE55: Confirmó | BF55: Guanajuato C2 | BG55: $420 | BI55: 0.3125 | BJ55: N | BK55: Particular | BL55: Luis Gerardo Padilla Cuellar | BM55: Individual 2025 | BN55: Rosy Macias | BO55: Confirmó | BP55: Morelos C1 | BQ55: 420 | BR55: Transf - 1872 | CN55: S | CO55: Particular | CP55: Katherine Isabel Garcia Hernandez | CQ55: Infantil | CR55: Perla Realme | CS55: Reagendó | CT55: Guanajuato C2 | CU55: 200 | CX55: S | CY55: Particular | CZ55: Oscar Jesus Sanchez Muñoz | DA55: Individual 2025 | DB55: José Arcadio | DC55: Asistió | DD55: Colinas C1 | DE55: $420 | DG55: 0.3125 | DH55: N | DI55: Particular | DJ55: María Liliana corpus González y Jesús segura tenorio | DK55: Pareja | DL55: Rosy Macias | DM55: Pendiente REAG | DN55: Morelos C1 | DO55: 520 | EB55: N | EC55: Particular | ED55: María Liliana corpus González y Jesús segura tenorio | EE55: Pareja | EF55: Rosy Macias | EG55: Asistió | EH55: Morelos C1 | EI55: 520 | FF55: S | FG55: Particular | FH55: Jesús Javier Torres García | FI55: Individual 2025 | FJ55: Daniel Salazar | FK55: Asistió | FL55: Morelos C1 | FM55: 420 | FN55: Transf - 1872 | FP55: S | FQ55: INSUNTE | FR55: Perla Veronica y Luis | FS55: Pareja | FT55: José Arcadio | FU55: Asistió | FV55: Colinas C1 | FW55: 350 | FY55: 0.3125 | FZ55: S | GA55: Particular | GB55: Mireya Tello | GC55: Individual | GE55: Pendiente REAG | GF55: Guanajuato C1 | GG55: 350 | GI55: Academia | GJ55: S | GK55: Particular | GL55: Emilio Alejandro Hernádez Montes | GM55: Individual 2025 | GN55: Javier Martínez | GO55: Reagendó | GP55: Guanajuato C3 | GQ55: 200 | GT55: S | GU55: Particular | GV55: María Liliana Corpus González y Jesús Segura Tenorio | GW55: Pareja | GX55: Rosy Macias | GY55: Confirmó | GZ55: Morelos C1 | HA55: 520 | IH55: S | II55: Particular | IJ55: Ernesto Lobo | IK55: Individual 2025 | IL55: José Arcadio | IM55: No confirmó | IN55: Colinas C1 | IO55: $340 | IQ55: 0.3125 | IR55: N | IS55: Particular | IT55: Martin Rodríguez | IU55: Individual 2025 | IV55: Fabiola Fragoso | IW55: Pendiente REAG | IX55: Guanajuato C2 | IY55: 450 | IZ55: Efectivo | JB55: S | JC55: GIASA | JD55: David Barrios Belmares | JE55: Individual 2025 | JF55: Benjamin Villagomez | JG55: Reagendó | JH55: Guanajuato C3 | JI55: 0 | JJ55: Pase | JL55: S | JM55: Particular | JN55: Carlos Enrique Escobar Pérez | JO55: Individual 2025 | JP55: Maricela Sena | JQ55: Confirmó | JR55: Guanajuato C1 | JS55: 280 | JT55: Transf - 1872
A56: 0.29166667 | V56: S | W56: Particular | X56: Katherine Isabel Garcia Hernandez | Y56: Infantil | Z56: Perla Realme | AA56: Reagendó | AB56: Guanajuato C2 | AC56: 200 | AD56: Efectivo | AF56: S | AG56: Particular | AH56: Oscar Jesus Sanchez Muñoz | AI56: Individual 2025 | AJ56: José Arcadio | AK56: Asistió | AL56: Colinas C1 | AM56: $420 | AN56: Efectivo | AO56: 0.3125 | AP56: S | AQ56: Particular | AR56: Jonas Alejandro Morales | AS56: Individual 2025 | AT56: José Arcadio | AU56: Confirmó | AV56: Colinas C1 | AW56: $420 | AX56: Transf - 1872 | CN56: S | CO56: Particular | CP56: Karina Figueroa | CQ56: Individual 2025 | CR56: José Arcadio | CS56: Asistió | CT56: Morelos C1 | CU56: $420 | CV56: Efectivo | CX56: S | CY56: Particular | CZ56: Iker Neymar Benito Sandoval | DA56: Individual 2025 | DB56: Esmeralda Colunga | DC56: Pendiente REAG | DD56: Morelos C3 | DE56: 340 | DH56: N | DI56: Particular | DJ56: Hugo Torres | DK56: Individual 2025 | DL56: José Arcadio | DM56: Asistió | DN56: Colinas C1 | DO56: 500 | DP56: Transf - 1872 | DQ56: 7.30 | EB56: N | EC56: Particular | ED56: Angel Mateo García González | EE56: Infantil | EF56: Fabiola Fragoso | EG56: Asistió | EH56: Guanajuato C1 | EI56: 480 | FP56: N | FQ56: Particular | FR56: Isidro Emmanuel Jimenez Casas y Gabriela Santana Ibarra | FS56: Pareja | FT56: Rosy Macias | FU56: Asistió | FV56: Morelos C3 | FW56: 520 | FZ56: S | GA56: Particular | GB56: Deicker Alexander Quiroz | GC56: Individual 2025 | GD56: Enrique Luna | GE56: No confirmó | GF56: Guanajuato C1 | GG56: 700 | IH56: S | II56: Particular | IJ56: Maria Magdalena Salcido Morales | IK56: Individual 2025 | IL56: Fabiola Fragoso | IM56: Asistió | IN56: Guanajuato C1 | IO56: 420 | IP56: Tarjeta | IR56: S | IS56: GIASA | IT56: David Barrios Belmares | IU56: Individual 2025 | IV56: Benjamin Villagomez | IW56: Asistió | IX56: Guanajuato C3 | IY56: 0 | IZ56: Pase | JB56: N | JC56: Particular | JD56: Martin Rodríguez | JE56: Individual 2025 | JF56: Fabiola Fragoso | JG56: Confirmó | JH56: Guanajuato C2 | JI56: 450 | JJ56: Efectivo
A57: 0.29166667 | W57: Particular | X57: juan de Dios Enriquez | Y57: Individual 2025 | Z57: Daniel Salazar | AA57: Asistió | AB57: Morelos C1 | AC57: $420 | AF57: S | AG57: Particular | AH57: Iker Neymar Benito Sandoval | AI57: Individual 2025 | AJ57: Esmeralda Colunga | AK57: Asistió | AL57: Morelos C1 | AM57: 340 | AN57: Efectivo | AO57: Revisar costo | AP57: N | AQ57: Particular | AR57: María Liliana corpus González y Jesús segura tenorio | AS57: Pareja | AT57: Rosy Macias | AU57: Confirmó | AV57: Morelos C1 | AW57: 520 | CX57: N | CY57: Particular | CZ57: Maria Magdalena Salcido Morales | DA57: Individual 2025 | DB57: Fabiola Fragoso | DC57: Asistió | DD57: Guanajuato C1 | DE57: 420 | DF57: Tarjeta | DH57: N | DI57: Particular | DJ57: Nancy Verónica y Néstor Sánchez | DK57: Pareja | DL57: Maria Amancio | DM57: Asistió | DN57: Guanajuato C2 | DO57: 550 | DP57: Efectivo | FZ57: S | GA57: Particular | GB57: Ernesto Lobo | GC57: Individual 2025 | GD57: José Arcadio | GE57: Confirmó | GF57: Colinas C1 | GG57: $340 | GH57: Efectivo | GI57: 0.3125 | IH57: N | II57: Particular | IJ57: Derek Ricardo Magallan Martinez | IK57: Infantil | IL57: Esmeralda Colunga | IM57: Asistió | IN57: Morelos C2 | IO57: 350 | IP57: Efectivo | JB57: N | JC57: Particular | JD57: María Liliana corpus González y Jesús segura tenorio | JE57: Pareja | JF57: Rosy Macias | JG57: Reagendó | JH57: Morelos C1 | JI57: 520
A58: 0.29166667 | V58: N | W58: Particular | X58: Ramiro Campos | Y58: Individual 2025 | Z58: Fabiola Fragoso | AA58: Asistió | AB58: Guanajuato C1 | AC58: 420 | AD58: Transf - 1872 | CZ58: Astrid Intra | DB58: Benjamin Villagomez | IH58: N | II58: Particular | IJ58: Amelia Alvarado Rodríguez | IK58: Individual 2025 | IL58: Rosy Macias | IM58: Asistió | IN58: Morelos C1 | IO58: 420 | IP58: Efectivo
A59: 0.33333333 | V59: S | W59: Particular | X59: Jesús Javier Torres García | Y59: Individual 2025 | Z59: Daniel Salazar | AA59: Asistió | AB59: Morelos C1 | AC59: 420 | AD59: Transf - 1872 | AF59: N | AG59: Particular | AH59: Derek Ricardo Magallan Martinez | AI59: Individual 2025 | AJ59: Esmeralda Colunga | AK59: Asistió | AL59: Morelos C2 | AM59: 480 | AN59: Efectivo | AO59: Se le deben $20 | AZ59: S | BA59: Particular | BB59: Cecilia Michelle Cavazos Cabello | BC59: Individual 2025 | BD59: Benjamin Villagomez | BE59: Confirmó | BF59: Guanajuato C1 | BG59: $350 | BH59: Efectivo | BI59: 0.35416667 | BJ59: N | BK59: GIASA | BL59: David Barrios Belmares | BM59: Individual 2025 | BN59: Benjamin Villagomez | BO59: Confirmó | BP59: Guanajuato C2 | BQ59: 0 | BR59: Pase | CN59: S | CO59: Particular | CP59: Jesús Javier Torres García | CQ59: Individual 2025 | CR59: Daniel Salazar | CS59: Asistió | CT59: Morelos C1 | CU59: 420 | CV59: Transf - 1872 | CX59: S | CY59: Particular | CZ59: José Miguel Trejo | DA59: Infantil | DB59: Esmeralda Colunga | DC59: Asistió | DD59: Morelos C3 | DE59: $480 | DF59: Efectivo | DR59: N | DS59: Particular | DT59: Angel Daniel Garcia Ruvalcaba | DU59: Consulta psiquiatrica | DV59: Enrique Luna | DW59: Confirmó | DX59: Guanajuato C2 | DY59: $850 | EB59: N | EC59: GIASA | ED59: David Barrios Belmares | EE59: Individual 2025 | EF59: Benjamin Villagomez | EG59: Asistió | EH59: Guanajuato C3 | EI59: 0 | EJ59: Pase | FP59: S | FQ59: Particular | FR59: Derek Ricardo Magallan Martinez | FS59: Individual 2025 | FT59: Esmeralda Colunga | FU59: Reagendó | FV59: Morelos C2 | FW59: 480 | GT59: S | GU59: GIASA | GV59: David Barrios Belmares | GW59: Individual 2025 | GX59: Benjamin Villagomez | GY59: Confirmó | GZ59: Guanajuato C3 | HA59: 0 | HB59: Pase | HC59: 0.35416667 | IH59: S | II59: Particular | IJ59: Diego Olivas De La Peña | IK59: Individual 2025 | IL59: Esmeralda Colunga | IM59: Asistió | IN59: Morelos C2 | IO59: 400 | IP59: Efectivo | IT59: Renta de espacio | IU59: Renta de espacios - Asociados | IV59: Enrique Luna | IW59: Asistió | IX59: Guanajuato C1 | IY59: 125
A60: 0.33333333 | AF60: S | AG60: Particular | AH60: Margarita Aguirre Lopez (Angela Carret) | AI60: Individual | AJ60: Benjamin Villagomez | AK60: Asistió | AL60: ZOOM C1 | AM60: 420 | AN60: Transf - 1872 | CX60: S | CY60: Particular | CZ60: Margarita Aguirre Lopez (Angela Carret) | DA60: Individual | DB60: Benjamin Villagomez | DC60: Asistió | DD60: Guanajuato C2 | DE60: 420 | DF60: Efectivo | FP60: S | FQ60: Particular | FR60: Margarita Aguirre Lopez (Angela Carret) | FS60: Individual | FT60: Benjamin Villagomez | FU60: Asistió | FV60: Guanajuato C2 | FW60: 420 | FY60: 0.35416667 | IH60: S | II60: Particular | IJ60: Angela Carret | IK60: Individual | IL60: Benjamin Villagomez | IM60: No confirmó | IN60: Guanajuato C2 | IO60: 340 | IQ60: 0.35416667
A61: 0.33333333
A62: 0.33333333
A63: 0.33333333

Sheet catalogo
B1: Individual | C1: 450 | D1: 420 | F1: Adriana Sucedo | H1: Guanajuato C1 | J1: Confirmó | L1: Efectivo
B2: Pareja | C2: 600 | D2: 520 | F2: Alejandra Durán | H2: Guanajuato C2 | J2: Canceló | L2: Gratuito
B3: Infantil | C3: 500 | D3: 480 | F3: Alisson Bermea | H3: Guanajuato C3 | J3: No llegó | L3: Pase
B4: Familiar | C4: 600 | D4: 550 | F4: Ana Juarez | H4: Poniente C1 | J4: Reagendó | L4: Tarjeta
B5: Hipnosis clinica | C5: 600 | D5: 550 | F5: Benjamin Villagomez | H5: Poniente C2 | J5: Pendiente REAG | L5: Transf - 1872
B6: Consulta nutricional | C6: 780 | D6: 550 | F6: Carolina Gonzalez | H6: WhereBy 1 | J6: Canceló - 2da | L6: Descuento de pago
B7: Constancia de alta | C7: 150 | D7: 120 | F7: Daniel Salazar | H7: WhereBy 2 | J7: No llegó - 2da
B8: Medica en salud mental | C8: 900 | D8: 850 | F8: Daniela Sarmiento | H8: Morelos C1 | J8: Reagendó - 2da
B9: Contancia de proceso | C9: 250 | D9: 120 | F9: David Bermejo | H9: Morelos C2 | J9: Canceló - 3ra
B10: Medica general | C10: 600 | D10: 550 | F10: Enrique Luna | H10: Morelos C3 | J10: No llegó - 3ra
B11: Psicotanatología | C11: 500 | D11: 400 | F11: Esmeralda Colunga | H11: Colinas C1 | J11: Reagendó - 3ra
B12: Evaluación neuropsicológica (Sesión) | C12: 450 | D12: 1050 | F12: Fabiola Fragoso | H12: Consultorio externo | J12: Asistió
B13: Evaluación Psicológica (Sesión) | C13: 400 | D13: 0 | F13: Gloria Sarmiento | H13: República C1 | J13: Renta de espacio
B14: Renta Abasolo- Independiente | D14: 180 | F14: Javier Martínez | H14: República C2 | J14: No confirmó
B15: Renta de espacios - Asociados | D15: 125 | F15: Jennifer Torres | H15: República C3 | J15: Por verificar
B16: Renta Morelos - Independiente | D16: 150 | F16: José Arcadio | H16: República C4
B17: Evaluación Wisc | D17: 250 | F17: Lucía Sánchez
B18: Certificado de mascotas de apoyo emocional | C18: 2000 | D18: 1900 | F18: Maria Amancio
B19: Equinoterapia | C19: 900 | D19: 900 | F19: María de la Luz
B20: Evaluación Psicoprofesional | F20: Maricela Sena
F21: Marisol Soto
F22: Perla Realme
B23: NUEVOS COSTOS REPÚBLICA | F23: Rosa Gómez
F24: Rosy Macias

Sheet Feb 26
B1: 46054 | L1: =B1+1 -> 46055 | V1: =L1+1 -> 46056 | AF1: =V1+1 -> 46057 | AP1: =AF1+1 -> 46058 | AZ1: =AP1+1 -> 46059 | BJ1: =AZ1+1 -> 46060 | BT1: =BJ1+1 -> 46061 | CD1: =BT1+1 -> 46062 | CN1: =CD1+1 -> 46063 | CX1: =CN1+1 -> 46064 | DH1: =CX1+1 -> 46065 | DR1: =DH1+1 -> 46066 | EB1: =DR1+1 -> 46067 | EL1: =EB1+1 -> 46068 | EV1: =EL1+1 -> 46069 | FF1: =EV1+1 -> 46070 | FP1: =FF1+1 -> 46071 | FZ1: =FP1+1 -> 46072 | GJ1: =FZ1+1 -> 46073 | GT1: =GJ1+1 -> 46074 | HD1: =GT1+1 -> 46075 | HN1: =HD1+1 -> 46076 | HX1: =HN1+1 -> 46077 | IH1: =HX1+1 -> 46078 | IR1: =IH1+1 -> 46079 | JB1: =IR1+1 -> 46080 | JL1: =JB1+1 -> 46081
A2: Hora | B2: Tipo | C2: División | D2: Paciente | E2: Servicio | F2: Terapeuta | G2: Situación | H2: Consultorio | I2: $ / Pase | J2: Tipo pago | K2: Notas | L2: Tipo | M2: División | N2: Paciente | O2: Servicio | P2: Terapeuta | Q2: Situación | R2: Consultorio | S2: $ / Pase | T2: Tipo pago | U2: Notas | V2: Tipo | W2: División | X2: Paciente | Y2: Servicio | Z2: Terapeuta | AA2: Situación | AB2: Consultorio | AC2: $ / Pase | AD2: Tipo pago | AE2: Notas | AF2: Tipo | AG2: División | AH2: Paciente | AI2: Servicio | AJ2: Terapeuta | AK2: Situación | AL2: Consultorio | AM2: $ / Pase | AN2: Tipo pago | AO2: Notas | AP2: Tipo | AQ2: División | AR2: Paciente | AS2: Servicio | AT2: Terapeuta | AU2: Situación | AV2: Consultorio | AW2: $ / Pase | AX2: Tipo pago | AY2: Notas | AZ2: Tipo | BA2: División | BB2: Paciente | BC2: Servicio | BD2: Terapeuta | BE2: Situación | BF2: Consultorio | BG2: $ / Pase | BH2: Tipo pago | BI2: Notas | BJ2: Tipo | BK2: División | BL2: Paciente | BM2: Servicio | BN2: Terapeuta | BO2: Situación | BP2: Consultorio | BQ2: $ / Pase | BR2: Tipo pago | BS2: Notas | BT2: Tipo | BU2: División | BV2: Paciente | BW2: Servicio | BX2: Terapeuta | BY2: Situación | BZ2: Consultorio | CA2: $ / Pase | CB2: Tipo pago | CC2: Notas | CD2: Tipo | CE2: División | CF2: Paciente | CG2: Servicio | CH2: Terapeuta | CI2: Situación | CJ2: Consultorio | CK2: $ / Pase | CL2: Tipo pago | CM2: Notas | CN2: Tipo | CO2: División | CP2: Paciente | CQ2: Servicio | CR2: Terapeuta | CS2: Situación | CT2: Consultorio | CU2: $ / Pase | CV2: Tipo pago | CW2: Notas | CX2: Tipo | CY2: División | CZ2: Paciente | DA2: Servicio | DB2: Terapeuta | DD2: Consultorio | DE2: $ / Pase | DF2: Tipo pago | DG2: Notas | DH2: Tipo | DI2: División | DJ2: Paciente | DK2: Servicio | DL2: Terapeuta | DM2: Situación | DN2: Consultorio | DO2: $ / Pase | DP2: Tipo pago | DQ2: Notas | DR2: Tipo | DS2: División | DT2: Paciente | DU2: Servicio | DV2: Terapeuta | DW2: Situación | DX2: Consultorio | DY2: $ / Pase | DZ2: Tipo pago | EA2: Notas | EB2: Tipo | EC2: División | ED2: Paciente | EE2: Servicio | EF2: Terapeuta | EG2: Situación | EH2: Consultorio | EI2: $ / Pase | EJ2: Tipo pago | EK2: Notas | EL2: Tipo | EM2: División | EN2: Paciente | EO2: Servicio | EP2: Terapeuta | EQ2: Situación | ER2: Consultorio | ES2: $ / Pase | ET2: Tipo pago | EU2: Notas | EV2: Tipo | EW2: División | EX2: Paciente | EY2: Servicio | EZ2: Terapeuta | FA2: Situación | FB2: Consultorio | FC2: $ / Pase | FD2: Tipo pago | FE2: Notas | FF2: Tipo | FG2: División | FH2: Paciente | FI2: Servicio | FJ2: Terapeuta | FK2: Situación | FL2: Consultorio | FM2: $ / Pase | FN2: Tipo pago | FO2: Notas | FP2: Tipo | FQ2: División | FR2: Paciente | FS2: Servicio | FT2: Terapeuta | FU2: Situación | FV2: Consultorio | FW2: $ / Pase | FX2: Tipo pago | FY2: Notas | FZ2: Tipo | GA2: División | GB2: Paciente | GC2: Servicio | GD2: Terapeuta | GE2: Situación | GF2: Consultorio | GG2: $ / Pase | GH2: Tipo pago | GI2: Notas | GJ2: Tipo | GK2: División | GL2: Paciente | GM2: Servicio | GN2: Terapeuta | GO2: Situación | GP2: Consultorio | GQ2: $ / Pase | GR2: Tipo pago | GS2: Notas | GT2: Tipo | GU2: División | GV2: Paciente | GW2: Servicio | GX2: Terapeuta | GY2: Situación | GZ2: Consultorio | HA2: $ / Pase | HB2: Tipo pago | HC2: Notas | HD2: Tipo | HE2: División | HF2: Paciente | HG2: Servicio | HH2: Terapeuta | HI2: Situación | HJ2: Consultorio | HK2: $ / Pase | HL2: Tipo pago | HM2: Notas | HN2: Tipo | HO2: División | HP2: Paciente | HQ2: Servicio | HR2: Terapeuta | HS2: Situación | HT2: Consultorio | HU2: $ / Pase | HV2: Tipo pago | HW2: Notas | HX2: Tipo | HY2: División | HZ2: Paciente | IA2: Servicio | IB2: Terapeuta | IC2: Situación | ID2: Consultorio | IE2: $ / Pase | IF2: Tipo pago | IG2: Notas | IH2: Tipo | II2: División | IJ2: Paciente | IK2: Servicio | IL2: Terapeuta | IM2: Situación | IN2: Consultorio | IO2: $ / Pase | IP2: Tipo pago | IQ2: Notas | IR2: Tipo | IS2: División | IT2: Paciente | IU2: Servicio | IV2: Terapeuta | IW2: Situación | IX2: Consultorio | IY2: $ / Pase | IZ2: Tipo pago | JA2: Notas | JB2: Tipo | JC2: División | JD2: Paciente | JE2: Servicio | JF2: Terapeuta | JG2: Situación | JH2: Consultorio | JI2: $ / Pase | JJ2: Tipo pago | JK2: Notas | JL2: Tipo | JM2: División | JN2: Paciente | JO2: Servicio | JP2: Terapeuta | JQ2: Situación | JR2: Consultorio | JS2: $ / Pase | JT2: Tipo pago | JU2: Notas
A3: 0.375 | N3: BLOQUEADO TODO EL | V3: S | W3: Particular | X3: Daniel Ramírez Cervantes | Y3: Individual | Z3: Maricela Sena | AA3: No llegó | AB3: República C1 | AC3: 420 | DJ3: BLOQUEADO LIC. ARCADIO | ED3: BLOQUEADO LIC. ARCADIO | HN3: S | HO3: Particular | HP3: María Fernanda Rodríguez Daniel | HQ3: Individual | HR3: Javier Martínez | HS3: Confirmó | HT3: República C1 | HU3: 350 | HV3: Efectivo | JN3: BLOQUEADO LIC MARTINEZ 9:00
A4: 0.375 | N4: DÍA LIC LUCÍA SÁNCHEZ
A5: 0.375
A6: 0.375
